Workbook

Sheet PLANT Intake Coding
G1: =SUM(G3:G17059) -> 5255.85 | K1: =SUM(K3:K997) -> 8141.15 | L1: =SUM(L3:L997) -> 666
A2: Date | B2: Source | C2: Genus | D2: Cultivar | E2: ID # | F2: SKU | G2: Total Cost | H2: Location | I2: Status | J2: Unique ID | K2: MSRP | L2: QTY | M2: Pot Type | N2: Unit Cost | O2: Owner Email | P2: Photo
A3: 38202 | B3: Home Stock | C3: Begonia | D3: Angel Wing | E3: 1A | F3: =IFERROR(__xludf.DUMMYFUNCTION("ARRAYFORMULA( IF(ROW(B3:B3059)<3,"""", IF(LEN(B3:B3059)=0,"""", IFERROR( VLOOKUP(UPPER(TRIM(B3:B3059)), {'Plant KEY'!A:A,'Plant KEY'!B:B}, 2, FALSE), LET( n, UPPER(TRIM(B3:B3059)), clean, REGEXREPLACE(n,""[^A-Z]"",""""), "&" base, IF(REGEXMATCH(n,""\s""), LEFT(SUBSTITUTE(REGEXREPLACE(REGEXREPLACE(SUBSTITUTE(n,""-"","" ""),""\b(OF|THE|AND|A|AN)\b"",""""),""(^| )([A-Z])[A-Z]+"","" $2""),"" "",""""),3), LEFT(clean,2) ), keycodes,"&" UPPER('Plant KEY'!F:F), fallback, IF(REGEXMATCH(n,""\s""), LET(lastword,IFERROR(TRIM(MID(n,FIND(""☺"",SUBSTITUTE(n,"" "",""☺"",LEN(n)-LEN(SUBSTITUTE(n,"" "",""""))))+1,100)),n),LEFT(base,2)&MID(lastword,2,1)), LEFT(c"&"lean,3) ), IF(COUNTIF(keycodes,base)=0,base,IF(COUNTIF(keycodes,fallback)=0,fallback,LEFT(clean,4))) ) ) & IF(LEN(C3:C3059), ""-"" & IFERROR( VLOOKUP(UPPER(TRIM(C3:C3059)), {'Plant KEY'!C:C,'Plant KEY'!D:D}, "&"2, FALSE), LET( n, UPPER(TRIM(C3:C3059)), clean, REGEXREPLACE(n,""[^A-Z]"",""""), base, IF(REGEXMATCH(n,""\s""), LEFT(SUBSTITUTE(REGEXREPLACE(REGEXREPLACE(SUBSTITUTE(n,""-"","" ""),""\b(OF|THE|AND|"&"A|AN)\b"",""""),""(^| )([A-Z])[A-Z]+"","" $2""),"" "",""""),3), LEFT(clean,2) ), keycodes, UPPER('Plant KEY'!D:D), fallback, IF(REGEXMATCH(n,""\s""), LET(lastword,IFERROR(TRIM(MID(n,FIND("""&"☺"",SUBSTITUTE(n,"" "",""☺"",LEN(n)-LEN(SUBSTITUTE(n,"" "",""""))))+1,100)),n),LEFT(base,2)&MID(lastword,2,1)), LEFT(clean,3) ), IF(COUNTIF(keycodes,base)=0,base,IF(COUNTIF(keycodes,fallback)=0,fallback,LEFT(clean,4))) "&" ) ), """") & IF(LEN(D3:D3059), ""-"" & IFERROR( VLOOKUP(UPPER(TRIM(D3:D3059)), {'Plant KEY'!E:E,'Plant KEY'!F:F}, 2, FALSE), LET( n, UPPER(TRIM(D3:D3059)), clean, REGEXREPLACE(n,""[^A-Z]"",""""),"&" base, IF(REGEXMATCH(n,""\s""), LEFT(SUBSTITUTE(REGEXREPLACE(REGEXREPLACE(SUBSTITUTE(n,""-"","" ""),""\b(OF|THE|AND|A|AN)\b"",""""),""(^| )([A-Z])[A-Z]+"","" $2""),"" "",""""),3), LEFT(clean,2) ), "&" keycodes, UPPER('Plant KEY'!F:F), fallback, IF(REGEXMATCH(n,""\s""), LET(lastword,IFERROR(TRIM(MID(n,FIND(""☺"",SUBSTITUTE(n,"" "",""☺"",LEN(n)-LEN(SUBSTITUTE(n,"" "",""""))))+1,100)),n),LEFT(base,2)&MID(lastword,2"&",1)), LEFT(clean,3) ), IF(COUNTIF(keycodes,base)=0,base,IF(COUNTIF(keycodes,fallback)=0,fallback,LEFT(clean,4))) ) ), """") & IF(LEN(E3:E3059), ""-"" & UPPER(TRIM(E3:E3059)),"""") ) ) )"),"HS-BE-AW-1A") -> HS-BE-AW-1A | G3: 0 | J3: E87921 | L3: 1 | M3: ST-PO-12-NU-1 | N3: {=IF(LEN(B3:B3059)=0, "", IFERROR(G3:G3059 / L3:L3059, "") )} -> 0 | O3: starr8@rocketmail.com
B4: Home Stock | C4: Pothos | D4: Golden | E4: 1A | F4: =IFERROR(__xludf.DUMMYFUNCTION("""COMPUTED_VALUE"""),"HS-PO-GO-1A") -> HS-PO-GO-1A | G4: 0 | J4: 9C3687 | L4: 1 | N4: 0 | O4: starr8@rocketmail.com
B5: Home Stock | C5: Philodendron | D5: Heart Leaf | E5: 1A | F5: =IFERROR(__xludf.DUMMYFUNCTION("""COMPUTED_VALUE"""),"HS-PH-HL-1A") -> HS-PH-HL-1A | G5: 0 | J5: 851D91 | L5: 1 | M5: ST-PO-0-CU-1 | N5: 0 | O5: starr8@rocketmail.com
B6: Home Stock | C6: Philodendron | D6: Brasil | E6: 1A | F6: =IFERROR(__xludf.DUMMYFUNCTION("""COMPUTED_VALUE"""),"HS-PH-BRL-1A") -> HS-PH-BRL-1A | G6: 0 | J6: FB20D8 | L6: 1 | N6: 0 | O6: starr8@rocketmail.com
B7: Home Stock | C7: Pilea | D7: Peperomioides | E7: 1A | F7: =IFERROR(__xludf.DUMMYFUNCTION("""COMPUTED_VALUE"""),"HS-PI-PEP-1A") -> HS-PI-PEP-1A | G7: 0 | J7: 62867D | L7: 1 | N7: 0 | O7: starr8@rocketmail.com
A8: 45899 | B8: Home Stock | C8: Ctenanthe | D8: Burle Marxii | E8: 1A | F8: =IFERROR(__xludf.DUMMYFUNCTION("""COMPUTED_VALUE"""),"HS-CT-BM-1A") -> HS-CT-BM-1A | G8: 0 | J8: 59D755 | L8: 1 | M8: ST-PO-4-NU-1 | N8: 0 | O8: starr8@rocketmail.com
F9: =IFERROR(__xludf.DUMMYFUNCTION("""COMPUTED_VALUE"""),"")
B10: Home Stock | C10: Dracaena | D10: Snake Plant | E10: 1A | F10: =IFERROR(__xludf.DUMMYFUNCTION("""COMPUTED_VALUE"""),"HS-DR-SP-1A") -> HS-DR-SP-1A | G10: 0 | J10: D10239 | L10: 1 | N10: 0 | O10: starr8@rocketmail.com
A11: 45873 | B11: Facebook Marketplace | C11: Philodendron | D11: White Knight | E11: 1A | F11: =IFERROR(__xludf.DUMMYFUNCTION("""COMPUTED_VALUE"""),"FM-PH-WK-1A") -> FM-PH-WK-1A | G11: 15 | H11: Cash | I11: None | J11: 8F306F | K11: 0 | L11: 1 | M11: ST-PO-6-NU-1 | N11: 15 | O11: starr8@rocketmail.com
A12: 45872 | B12: Walmart | C12: Philodendron | D12: White Knight | E12: 1A | F12: =IFERROR(__xludf.DUMMYFUNCTION("""COMPUTED_VALUE"""),"WM-PH-WK-1A") -> WM-PH-WK-1A | G12: 19.97 | J12: 3A0A52 | L12: 1 | N12: 19.97 | O12: starr8@rocketmail.com
B13: Walmart | C13: Monstera | D13: Peru | E13: 1A | F13: =IFERROR(__xludf.DUMMYFUNCTION("""COMPUTED_VALUE"""),"WM-MA-PE-1A") -> WM-MA-PE-1A | G13: 7 | J13: C7E314 | L13: 1 | N13: 7 | O13: starr8@rocketmail.com
A14: 45873 | B14: The Lady Cove | C14: Philodendron | D14: Cream Splash | E14: 1A | F14: =IFERROR(__xludf.DUMMYFUNCTION("""COMPUTED_VALUE"""),"TLC-PH-CS-1A") -> TLC-PH-CS-1A | G14: 0 | J14: AA4996 | L14: 1 | N14: 0 | O14: starr8@rocketmail.com
A15: 45874 | B15: The Amazing Garden | C15: Adenium Obesum | D15: Desert Rose | E15: 1A | F15: =IFERROR(__xludf.DUMMYFUNCTION("""COMPUTED_VALUE"""),"TAG-AO-DR-1A") -> TAG-AO-DR-1A | G15: 0 | J15: B16039 | L15: 1 | N15: 0 | O15: starr8@rocketmail.com
A16: 45880 | B16: Fred Meyer | C16: Philodendron | D16: Golden Crocodile | E16: 1A | F16: =IFERROR(__xludf.DUMMYFUNCTION("""COMPUTED_VALUE"""),"FMY-PH-GC-1A") -> FMY-PH-GC-1A | G16: 16.99 | J16: 4546BE | L16: 1 | M16: ST-PO-6-NU-1 | N16: 16.99 | O16: starr8@rocketmail.com
A17: 45880 | B17: Fred Meyer | C17: Alocasia | D17: Regal Shield | E17: 1A | F17: =IFERROR(__xludf.DUMMYFUNCTION("""COMPUTED_VALUE"""),"FMY-AL-RSD-1A") -> FMY-AL-RSD-1A | G17: 10.99 | J17: 5DCD93 | L17: 1 | N17: 10.99 | O17: starr8@rocketmail.com
A18: 45880 | B18: Fred Meyer | C18: Alocasia | D18: Green Velvet Frydek | E18: 1A | F18: =IFERROR(__xludf.DUMMYFUNCTION("""COMPUTED_VALUE"""),"FMY-AL-GVF-1A") -> FMY-AL-GVF-1A | G18: 10.99 | J18: 66B4DB | L18: 1 | N18: 10.99 | O18: starr8@rocketmail.com
A19: 45880 | B19: Fred Meyer | C19: Monstera | D19: Deliciosa | E19: 1A | F19: =IFERROR(__xludf.DUMMYFUNCTION("""COMPUTED_VALUE"""),"FMY-MA-DE-1A") -> FMY-MA-DE-1A | G19: 10.99 | J19: D764EE | K19: 25 | L19: 1 | M19: ST-PO-6-NU-1 | N19: 10.99 | O19: starr8@rocketmail.com
A20: 45880 | B20: Fred Meyer | C20: Monstera | D20: Deliciosa | E20: 1A-2 | F20: =IFERROR(__xludf.DUMMYFUNCTION("""COMPUTED_VALUE"""),"FMY-MA-DE-1A-2") -> FMY-MA-DE-1A-2 | G20: 19.99 | J20: BA6B4C | L20: 1 | M20: ST-PO-6-NU-1 | N20: 19.99 | O20: starr8@rocketmail.com
A21: 45880 | B21: The Lady Cove | C21: Scindapsus | D21: Silver Splash | E21: 1A | F21: =IFERROR(__xludf.DUMMYFUNCTION("""COMPUTED_VALUE"""),"TLC-SC-SS-1A") -> TLC-SC-SS-1A | G21: 1 | J21: 1DD88F | L21: 1 | N21: 1 | O21: starr8@rocketmail.com
A22: 45870 | B22: Maggie Mae Plants | C22: Monstera | D22: Adansonii | E22: 1A | F22: =IFERROR(__xludf.DUMMYFUNCTION("""COMPUTED_VALUE"""),"MMP-MA-AD-1A") -> MMP-MA-AD-1A | G22: 1 | J22: D78BB8 | L22: 1 | N22: 1 | O22: starr8@rocketmail.com
A23: 45866 | B23: Orange Lake Nursery | C23: Monstera | D23: Adansonii | E23: 1A | F23: =IFERROR(__xludf.DUMMYFUNCTION("""COMPUTED_VALUE"""),"OLN-MA-AD-1A") -> OLN-MA-AD-1A | G23: 3.66 | H23: Credit Card | I23: 2163 | J23: DB15AC | L23: 1 | M23: ST-PO-0-PL-1 | N23: 3.66 | O23: starr8@rocketmail.com
A24: 45866 | B24: Orange Lake Nursery | C24: Philodendron | D24: White Princess | E24: 1A | F24: =IFERROR(__xludf.DUMMYFUNCTION("""COMPUTED_VALUE"""),"OLN-PH-WP-1A") -> OLN-PH-WP-1A | G24: 3.66 | H24: Credit Card | I24: 2163 | J24: 1A5668 | L24: 1 | M24: ST-PO-0-PL-1 | N24: 3.66 | O24: starr8@rocketmail.com
A25: 45866 | B25: Orange Lake Nursery | C25: Alternanthera | D25: Party Time | E25: 1A | F25: =IFERROR(__xludf.DUMMYFUNCTION("""COMPUTED_VALUE"""),"OLN-ALT-PT-1A") -> OLN-ALT-PT-1A | G25: 9.99 | H25: Credit Card | I25: 2163 | J25: 30FC62 | L25: 1 | M25: ST-PO-0-PL-1 | N25: 9.99 | O25: starr8@rocketmail.com
A26: 45866 | B26: Orange Lake Nursery | C26: Fittonia | D26: Red Flame | E26: 1A | F26: =IFERROR(__xludf.DUMMYFUNCTION("""COMPUTED_VALUE"""),"OLN-FI-RF-1A") -> OLN-FI-RF-1A | G26: 3.66 | H26: Credit Card | I26: 2163 | J26: C4919B | L26: 1 | M26: ST-PO-4-NU-1 | N26: 3.66 | O26: starr8@rocketmail.com
A27: 45902 | B27: Orange Lake Nursery | C27: Philodendron | D27: Strawberry Shake | E27: 1A | F27: =IFERROR(__xludf.DUMMYFUNCTION("""COMPUTED_VALUE"""),"OLN-PH-STS-1A") -> OLN-PH-STS-1A | G27: 52 | H27: Credit Card | I27: 1002 | J27: DD2EF3 | L27: 1 | M27: ST-PO-4-NU-1 | N27: 52 | O27: starr8@rocketmail.com
A28: 45902 | B28: Orange Lake Nursery | C28: Philodendron | D28: Snow Drift | E28: 1A | F28: =IFERROR(__xludf.DUMMYFUNCTION("""COMPUTED_VALUE"""),"OLN-PH-SD-1A") -> OLN-PH-SD-1A | G28: 16 | H28: Credit Card | I28: 1002 | J28: A09A6D | L28: 1 | M28: ST-PO-4-NU-1 | N28: 16 | O28: starr8@rocketmail.com
A29: 45871 | B29: Aura Rooted | C29: Philodendron | D29: White Princess | E29: 1A | F29: =IFERROR(__xludf.DUMMYFUNCTION("""COMPUTED_VALUE"""),"AR-PH-WP-1A") -> AR-PH-WP-1A | G29: 20.4 | J29: F323DF | L29: 1 | N29: 20.4 | O29: starr8@rocketmail.com
A30: 45871 | B30: Aura Rooted | C30: Alocasia | D30: Longiloba Mint | E30: 1A | F30: =IFERROR(__xludf.DUMMYFUNCTION("""COMPUTED_VALUE"""),"AR-AL-LM-1A") -> AR-AL-LM-1A | G30: 18.9 | J30: D4D950 | L30: 1 | N30: 18.9 | O30: starr8@rocketmail.com
A31: 45877 | B31: Zen Botanicals | C31: Senecio | D31: Haworthii | E31: 1A | F31: =IFERROR(__xludf.DUMMYFUNCTION("""COMPUTED_VALUE"""),"ZB-SE-HA-1A") -> ZB-SE-HA-1A | G31: 0 | J31: D8F201 | L31: 1 | N31: 0 | O31: starr8@rocketmail.com
A32: 45878 | B32: It's a Succulent Thang | C32: Philodendron | D32: Pink Princess | E32: 1A | F32: =IFERROR(__xludf.DUMMYFUNCTION("""COMPUTED_VALUE"""),"IST-PH-PP-1A") -> IST-PH-PP-1A | G32: 10.8 | J32: B46EF4 | L32: 1 | N32: 10.8 | O32: starr8@rocketmail.com
A33: 45878 | B33: It's a Succulent Thang | C33: Philodendron | D33: Green Congo Nuclear | E33: 1A | F33: =IFERROR(__xludf.DUMMYFUNCTION("""COMPUTED_VALUE"""),"IST-PH-GCN-1A") -> IST-PH-GCN-1A | G33: 25 | J33: F3374E | L33: 1 | M33: ST-PO-4-NU-1 | N33: 25 | O33: starr8@rocketmail.com
A34: 45882 | B34: Ts Garden Gems | C34: Hoya | D34: Golden Flame | E34: 1A | F34: =IFERROR(__xludf.DUMMYFUNCTION("""COMPUTED_VALUE"""),"TGG-HO-GF-1A") -> TGG-HO-GF-1A | G34: 0 | J34: 1E3D42 | L34: 1 | N34: 0 | O34: starr8@rocketmail.com
A35: 45882 | B35: Ts Garden Gems | C35: Hoya | D35: Publicalyx | E35: 1A | F35: =IFERROR(__xludf.DUMMYFUNCTION("""COMPUTED_VALUE"""),"TGG-HO-PU-1A") -> TGG-HO-PU-1A | G35: 5 | J35: C41DCD | L35: 1 | N35: 5 | O35: starr8@rocketmail.com
A36: 45886 | B36: Facebook Marketplace | C36: Monstera | D36: Deliciosa | E36: 1A | F36: =IFERROR(__xludf.DUMMYFUNCTION("""COMPUTED_VALUE"""),"FM-MA-DE-1A") -> FM-MA-DE-1A | G36: 5 | H36: Cash | I36: None | J36: BC6E95 | K36: 0 | L36: 1 | M36: ST-PO-0-CU-1 | N36: 5 | O36: starr8@rocketmail.com
A37: 45882 | B37: Amazon | C37: Philodendron | D37: Pink Princess | E37: 1A | F37: =IFERROR(__xludf.DUMMYFUNCTION("""COMPUTED_VALUE"""),"AM-PH-PP-1A") -> AM-PH-PP-1A | G37: 10.25 | J37: EABB58 | L37: 1 | N37: 10.25 | O37: starr8@rocketmail.com
A38: 45882 | B38: Amazon | C38: Philodendron | D38: White Wizard | E38: 1A | F38: =IFERROR(__xludf.DUMMYFUNCTION("""COMPUTED_VALUE"""),"AM-PH-WW-1A") -> AM-PH-WW-1A | G38: 10.25 | J38: A7877B | L38: 1 | N38: 10.25 | O38: starr8@rocketmail.com
A39: 45882 | B39: Amazon | C39: Philodendron | D39: Gloriosum | E39: 1A | F39: =IFERROR(__xludf.DUMMYFUNCTION("""COMPUTED_VALUE"""),"AM-PH-GL-1A") -> AM-PH-GL-1A | G39: 10.25 | J39: 367351 | L39: 1 | N39: 10.25 | O39: starr8@rocketmail.com
A40: 45882 | B40: Amazon | C40: Philodendron | D40: Birkin | E40: 1A | F40: =IFERROR(__xludf.DUMMYFUNCTION("""COMPUTED_VALUE"""),"AM-PH-BI-1A") -> AM-PH-BI-1A | G40: 10.25 | J40: EBE164 | L40: 1 | N40: 10.25 | O40: starr8@rocketmail.com
A41: 45881 | B41: The Gay Ole Plant Shop | C41: Philodendron | D41: Pink Princess Marbled | E41: 1A | F41: =IFERROR(__xludf.DUMMYFUNCTION("""COMPUTED_VALUE"""),"TGOPS-PH-PPM-1A") -> TGOPS-PH-PPM-1A | G41: 16.19 | J41: 3EF9AE | K41: 26.99 | L41: 1 | N41: 16.19 | O41: starr8@rocketmail.com
A42: 45881 | B42: The Gay Ole Plant Shop | C42: Philodendron | D42: Pink Princess Marbled | E42: 1A-2 | F42: =IFERROR(__xludf.DUMMYFUNCTION("""COMPUTED_VALUE"""),"TGOPS-PH-PPM-1A-2") -> TGOPS-PH-PPM-1A-2 | G42: 16.19 | J42: 95E24C | K42: 26.99 | L42: 1 | N42: 16.19 | O42: starr8@rocketmail.com
A43: 45881 | B43: The Gay Ole Plant Shop | C43: Philodendron | D43: Pink Princess Marbled | E43: 1A-3 | F43: =IFERROR(__xludf.DUMMYFUNCTION("""COMPUTED_VALUE"""),"TGOPS-PH-PPM-1A-3") -> TGOPS-PH-PPM-1A-3 | G43: 16.19 | J43: D83913 | K43: 26.99 | L43: 1 | N43: 16.19 | O43: starr8@rocketmail.com
A44: 45881 | B44: The Gay Ole Plant Shop | C44: Philodendron | D44: Prince of Orange | E44: 1A | F44: =IFERROR(__xludf.DUMMYFUNCTION("""COMPUTED_VALUE"""),"TGOPS-PH-POO-1A") -> TGOPS-PH-POO-1A | G44: 7.79 | J44: F6DAF1 | K44: 12.99 | L44: 1 | N44: 7.79 | O44: starr8@rocketmail.com
A45: 45881 | B45: The Gay Ole Plant Shop | C45: Philodendron | D45: Prince of Orange | E45: 1A-2 | F45: =IFERROR(__xludf.DUMMYFUNCTION("""COMPUTED_VALUE"""),"TGOPS-PH-POO-1A-2") -> TGOPS-PH-POO-1A-2 | G45: 7.79 | J45: D2855E | K45: 12.99 | L45: 1 | N45: 7.79 | O45: starr8@rocketmail.com
A46: 45881 | B46: The Gay Ole Plant Shop | C46: Philodendron | D46: Prince of Orange | E46: 1A-3 | F46: =IFERROR(__xludf.DUMMYFUNCTION("""COMPUTED_VALUE"""),"TGOPS-PH-POO-1A-3") -> TGOPS-PH-POO-1A-3 | G46: 7.79 | J46: 746666 | K46: 12.99 | L46: 1 | N46: 7.79 | O46: starr8@rocketmail.com
A47: 45881 | B47: The Gay Ole Plant Shop | C47: Philodendron | D47: White Wizard | E47: 1A | F47: =IFERROR(__xludf.DUMMYFUNCTION("""COMPUTED_VALUE"""),"TGOPS-PH-WW-1A") -> TGOPS-PH-WW-1A | G47: 13.19 | J47: FDCDBC | L47: 1 | N47: 13.19 | O47: starr8@rocketmail.com
A48: 45881 | B48: The Gay Ole Plant Shop | C48: Philodendron | D48: White Wizard | E48: 1A-2 | F48: =IFERROR(__xludf.DUMMYFUNCTION("""COMPUTED_VALUE"""),"TGOPS-PH-WW-1A-2") -> TGOPS-PH-WW-1A-2 | G48: 13.19 | J48: B86EBE | L48: 1 | N48: 13.19 | O48: starr8@rocketmail.com
A49: 45881 | B49: The Gay Ole Plant Shop | C49: Philodendron | D49: White Wizard | E49: 1A-3 | F49: =IFERROR(__xludf.DUMMYFUNCTION("""COMPUTED_VALUE"""),"TGOPS-PH-WW-1A-3") -> TGOPS-PH-WW-1A-3 | G49: 13.19 | J49: B248B2 | L49: 1 | N49: 13.19 | O49: starr8@rocketmail.com
A50: 45884 | B50: BWH Plant Company | C50: Philodendron | D50: Moonlight | E50: 1A | F50: =IFERROR(__xludf.DUMMYFUNCTION("""COMPUTED_VALUE"""),"BWH-PH-MO-1A") -> BWH-PH-MO-1A | G50: 6 | J50: 865761 | K50: 12.99 | L50: 1 | N50: 6 | O50: starr8@rocketmail.com
A51: 45884 | B51: BWH Plant Company | C51: Philodendron | D51: Moonlight | E51: 1A-2 | F51: =IFERROR(__xludf.DUMMYFUNCTION("""COMPUTED_VALUE"""),"BWH-PH-MO-1A-2") -> BWH-PH-MO-1A-2 | G51: 6 | J51: 3475AD | K51: 12.99 | L51: 1 | N51: 6 | O51: starr8@rocketmail.com
A52: 45884 | B52: BWH Plant Company | C52: Philodendron | D52: Moonlight | E52: 1A-3 | F52: =IFERROR(__xludf.DUMMYFUNCTION("""COMPUTED_VALUE"""),"BWH-PH-MO-1A-3") -> BWH-PH-MO-1A-3 | G52: 6 | J52: 87BA03 | K52: 12.99 | L52: 1 | N52: 6 | O52: starr8@rocketmail.com
A53: 45884 | B53: BWH Plant Company | C53: Philodendron | D53: Moonlight | E53: 1A-4 | F53: =IFERROR(__xludf.DUMMYFUNCTION("""COMPUTED_VALUE"""),"BWH-PH-MO-1A-4") -> BWH-PH-MO-1A-4 | G53: 6 | J53: 9D266F | K53: 12.99 | L53: 1 | N53: 6 | O53: starr8@rocketmail.com
A54: 45884 | B54: BWH Plant Company | C54: Philodendron | D54: Moonlight | E54: 1A-5 | F54: =IFERROR(__xludf.DUMMYFUNCTION("""COMPUTED_VALUE"""),"BWH-PH-MO-1A-5") -> BWH-PH-MO-1A-5 | G54: 6 | J54: 11DB77 | K54: 12.99 | L54: 1 | N54: 6 | O54: starr8@rocketmail.com
A55: 45884 | B55: BWH Plant Company | C55: Philodendron | D55: Red Anderson Pink Knight | E55: 1A | F55: =IFERROR(__xludf.DUMMYFUNCTION("""COMPUTED_VALUE"""),"BWH-PH-RAPK-1A") -> BWH-PH-RAPK-1A | G55: 10.2 | I55: 1002 | J55: DA2B69 | K55: 24.99 | L55: 1 | N55: 10.2 | O55: starr8@rocketmail.com
A56: 45884 | B56: BWH Plant Company | C56: Philodendron | D56: Red Anderson Pink Knight | E56: 1A-2 | F56: =IFERROR(__xludf.DUMMYFUNCTION("""COMPUTED_VALUE"""),"BWH-PH-RAPK-1A-2") -> BWH-PH-RAPK-1A-2 | G56: 10.2 | I56: 1002 | J56: DD7D9F | K56: 24.99 | L56: 1 | N56: 10.2 | O56: starr8@rocketmail.com
A57: 45884 | B57: BWH Plant Company | C57: Philodendron | D57: Red Anderson Pink Knight | E57: 1A-3 | F57: =IFERROR(__xludf.DUMMYFUNCTION("""COMPUTED_VALUE"""),"BWH-PH-RAPK-1A-3") -> BWH-PH-RAPK-1A-3 | G57: 10.2 | I57: 1002 | J57: 28945C | K57: 24.99 | L57: 1 | N57: 10.2 | O57: starr8@rocketmail.com
A58: 45884 | B58: BWH Plant Company | C58: Philodendron | D58: Red Anderson Pink Knight | E58: 1A-4 | F58: =IFERROR(__xludf.DUMMYFUNCTION("""COMPUTED_VALUE"""),"BWH-PH-RAPK-1A-4") -> BWH-PH-RAPK-1A-4 | G58: 10.2 | I58: 1002 | J58: 29B762 | K58: 24.99 | L58: 1 | N58: 10.2 | O58: starr8@rocketmail.com
A59: 45884 | B59: BWH Plant Company | C59: Philodendron | D59: Red Anderson Pink Knight | E59: 1A-5 | F59: =IFERROR(__xludf.DUMMYFUNCTION("""COMPUTED_VALUE"""),"BWH-PH-RAPK-1A-5") -> BWH-PH-RAPK-1A-5 | G59: 10.2 | I59: 1002 | J59: B756B2 | K59: 24.99 | L59: 1 | N59: 10.2 | O59: starr8@rocketmail.com
A60: 45884 | B60: BWH Plant Company | C60: Pothos | D60: Pearls and Jade | E60: 1A | F60: =IFERROR(__xludf.DUMMYFUNCTION("""COMPUTED_VALUE"""),"BWH-PO-PAJ-1A") -> BWH-PO-PAJ-1A | G60: 7.8 | J60: 347F1B | K60: 16.99 | L60: 1 | N60: 7.8 | O60: starr8@rocketmail.com
A61: 45884 | B61: BWH Plant Company | C61: Pothos | D61: Pearls and Jade | E61: 1A-2 | F61: =IFERROR(__xludf.DUMMYFUNCTION("""COMPUTED_VALUE"""),"BWH-PO-PAJ-1A-2") -> BWH-PO-PAJ-1A-2 | G61: 7.8 | J61: C770F5 | K61: 16.99 | L61: 1 | N61: 7.8 | O61: starr8@rocketmail.com
A62: 45884 | B62: BWH Plant Company | C62: Pothos | D62: Pearls and Jade | E62: 1A-3 | F62: =IFERROR(__xludf.DUMMYFUNCTION("""COMPUTED_VALUE"""),"BWH-PO-PAJ-1A-3") -> BWH-PO-PAJ-1A-3 | G62: 7.8 | J62: F0D337 | K62: 16.99 | L62: 1 | N62: 7.8 | O62: starr8@rocketmail.com
A63: 45884 | B63: BWH Plant Company | C63: Pothos | D63: Pearls and Jade | E63: 1A-4 | F63: =IFERROR(__xludf.DUMMYFUNCTION("""COMPUTED_VALUE"""),"BWH-PO-PAJ-1A-4") -> BWH-PO-PAJ-1A-4 | G63: 7.8 | J63: E5EA44 | K63: 16.99 | L63: 1 | N63: 7.8 | O63: starr8@rocketmail.com
A64: 45884 | B64: BWH Plant Company | C64: Pothos | D64: Pearls and Jade | E64: 1A-5 | F64: =IFERROR(__xludf.DUMMYFUNCTION("""COMPUTED_VALUE"""),"BWH-PO-PAJ-1A-5") -> BWH-PO-PAJ-1A-5 | G64: 7.8 | J64: DAE397 | K64: 16.99 | L64: 1 | N64: 7.8 | O64: starr8@rocketmail.com
A65: 45884 | B65: BWH Plant Company | C65: Syngonium | D65: Pink Splash | E65: 1A | F65: =IFERROR(__xludf.DUMMYFUNCTION("""COMPUTED_VALUE"""),"BWH-SYN-PS-1A") -> BWH-SYN-PS-1A | G65: 9 | J65: DAB222 | K65: 19.99 | L65: 1 | N65: 9 | O65: starr8@rocketmail.com
A66: 45884 | B66: BWH Plant Company | C66: Syngonium | D66: Pink Splash | E66: 1A-2 | F66: =IFERROR(__xludf.DUMMYFUNCTION("""COMPUTED_VALUE"""),"BWH-SYN-PS-1A-2") -> BWH-SYN-PS-1A-2 | G66: 9 | J66: C20928 | K66: 19.99 | L66: 1 | N66: 9 | O66: starr8@rocketmail.com
A67: 45884 | B67: BWH Plant Company | C67: Syngonium | D67: Pink Splash | E67: 1A-3 | F67: =IFERROR(__xludf.DUMMYFUNCTION("""COMPUTED_VALUE"""),"BWH-SYN-PS-1A-3") -> BWH-SYN-PS-1A-3 | G67: 9 | J67: 3D8402 | K67: 19.99 | L67: 1 | N67: 9 | O67: starr8@rocketmail.com
A68: 45884 | B68: BWH Plant Company | C68: Syngonium | D68: Pink Splash | E68: 1A-4 | F68: =IFERROR(__xludf.DUMMYFUNCTION("""COMPUTED_VALUE"""),"BWH-SYN-PS-1A-4") -> BWH-SYN-PS-1A-4 | G68: 9 | J68: 5A338D | K68: 19.99 | L68: 1 | N68: 9 | O68: starr8@rocketmail.com
A69: 45884 | B69: BWH Plant Company | C69: Syngonium | D69: Pink Splash | E69: 1A-5 | F69: =IFERROR(__xludf.DUMMYFUNCTION("""COMPUTED_VALUE"""),"BWH-SYN-PS-1A-5") -> BWH-SYN-PS-1A-5 | G69: 9 | J69: 1566D4 | K69: 19.99 | L69: 1 | N69: 9 | O69: starr8@rocketmail.com
A70: 45885 | B70: Fontanimal Plant House | C70: Philodendron | D70: Green Congo Nuclear | E70: 1A | F70: =IFERROR(__xludf.DUMMYFUNCTION("""COMPUTED_VALUE"""),"FPH-PH-GCN-1A") -> FPH-PH-GCN-1A | G70: 40 | J70: 41FAF6 | L70: 1 | M70: ST-PO-4-NU-1 | N70: 40 | O70: starr8@rocketmail.com
A71: 45885 | B71: Brandon The Plant Guy | C71: Hoya | D71: Krimson Princess | E71: 1A | F71: =IFERROR(__xludf.DUMMYFUNCTION("""COMPUTED_VALUE"""),"BTPG-HO-KP-1A") -> BTPG-HO-KP-1A | G71: 36.5 | J71: 5FC77C | L71: 1 | M71: ST-PO-6-HA-1 | N71: 36.5 | O71: starr8@rocketmail.com
A72: 45902 | B72: Best Plant Friend | C72: Ceropegia | D72: String of Hearts | E72: 1A | F72: =IFERROR(__xludf.DUMMYFUNCTION("""COMPUTED_VALUE"""),"BPF-CE-SOH-1A") -> BPF-CE-SOH-1A | G72: 5.84 | J72: 8EB23B | K72: 8.99 | L72: 1 | N72: 5.84 | O72: starr8@rocketmail.com
A73: 45902 | B73: Best Plant Friend | C73: Ceropegia | D73: String of Hearts | E73: 1A-2 | F73: =IFERROR(__xludf.DUMMYFUNCTION("""COMPUTED_VALUE"""),"BPF-CE-SOH-1A-2") -> BPF-CE-SOH-1A-2 | G73: 5.84 | J73: 4EE16A | K73: 8.99 | L73: 1 | N73: 5.84 | O73: starr8@rocketmail.com
A74: 45902 | B74: Best Plant Friend | C74: Ceropegia | D74: String of Hearts | E74: 1A-3 | F74: =IFERROR(__xludf.DUMMYFUNCTION("""COMPUTED_VALUE"""),"BPF-CE-SOH-1A-3") -> BPF-CE-SOH-1A-3 | G74: 5.84 | J74: 676712 | K74: 8.99 | L74: 1 | N74: 5.84 | O74: starr8@rocketmail.com
A75: 45902 | B75: Best Plant Friend | C75: Ceropegia | D75: String of Hearts | E75: 1A-4 | F75: =IFERROR(__xludf.DUMMYFUNCTION("""COMPUTED_VALUE"""),"BPF-CE-SOH-1A-4") -> BPF-CE-SOH-1A-4 | G75: 5.84 | J75: EB46AC | K75: 8.99 | L75: 1 | N75: 5.84 | O75: starr8@rocketmail.com
A76: 45902 | B76: Best Plant Friend | C76: Ceropegia | D76: String of Hearts | E76: 1A-5 | F76: =IFERROR(__xludf.DUMMYFUNCTION("""COMPUTED_VALUE"""),"BPF-CE-SOH-1A-5") -> BPF-CE-SOH-1A-5 | G76: 5.84 | J76: 4D2FA7 | K76: 8.99 | L76: 1 | N76: 5.84 | O76: starr8@rocketmail.com
A77: 45902 | B77: Best Plant Friend | C77: Senecio | D77: String of Pearls | E77: 1A | F77: =IFERROR(__xludf.DUMMYFUNCTION("""COMPUTED_VALUE"""),"BPF-SE-SOP-1A") -> BPF-SE-SOP-1A | G77: 4.71 | J77: 7EBCBB | K77: 7.25 | L77: 1 | N77: 4.71 | O77: starr8@rocketmail.com
A78: 45902 | B78: Best Plant Friend | C78: Senecio | D78: String of Pearls | E78: 1A-2 | F78: =IFERROR(__xludf.DUMMYFUNCTION("""COMPUTED_VALUE"""),"BPF-SE-SOP-1A-2") -> BPF-SE-SOP-1A-2 | G78: 4.71 | J78: 48B232 | K78: 7.25 | L78: 1 | N78: 4.71 | O78: starr8@rocketmail.com
A79: 45902 | B79: Best Plant Friend | C79: Senecio | D79: String of Pearls | E79: 1A-3 | F79: =IFERROR(__xludf.DUMMYFUNCTION("""COMPUTED_VALUE"""),"BPF-SE-SOP-1A-3") -> BPF-SE-SOP-1A-3 | G79: 4.71 | J79: 6DE8C5 | K79: 7.25 | L79: 1 | N79: 4.71 | O79: starr8@rocketmail.com
A80: 45902 | B80: Best Plant Friend | C80: Senecio | D80: String of Pearls | E80: 1A-4 | F80: =IFERROR(__xludf.DUMMYFUNCTION("""COMPUTED_VALUE"""),"BPF-SE-SOP-1A-4") -> BPF-SE-SOP-1A-4 | G80: 4.71 | J80: E07801 | K80: 7.25 | L80: 1 | N80: 4.71 | O80: starr8@rocketmail.com
A81: 45902 | B81: Best Plant Friend | C81: Senecio | D81: String of Pearls | E81: 1A-5 | F81: =IFERROR(__xludf.DUMMYFUNCTION("""COMPUTED_VALUE"""),"BPF-SE-SOP-1A-5") -> BPF-SE-SOP-1A-5 | G81: 4.71 | J81: 5EC9AE | K81: 7.25 | L81: 1 | N81: 4.71 | O81: starr8@rocketmail.com
A82: 45902 | B82: Best Plant Friend | C82: Pothos | D82: Neon | E82: 1A | F82: =IFERROR(__xludf.DUMMYFUNCTION("""COMPUTED_VALUE"""),"BPF-PO-NE-1A") -> BPF-PO-NE-1A | G82: 13 | J82: 2B1649 | K82: 20 | L82: 1 | N82: 13 | O82: starr8@rocketmail.com
A83: 45902 | B83: Best Plant Friend | C83: Pothos | D83: Neon | E83: 1A-2 | F83: =IFERROR(__xludf.DUMMYFUNCTION("""COMPUTED_VALUE"""),"BPF-PO-NE-1A-2") -> BPF-PO-NE-1A-2 | G83: 13 | J83: 69DB07 | K83: 20 | L83: 1 | N83: 13 | O83: starr8@rocketmail.com
A84: 45900 | B84: Facebook Marketplace | C84: Philodendron | D84: Pink Princess | E84: 1A | F84: =IFERROR(__xludf.DUMMYFUNCTION("""COMPUTED_VALUE"""),"FM-PH-PP-1A") -> FM-PH-PP-1A | G84: 0 | H84: None | I84: None | J84: 24FF6A | K84: 0 | L84: 1 | M84: ST-PO-0-CU-1 | N84: 0 | O84: starr8@rocketmail.com
A85: 45903 | B85: Facebook Marketplace | C85: Philodendron | D85: Burle Marx Variegated | E85: 1A | F85: =IFERROR(__xludf.DUMMYFUNCTION("""COMPUTED_VALUE"""),"FM-PH-BMV-1A") -> FM-PH-BMV-1A | G85: 7.5 | H85: Cash | I85: None | J85: 5ECF2F | K85: 0 | L85: 1 | M85: ST-PO-0-CU-1 | N85: 7.5 | O85: starr8@rocketmail.com
A86: 45904 | B86: Facebook Marketplace | C86: Philodendron | D86: Burle Marx Variegated | E86: 1A-2 | F86: =IFERROR(__xludf.DUMMYFUNCTION("""COMPUTED_VALUE"""),"FM-PH-BMV-1A-2") -> FM-PH-BMV-1A-2 | G86: 15 | H86: Cash | I86: None | J86: B923BF | K86: 0 | L86: 1 | M86: ST-PO-6-NU-1 | N86: 15 | O86: starr8@rocketmail.com
A87: 45903 | B87: Facebook Marketplace | C87: Syngonium | D87: Batik | E87: 1A | F87: =IFERROR(__xludf.DUMMYFUNCTION("""COMPUTED_VALUE"""),"FM-SYN-BA-1A") -> FM-SYN-BA-1A | G87: 7.5 | H87: Cash | I87: None | J87: E1B355 | K87: 0 | L87: 1 | M87: ST-PO-0-CU-1 | N87: 7.5 | O87: starr8@rocketmail.com
A88: 45886 | B88: Fred Meyer | C88: Alocasia | D88: Regal Shield | E88: 1A-2 | F88: =IFERROR(__xludf.DUMMYFUNCTION("""COMPUTED_VALUE"""),"FMY-AL-RSD-1A-2") -> FMY-AL-RSD-1A-2 | G88: 10.99 | J88: EA64D3 | L88: 1 | N88: 10.99 | O88: starr8@rocketmail.com
A89: 45886 | B89: Fred Meyer | C89: Monstera | D89: Peru | E89: 1A | F89: =IFERROR(__xludf.DUMMYFUNCTION("""COMPUTED_VALUE"""),"FMY-MA-PE-1A") -> FMY-MA-PE-1A | G89: 16.99 | J89: 856273 | L89: 1 | N89: 16.99 | O89: starr8@rocketmail.com
A90: 45886 | B90: Fred Meyer | C90: Aglaonema | D90: Spathonema | E90: 1A | F90: =IFERROR(__xludf.DUMMYFUNCTION("""COMPUTED_VALUE"""),"FMY-AG-SPA-1A") -> FMY-AG-SPA-1A | G90: 19.99 | J90: BAFDC6 | L90: 1 | N90: 19.99 | O90: starr8@rocketmail.com
A91: 45886 | B91: Fred Meyer | C91: Calathea | D91: Makoyana | E91: 1A | F91: =IFERROR(__xludf.DUMMYFUNCTION("""COMPUTED_VALUE"""),"FMY-CA-MA-1A") -> FMY-CA-MA-1A | G91: 19.99 | J91: C98895 | K91: 16.99 | L91: 1 | N91: 19.99 | O91: starr8@rocketmail.com
A92: 45886 | B92: Fred Meyer | C92: Monstera | D92: Deliciosa | E92: 1A-3 | F92: =IFERROR(__xludf.DUMMYFUNCTION("""COMPUTED_VALUE"""),"FMY-MA-DE-1A-3") -> FMY-MA-DE-1A-3 | G92: 19.99 | J92: A6E2FF | L92: 1 | N92: 19.99 | O92: starr8@rocketmail.com
A93: 45886 | B93: Fred Meyer | C93: Monstera | D93: Deliciosa | E93: 1A-4 | F93: =IFERROR(__xludf.DUMMYFUNCTION("""COMPUTED_VALUE"""),"FMY-MA-DE-1A-4") -> FMY-MA-DE-1A-4 | G93: 10.99 | J93: 57F95F | L93: 1 | N93: 10.99 | O93: starr8@rocketmail.com
A94: 45886 | B94: Fred Meyer | C94: Monstera | D94: Deliciosa | E94: 1A-5 | F94: =IFERROR(__xludf.DUMMYFUNCTION("""COMPUTED_VALUE"""),"FMY-MA-DE-1A-5") -> FMY-MA-DE-1A-5 | G94: 10.99 | J94: 5AF6AE | L94: 1 | N94: 10.99 | O94: starr8@rocketmail.com
A95: 45886 | B95: Fred Meyer | C95: Philodendron | D95: Painted Lady | E95: 1A | F95: =IFERROR(__xludf.DUMMYFUNCTION("""COMPUTED_VALUE"""),"FMY-PH-PL-1A") -> FMY-PH-PL-1A | G95: 19.99 | J95: 6B60A0 | K95: 40 | L95: 1 | M95: ST-PO-6-NU-1 | N95: 19.99 | O95: starr8@rocketmail.com
A96: 45886 | B96: Home Depot | C96: Alocasia | D96: Longiloba | E96: 1A | F96: =IFERROR(__xludf.DUMMYFUNCTION("""COMPUTED_VALUE"""),"HD-AL-LO-1A") -> HD-AL-LO-1A | G96: 29.98 | J96: 90C267 | L96: 1 | N96: 29.98 | O96: starr8@rocketmail.com
A97: 45886 | B97: Home Depot | C97: Alocasia | D97: Longiloba | E97: 1A-2 | F97: =IFERROR(__xludf.DUMMYFUNCTION("""COMPUTED_VALUE"""),"HD-AL-LO-1A-2") -> HD-AL-LO-1A-2 | G97: 29.98 | J97: F2B4F5 | L97: 1 | N97: 29.98 | O97: starr8@rocketmail.com
A98: 45886 | B98: Home Depot | C98: Alocasia | D98: Green Velvet Frydek | E98: 1A-2 | F98: =IFERROR(__xludf.DUMMYFUNCTION("""COMPUTED_VALUE"""),"HD-AL-GVF-1A-2") -> HD-AL-GVF-1A-2 | G98: 29.98 | J98: DCED1B | L98: 1 | N98: 29.98 | O98: starr8@rocketmail.com
A99: 45886 | B99: Home Depot | C99: Alocasia | D99: Bisma Dragon Scale | E99: 1A | F99: =IFERROR(__xludf.DUMMYFUNCTION("""COMPUTED_VALUE"""),"HD-AL-BDS-1A") -> HD-AL-BDS-1A | G99: 19.98 | J99: 956FA2 | L99: 1 | M99: ST-PO-6-NU-1 | N99: 19.98 | O99: starr8@rocketmail.com
A100: 45886 | B100: Home Depot | C100: Philodendron | D100: Golden Girl | E100: 1A | F100: =IFERROR(__xludf.DUMMYFUNCTION("""COMPUTED_VALUE"""),"HD-PH-GG-1A") -> HD-PH-GG-1A | G100: 19.98 | J100: FD5AF1 | L100: 1 | N100: 19.98 | O100: starr8@rocketmail.com
...

Sheet Repotting Estimates
A1: Date | B1: Customer Name | C1: Customer Contact | D1: Hourly Wage | E1: Est. Labor Hours | F1: Est. Labor Charge | G1: Est. Materials Charge | H1: Est. Total | I1: Notes | J1: U ID | K1: User Email
A2: 46140 | B2: Caroline Seitz | D2: 30 | E2: 0.5 | F2: 15 | G2: 6.41 | H2: 21.41 | J2: d52bf719 | K2: starr8@rocketmail.com

Sheet Repotting Estimate Line Items
A1: Date | B1: Plant Description | C1: Action | D1: Pot Used | E1: Soil Mix | F1: Pot Charge | G1: Soil Charge | H1: Total Charge | I1: Notes | J1: Estimate ID | K1: U ID
A2: 46140 | B2: Angel Wing Begonia | C2: Transplant | D2: MA-PO-4-SW-1 | E2: BS-SO-FRM-2 | F2: 5 | G2: 1.41 | H2: 6.41 | J2: d52bf719 | K2: 6dd87619

Sheet Repotting Jobs
A1: Date | B1: Customer Name | C1: Customer Contact | D1: Hourly Wage | E1: Labor Hours | F1: Labor Charge | G1: Materials Charge | H1: Total Job Charge | I1: Other Item Total | J1: Total Paid | K1: Grand Total | L1: Status | M1: Notes | N1: U ID | O1: User Email
A2: 46136 | B2: Jennifer Rockwell | C2: Facebook | D2: 25 | E2: 2.83 | F2: 70.75 | G2: 52.08 | H2: 122.83 | I2: 49 | J2: 171.83 | K2: 171.83 | L2: Complete | N2: 293FF1 | O2: starr8@rocketmail.com
A3: 46140 | B3: Caroline Seitz | C3: Facebook | D3: 30 | F3: 0 | G3: 0 | H3: 0 | K3: 0 | N3: 4f803159 | O3: starr8@rocketmail.com
A4: 46156 | B4: Kloey Downs | C4: 541-295-5854 | D4: 30 | E4: 0.5 | F4: 15 | G4: 5.16 | H4: 20.16 | K4: 20.16 | N4: 24878c7e | O4: starr8@rocketmail.com

Sheet Repotting Jobs Cost
A1: Date | B1: Customer Name | C1: Customer Contact | D1: Hourly Wage | E1: Labor Hours | F1: Labor Cost | G1: Materials Cost | H1: Total Job Cost | I1: Status | J1: Total Paid | K1: Grand Total | L1: Profit | M1: Margin | N1: Notes | O1: U ID | P1: User Email | Q1: Job ID
A2: 45771 | B2: Jennifer Rockwell | C2: Facebook | D2: 25 | E2: 2.83 | F2: 70.75 | G2: 16.72 | H2: 87.47 | I2: Complete | J2: 171.83 | K2: 171.83 | L2: 84.36 | M2: 49.1 | O2: 293FF1 | P2: starr8@rocketmail.com | Q2: 293FF1

Sheet Kristina Overhead
A1: Date | B1: Vendor | C1: Brand | D1: Category | E1: Description | F1: Qty | G1: Sub Tot | H1: Ship. | I1: Disc. | J1: Un. Cost | K1: Act. Tot | L1: Pmt. M. | M1: Card # | N1: Invoice # | O1: Notes / Project | P1: U ID | Q1: Owner Email | R1: Receipt
A2: 46099 | B2: Mazda Of Olympia | C2: Subaru Forrester Wilderness | D2: Company Vehicle | E2: Company Vehicle | F2: 1 | G2: 18759 | I2: 0 | J2: 18759 | K2: 18759 | L2: Debit Card | M2: 4269 | P2: a4407819 | Q2: peakprecisionflooring@gmail.com
A3: 46102 | B3: Lumber Liquidators | C3: Coreluxe Flooring | D3: Floor Install | E3: Bedroom, hallway | F3: 14 | G3: 761.74 | I3: 0 | J3: 54.41 | K3: 761.74 | L3: Debit Card | M3: 4269 | N3: 43545 | O3: Home project | P3: 2fdbb9bf | Q3: peakprecisionflooring@gmail.com | R3: Blooming Starr Receipts/2fdbb9bf.Receipt.164010.jpg
A4: 46090 | B4: State Of Washington | C4: Peak precision flooring llc | D4: Licenses & Fees | E4: Liscencing | F4: 1 | G4: 108.11 | I4: 0 | J4: 108.11 | K4: 108.11 | L4: Debit Card | M4: 4269 | P4: 4031dfc4 | Q4: peakprecisionflooring@gmail.com

Sheet Repotting Line Items
A1: Date | B1: Plant Description | C1: Action | D1: Pot Used | E1: Soil Mix | F1: Pot Charge | G1: Soil Charge | H1: Total Charge | I1: Notes | J1: Job ID | K1: U ID
A2: 46136 | B2: Cactus | C2: Transplant | D2: LO-PO-3.7-CD-1 | E2: BS-SO-CA-1 | F2: 10 | G2: 1.31 | H2: 11.31 | J2: 293FF1 | K2: fdd322d0
A3: 46136 | B3: Snake Plant Rooted Cutting | C3: Plant | D3: TO-PO-4-MU-1 | E3: BS-SO-CA-1 | F3: 5 | G3: 1.41 | H3: 6.41 | I3: Purple Pot | J3: 293FF1 | K3: 49d69e7f
A4: 46136 | B4: Spider Plant | C4: Transplant | D4: ST-PO-6-COP-1 | E4: BS-SO-FRM-2 | F4: 0 | G4: 5.16 | H4: 5.16 | J4: 293FF1 | K4: 0ca7eb0f
A5: 46136 | B5: Syngonium 1 | C5: Tran/Div | D5: NR-PO-5-BP-1 | E5: BS-SO-ACM-5 | F5: 12 | G5: 4.22 | H5: 16.22 | J5: 293FF1 | K5: 5524d4b4
A6: 46136 | B6: Syngonium 2 | C6: Tran/Div | D6: MU-PO-4-WH-1 | E6: BS-SO-ACM-5 | F6: 5 | G6: 1.41 | H6: 6.41 | I6: White Pot | J6: 293FF1 | K6: 20873e5f
A7: 46136 | B7: Aloe Vera | C7: Transplant | D7: ST-PO-4-COP-1 | E7: BS-SO-CA-1 | F7: 0 | G7: 1.41 | H7: 1.41 | J7: 293FF1 | K7: 7b816b8a
A8: 46136 | B8: Snake Plant | C8: Transplant | D8: ST-PO-6-COP-1 | E8: BS-SO-CA-1 | F8: 0 | G8: 5.16 | H8: 5.16 | J8: 293FF1 | K8: 3afb867f
A9: 46156 | B9: Pothos | C9: Transplant | D9: ST-PO-6-NU-1 | E9: BS-SO-ACM-7 | F9: 0 | G9: 5.16 | H9: 5.16 | J9: 24878c7e | K9: 97adb881

Sheet Plant KEY
A1: Sources | B1: Code | C1: Genus | D1: Code | E1: Cultivars | F1: Code | G1: Card Number | H1: ID # | I1: Payment Method
A2: Arcadia Garden Products | B2: AGP | C2: Acer | D2: AC | E2: Adansonii | F2: AD | G2: 0590 | H2: 1A | I2: ACH
A3: Amazon | B3: AM | C3: Adenium Obesum | D3: AO | E3: Angel Wing | F3: AW | G3: 1002 | H3: 1A-2 | I3: Credit Card
A4: Facebook Marketplace | B4: FM | C4: Blechnum | D4: BL | E4: Beauty Star | F4: BS | G4: 3150 | H4: 1A-7 | I4: Cash
A5: Brandon The Plant Guy | B5: BTPG | C5: Alternanthera | D5: ALT | E5: Birkin | F5: BI | G5: 5770 | H5: 1A-4 | I5: Cash App
A6: Best Plant Friend | B6: BPF | C6: Alocasia | D6: AL | E6: Bisma Dragon Scale | F6: BDS | G6: 6116 | H6: 1A-3 | I6: Other
A7: Aura Rooted | B7: AR | C7: Aglaonema | D7: AG | E7: Black Cardinal | F7: BC | G7: 9565 | H7: 1A-6 | I7: PayPal
A8: Dicks Sticks & Exotics | B8: DSE | C8: Begonia | D8: BE | E8: Brasil | F8: BRL | G8: UI | I8: Square
A9: Ed Hume | B9: EH | C9: Chamaedorea | D9: CHA | E9: Burle Marx Variegated | F9: BMV | G9: 6921 | H9: 1A-5 | I9: Venmo
A10: My Plants LLC | B10: MPL | C10: Asplenium | D10: ASP | E10: Burle Marxii | F10: BM | H10: 1A-8 | I10: Zelle
A11: The Rooted Plant Shop | B11: RPS | C11: Aeschynanthus | D11: AE | E11: Carnosa | F11: CA | H11: 1A-9 | I11: Promotional Credit
A12: Succulents and Such | B12: SS | C12: Allium | D12: ALL | E12: Common Lilac | F12: CL | I12: Gift Certificate
A13: Tactiko | B13: TA | C13: Aloe | D13: ALO | E13: Cream Splash | F13: CS | H13: 1A-10 | I13: Debit Card
A14: The Green Escape | B14: TGE | C14: Anthurium | D14: AN | E14: Crocatum | F14: CR | H14: 1A-11 | I14: Unpaid Invoice
A15: Home Stock | B15: HS | C15: Cymbopogon | D15: CY | E15: Deliciosa | F15: DE
A16: Fred Meyer | B16: FMY | C16: Farfuglum | D16: FA | E16: Desert Rose | F16: DR | H16: 1A-12
A17: It's a Succulent Thang | B17: IST | C17: Neanthe | D17: NE | E17: Diamond | F17: DI | H17: 1A-13
A18: Jumanji Jon Plants | B18: JJP | C18: Ocimum | D18: OC | E18: Domesticum | F18: DO | H18: 1A-14
A19: Land Of Alice | B19: LOA | C19: Origanum | D19: OR | E19: Dottie | F19: DOT | H19: 1A-15
A20: Micro Cultivate | B20: MI | C20: Pinguicula | D20: PIN | E20: Elegans | F20: EL | H20: 1B
A21: Maggie Mae Plants | B21: MMP | C21: Rhaphidophora | D21: RH | E21: Florida Bronze | F21: FB | H21: 1C
A22: Orange Lake Nursery | B22: OLN | C22: Salvia | D22: SAL | E22: Fusion White | F22: FW | H22: 1H
A23: The Green Escape | B23: TGE | C23: Thymus | D23: TH | E23: Gloriosum | F23: GL
A24: Palm Street | B24: PS | C24: Tomato | D24: TO | E24: Golden | F24: GO | H24: 1D
A25: Rooted Summerville | B25: RSV | C25: Fittonia | D25: FI | E25: Golden Crocodile | F25: GC | H25: 1E
A26: The Amazing Garden | B26: TAG | C26: Hoya | D26: HO | E26: Golden Flame | F26: GF | H26: 1F
A27: Thorsen's Greenhouse | B27: TG | C27: Hurricane | D27: HU | E27: Golden Girl | F27: GG | H27: 1G
A28: The Gay Ole Plant Shop | B28: TGOPS | C28: Hydrangea | D28: HY | E28: Gollum Jade | F28: GJ | H28: 1I
A29: Totally Rooted LLC | B29: TRL | C29: Maranta | D29: MAR | E29: Green Congo Nuclear | F29: GCN | H29: 1J
A30: TikTok | B30: TT | C30: Monstera | D30: MA | E30: Green Velvet Frydek | F30: GVF | H30: 1K
A31: Zen Botanicals | B31: ZB | C31: Philodendron | D31: PH | E31: Haworthii | F31: HA
A32: Walmart | B32: WM | C32: Pilea | D32: PI | E32: Heart Leaf | F32: HL | H32: 1M
A33: The Lady Cove | B33: TLC | C33: Philodendron Hederaceum | D33: PHH | E33: Japanese Maple | F33: JM | H33: 1L
A34: Ts Garden Gems | B34: TGG | C34: Piper | D34: PIP | E34: Jose Buono | F34: JB | H34: 1N
A35: BWH Plant Company | B35: BWH | C35: Pothos | D35: PO | E35: Krimson Princess | F35: KP | H35: 1O
A36: Fontanimal Plant House | B36: FPH | C36: Scindapsus | D36: SC | E36: Lacecap | F36: LC | H36: 1P
A37: Home Depot | B37: HD | C37: Sensation Aurea | D37: SA | E37: Leuconeura Lemon | F37: LL | H37: 1R
A38: Dell Road | B38: DR | C38: Senecio | D38: SE | E38: Longiloba | F38: LO | H38: 1Q
C39: Stromanthe | D39: ST | E39: Longiloba Mint | F39: LM
C40: Syngonium | D40: SYN | E40: Makoyana | F40: MA | H40: 1S
C41: Unknown | D41: UNK | E41: Mandalay | F41: MAN | H41: 1T
C42: Syringa | D42: SY | E42: McColley's Finale | F42: MF | H42: 2B
C43: Spathiphyllum | D43: SP | E43: Mint Batik | F43: MB | H43: 2B-2
C44: Ctenanthe | D44: CT | E44: Mojito | F44: MOJ | H44: 2C
C45: Dracaena | D45: DR | E45: Moonlight | F45: MO | H45: 3D
C46: Ceropegia | D46: CE | E46: Neon | F46: NE | H46: 2D
C47: Calathea | D47: CA | E47: Ninja | F47: NI | H47: TC
C48: Ficus | D48: FIC | E48: Orange Marmalade | F48: OM | H48: 3A
C49: Epipremnum | D49: EPI | E49: Painted Lady | F49: PL | H49: 3C
C50: Colocasia | D50: COL | E50: Panda | F50: PA | H50: 3C
C51: Crassula | D51: CR | E51: Paraiso Verde | F51: PV
C52: Hypoestes | D52: HYP | E52: Party Time | F52: PT
C53: Chlorophytum | D53: CHL | E53: Peace Lily Domino | F53: PLD
C54: Dieffenbachia | D54: DI | E54: Pearls and Jade | F54: PAJ
E55: Peperomioides | F55: PEP | H55: 3C-2
E56: Peru | F56: PE
E57: Pink Princess | F57: PP
E58: Pink Princess Marbled | F58: PPM
E59: Pink Splash | F59: PS | H59: 3B
E60: Pinnatum Marble | F60: PM | H60: 2A
E61: Pinstripe | F61: PIN | H61: 2A-2
E62: Polly | F62: PO | H62: 2A-3
E63: Prince of Orange | F63: POO | H63: 2A-4
E64: Publicalyx | F64: PU | H64: 2A-5
E65: Purple Cloak | F65: PC | H65: 2A-6
E66: Red | F66: RE | H66: 2A-7
E67: Red Anderson Pink Knight | F67: RAPK | H67: 2A-8
E68: Red Flame | F68: RF | H68: 2A-9
E69: Red King | F69: RK | H69: 2A-10
E70: Red Sun | F70: RS
E71: Regal Shield | F71: RSD
E72: Rex | F72: REX
E73: Ring of Fire | F73: ROF
E74: Shining Sea Star | F74: SSS
E75: Shivereana | F75: SH
E76: Silver Splash | F76: SS
E77: Silver Sword | F77: SSW
E78: Snake Plant | F78: SP
E79: Snow Drift | F79: SD
E80: Spathonema | F80: SPA
E81: Spider Plant | F81: SPI
... E172: Japanese Maple Bloodgood | F172: JMB

Sheet Plant Inventory
A2: Date | B2: SKU | C2: Product Name | D2: Plant Cost | E2: Plant MSRP | F2: Est. Sale Price | G2: Act. Sell Price | H2: Profit | I2: Margin | J2: Status | K2: Notes | L2: U ID | M2: QTY Purchased | N2: QTY Sold | O2: QTY Used | P2: QTY Remaining | Q2: Owner Email | R2: Other Cost | S2: Total Cost | T2: Photo | U2: Other MSRP | V2: Total MSRP
A3: 42181 | B3: HS-CHL-SPI-1A | C3: Chlorophytum Spider Plant | D3: 0 | E3: 0 | J3: Status Pending | L3: XUZG6O | M3: 1 | N3: 0 | O3: 0 | P3: 1 | Q3: starr8@rocketmail.com | R3: 0 | S3: 0 | U3: 0
A4: 42181 | B4: HS-CHL-SPI-1A-2 | C4: Chlorophytum Spider Plant | D4: 0 | E4: 0 | J4: Status Pending | L4: OTJGIB | M4: 1 | N4: 0 | O4: 0 | P4: 1 | Q4: starr8@rocketmail.com | R4: 0 | S4: 0 | U4: 0
A5: 45866 | B5: OLN-FI-RF-1A | C5: Fittonia Red Flame | D5: 3.66 | E5: 0 | J5: Status Pending | L5: 39X0FM | M5: 1 | N5: 0 | O5: 0 | P5: 1 | Q5: starr8@rocketmail.com | R5: 0 | S5: 3.66 | U5: 0.25 | V5: 0.25
A6: 45873 | B6: TLC-PH-CS-1A | C6: Philodendron Cream Splash | D6: 0 | E6: 0 | J6: Status Pending | L6: WHQ1FG | M6: 1 | N6: 0 | O6: 0 | P6: 1 | Q6: starr8@rocketmail.com | R6: 0 | S6: 0 | U6: 0
A7: 45880 | B7: FMY-AL-RSD-1A | C7: Alocasia Regal Shield | D7: 10.99 | E7: 0 | F7: 40 | H7: 29.01 | I7: 0.72525 | J7: For Sale | L7: YSRDV1 | M7: 1 | N7: 0 | O7: 0 | P7: 1 | Q7: starr8@rocketmail.com | R7: 0 | S7: 10.99 | U7: 0
A8: 45881 | B8: TGOPS-PH-POO-1A-2 | C8: Philodendron Prince of Orange | D8: 7.79 | E8: 12.99 | J8: Status Pending | L8: WWGDIW | M8: 1 | N8: 0 | O8: 0 | P8: 1 | Q8: starr8@rocketmail.com | R8: 0 | S8: 7.79 | U8: 0 | V8: 12.99
A9: 45885 | B9: HS-PO-GO-1H | C9: Pothos Golden | D9: 0 | E9: 0 | J9: Status Pending | L9: NUMDI0 | M9: 1 | N9: 0 | O9: 0 | P9: 1 | Q9: starr8@rocketmail.com | R9: 0.92 | S9: 0.92 | U9: 0
A10: 45885 | B10: HS-PH-HL-1B | C10: Philodendron Heart Leaf | D10: 0 | E10: 0 | J10: Status Pending | L10: MV58CR | M10: 1 | N10: 0 | O10: 0 | P10: 1 | Q10: starr8@rocketmail.com | R10: 0.5 | S10: 0.5 | U10: 5 | V10: 5
A11: 45886 | B11: FM-MA-DE-1A | C11: Monstera Deliciosa | D11: 5 | E11: 0 | J11: Status Pending | L11: WD7WRM | M11: 1 | N11: 0 | O11: 0 | P11: 1 | Q11: starr8@rocketmail.com | R11: 0 | S11: 5 | U11: 0
A12: 45886 | B12: HD-PH-GG-1A | C12: Philodendron Golden Girl | D12: 19.98 | E12: 0 | J12: Status Pending | L12: AJGH01 | M12: 1 | N12: 0 | O12: 0 | P12: 1 | Q12: starr8@rocketmail.com | R12: 0 | S12: 19.98 | U12: 0
A13: 45886 | B13: HD-HO-SSS-1A | C13: Hoya Shining Sea Star | D13: 19.98 | E13: 0 | J13: Not for Sale | L13: 4QPCZJ | M13: 1 | N13: 0 | O13: 0 | P13: 1 | Q13: starr8@rocketmail.com | R13: 0 | S13: 19.98 | U13: 0
A14: 45886 | B14: HD-AL-LO-1B | C14: Alocasia Longiloba | D14: 7.5 | E14: 0 | F14: 25 | H14: 16.08 | I14: 0.6432 | J14: For Sale | L14: 0581CE | M14: 1 | N14: 0 | O14: 0 | P14: 1 | Q14: starr8@rocketmail.com | R14: 1.42 | S14: 8.92 | U14: 0
A15: 45888 | B15: HS-PI-PEP-1C | C15: Pilea Peperomioides | D15: 0 | E15: 0 | J15: Status Pending | L15: ADNJZH | M15: 1 | N15: 0 | O15: 0 | P15: 1 | Q15: starr8@rocketmail.com | R15: 0.29 | S15: 0.29 | U15: 0
A16: 45889 | B16: BWH-PH-RAPK-1A-3 | C16: Philodendron Red Anderson Pink Knight | D16: 10.2 | E16: 24.99 | F16: 30 | H16: 18.45 | I16: 0.615 | J16: For Sale | L16: JNFAYP | M16: 1 | N16: 0 | O16: 0 | P16: 1 | Q16: starr8@rocketmail.com | R16: 1.35 | S16: 11.55 | U16: 0 | V16: 24.99
A17: 45889 | B17: BWH-PH-RAPK-1A-4 | C17: Philodendron Red Anderson Pink Knight | D17: 10.2 | E17: 24.99 | J17: Status Pending | L17: N3BIB5 | M17: 1 | N17: 0 | O17: 0 | P17: 1 | Q17: starr8@rocketmail.com | R17: 1.35 | S17: 11.55 | U17: 0 | V17: 24.99
A18: 45890 | B18: HS-PI-PEP-1B | C18: Pilea Peperomioides | D18: 0 | E18: 0 | F18: 45 | H18: 44.71 | I18: 0.99355556 | J18: Status Pending | L18: 28327B | M18: 1 | N18: 0 | O18: 0 | P18: 1 | Q18: starr8@rocketmail.com | R18: 0.29 | S18: 0.29 | U18: 0
A19: 45890 | B19: BWH-PO-PAJ-1A-4A | C19: Pothos Pearls and Jade | D19: 1.95 | E19: 4.25 | J19: Status Pending | L19: G3NJBQ | M19: 1 | N19: 0 | O19: 0 | P19: 1 | Q19: starr8@rocketmail.com | R19: 0.92 | S19: 2.87 | U19: 0 | V19: 4.25
A20: 45890 | B20: BWH-PH-MO-1A-4 | C20: Philodendron Moonlight | D20: 6 | E20: 12.99 | J20: Status Pending | L20: Q34PVG | M20: 1 | N20: 0 | O20: 0 | P20: 1 | Q20: starr8@rocketmail.com | R20: 0.5 | S20: 6.5 | U20: 5 | V20: 17.99
A21: 45890 | B21: TGE-COL-DI-1A | C21: Colocasia Diamond | D21: 12.5 | E21: 0 | J21: Status Pending | L21: IEVN04 | M21: 1 | N21: 0 | O21: 0 | P21: 1 | Q21: starr8@rocketmail.com | R21: 0 | S21: 12.5 | U21: 0
A22: 45891 | B22: FMY-MA-DE-1A-3 | C22: Monstera Deliciosa | D22: 3.33 | E22: 0 | J22: Status Pending | L22: 7782F2 | M22: 1 | N22: 0 | O22: 0 | P22: 1 | Q22: starr8@rocketmail.com | R22: 0.5 | S22: 3.83 | U22: 5 | V22: 5
A23: 45891 | B23: FMY-MA-DE-1A-5 | C23: Monstera Deliciosa | D23: 2.75 | E23: 0 | J23: Status Pending | L23: GPYXM3 | M23: 1 | N23: 0 | O23: 0 | P23: 1 | Q23: starr8@rocketmail.com | R23: 1.35 | S23: 4.1 | U23: 0
A24: 45891 | B24: FMY-MA-DE-1A-4C | C24: Monstera Deliciosa | D24: 1.57 | E24: 0 | J24: Status Pending | L24: HL79I0 | M24: 1 | N24: 0 | O24: 0 | P24: 1 | Q24: starr8@rocketmail.com | R24: 0.5 | S24: 2.07 | U24: 5 | V24: 5
A25: 45891 | B25: FMY-MA-DE-1A-4D | C25: Monstera Deliciosa | D25: 1.57 | E25: 0 | J25: Status Pending | L25: 2MDRWW | M25: 1 | N25: 0 | O25: 0 | P25: 1 | Q25: starr8@rocketmail.com | R25: 0.5 | S25: 2.07 | U25: 5 | V25: 5
A26: 45891 | B26: FMY-MA-DE-1A-4F | C26: Monstera Deliciosa | D26: 1.57 | E26: 0 | F26: 20 | H26: 17.51 | I26: 0.8755 | J26: Status Pending | L26: CE12DE | M26: 1 | N26: 0 | O26: 0 | P26: 1 | Q26: starr8@rocketmail.com | R26: 0.92 | S26: 2.49 | U26: 0
A27: 45891 | B27: FMY-MA-DE-1A-3A | C27: Monstera Deliciosa | D27: 3.33 | E27: 0 | J27: Status Pending | L27: CX628U | M27: 1 | N27: 0 | O27: 0 | P27: 1 | Q27: starr8@rocketmail.com | R27: 1.06 | S27: 4.39 | U27: 5 | V27: 5
A28: 45891 | B28: FMY-MA-DE-1A-3B | C28: Monstera Deliciosa | D28: 3.33 | E28: 0 | J28: Status Pending | L28: 15ZW4Q | M28: 1 | N28: 0 | O28: 0 | P28: 1 | Q28: starr8@rocketmail.com | R28: 1.06 | S28: 4.39 | U28: 5 | V28: 5
A29: 45891 | B29: FMY-MA-DE-1A-3D | C29: Monstera Deliciosa | D29: 3.33 | E29: 0 | J29: Status Pending | L29: PNO518 | M29: 1 | N29: 0 | O29: 0 | P29: 1 | Q29: starr8@rocketmail.com | R29: 1.06 | S29: 4.39 | U29: 5 | V29: 5
A30: 45891 | B30: FMY-MA-DE-1A-3E | C30: Monstera Deliciosa | D30: 3.33 | E30: 0 | J30: Status Pending | L30: D8ZBCX | M30: 1 | N30: 0 | O30: 0 | P30: 1 | Q30: starr8@rocketmail.com | R30: 0.29 | S30: 3.62 | U30: 0
A31: 45892 | B31: HD-AL-GVF-1A-2 | C31: Alocasia Green Velvet Frydek | D31: 14.99 | E31: 0 | J31: Status Pending | L31: SNAZUL | M31: 1 | N31: 0 | O31: 0 | P31: 1 | Q31: starr8@rocketmail.com | R31: 1.35 | S31: 16.34 | U31: 0
A32: 45892 | B32: HD-ST-TR-1A | C32: Stromanthe Triostar | D32: 19.98 | E32: 0 | J32: Status Pending | L32: H43F16 | M32: 1 | N32: 0 | O32: 0 | P32: 1 | Q32: starr8@rocketmail.com | R32: 0.61 | S32: 20.59 | U32: 5 | V32: 5
A33: 45892 | B33: IST-PH-PP-1B | C33: Philodendron Pink Princess | D33: 5.4 | E33: 0 | J33: Status Pending | L33: PHIQRY | M33: 1 | N33: 0 | O33: 0 | P33: 1 | Q33: starr8@rocketmail.com | R33: 0.13 | S33: 5.53 | U33: 0
A34: 45892 | B34: IST-PH-PP-1C | C34: Philodendron Pink Princess | D34: 5.4 | E34: 0 | J34: Status Pending | L34: UKSX6B | M34: 1 | N34: 0 | O34: 0 | P34: 1 | Q34: starr8@rocketmail.com | R34: 0.13 | S34: 5.53 | U34: 0
A35: 45892 | B35: HD-AL-GVF-1A-2B | C35: Alocasia Green Velvet Frydek | D35: 14.99 | E35: 0 | J35: Status Pending | L35: BJTOC6 | M35: 1 | N35: 0 | O35: 0 | P35: 1 | Q35: starr8@rocketmail.com | R35: 1.35 | S35: 16.34 | U35: 0
A36: 45893 | B36: HS-SP-PLD-1A | C36: Spathiphyllum Peace Lily Domino | D36: 2.5 | E36: 3.75 | J36: Status Pending | L36: 6ZZ49C | M36: 1 | N36: 0 | O36: 0 | P36: 1 | Q36: starr8@rocketmail.com | R36: 0 | S36: 2.5 | U36: 0 | V36: 3.75
A37: 45893 | B37: HS-SP-PLD-1E | C37: Spathiphyllum Peace Lily Domino | D37: 2.5 | E37: 3.75 | J37: Status Pending | L37: 1CSDUP | M37: 1 | N37: 0 | O37: 0 | P37: 1 | Q37: starr8@rocketmail.com | R37: 0.5 | S37: 3 | U37: 5 | V37: 8.75
A38: 45893 | B38: HS-BE-AW-1C | C38: Begonia Angel Wing | D38: 0 | E38: 0 | J38: Status Pending | L38: 4G22U5 | M38: 1 | N38: 0 | O38: 0 | P38: 1 | Q38: starr8@rocketmail.com | R38: 1.42 | S38: 1.42 | U38: 0
A39: 45893 | B39: FMY-CA-MA-1D | C39: Calathea Makoyana | D39: 3.33 | E39: 2.83 | J39: Status Pending | L39: C7QOSP | M39: 1 | N39: 0 | O39: 0 | P39: 1 | Q39: starr8@rocketmail.com | R39: 0.5 | S39: 3.83 | U39: 5 | V39: 7.83
A40: 45893 | B40: FMY-CA-MA-1G | C40: Calathea Makoyana | D40: 3.33 | E40: 2.83 | J40: Status Pending | L40: EN413Y | M40: 1 | N40: 0 | O40: 0 | P40: 1 | Q40: starr8@rocketmail.com | R40: 0.67 | S40: 4 | U40: 0 | V40: 2.83
A41: 45893 | B41: FMY-CA-MA-1H | C41: Calathea Makoyana | D41: 3.33 | E41: 2.83 | J41: Status Pending | L41: Q2YSXQ | M41: 1 | N41: 0 | O41: 0 | P41: 1 | Q41: starr8@rocketmail.com | R41: 0.67 | S41: 4 | U41: 0 | V41: 2.83
A42: 45893 | B42: HS-BE-AW-1G | C42: Begonia Angel Wing | D42: 0 | E42: 0 | J42: Status Pending | L42: LI0IFZ | M42: 1 | N42: 0 | O42: 0 | P42: 1 | Q42: starr8@rocketmail.com | R42: 0.29 | S42: 0.29 | U42: 0
A43: 45893 | B43: HS-SP-PLD-1B | C43: Spathiphyllum Peace Lily Domino | D43: 2.5 | E43: 3.75 | F43: 20 | H43: 17.5 | I43: 0.875 | J43: For Sale | L43: 967C9B | M43: 1 | N43: 0 | O43: 0 | P43: 1 | Q43: starr8@rocketmail.com | R43: 0 | S43: 2.5 | U43: 0 | V43: 3.75
A44: 45893 | B44: HS-SP-PLD-1D | C44: Spathiphyllum Peace Lily Domino | D44: 2.5 | E44: 3.75 | J44: Status Pending | L44: 1ODAQT | M44: 1 | N44: 0 | O44: 0 | P44: 1 | Q44: starr8@rocketmail.com | R44: 0.5 | S44: 3 | U44: 5 | V44: 8.75
A45: 45893 | B45: HS-SP-PLD-1F | C45: Spathiphyllum Peace Lily Domino | D45: 2.5 | E45: 3.75 | J45: Status Pending | L45: BQ1CPO | M45: 1 | N45: 0 | O45: 0 | P45: 1 | Q45: starr8@rocketmail.com | R45: 0.92 | S45: 3.42 | U45: 0 | V45: 3.75
A46: 45893 | B46: HS-SP-PLD-1G | C46: Spathiphyllum Peace Lily Domino | D46: 2.5 | E46: 3.75 | J46: Status Pending | L46: TVDI1D | M46: 1 | N46: 0 | O46: 0 | P46: 1 | Q46: starr8@rocketmail.com | R46: 0.47 | S46: 2.97 | U46: 0 | V46: 3.75
A47: 45893 | B47: HS-SP-PLD-1H | C47: Spathiphyllum Peace Lily Domino | D47: 2.5 | E47: 3.75 | J47: Status Pending | L47: 3HQGQ2 | M47: 1 | N47: 0 | O47: 0 | P47: 1 | Q47: starr8@rocketmail.com | R47: 0.92 | S47: 3.42 | U47: 0 | V47: 3.75
A48: 45894 | B48: HS-PH-BRL-1A | C48: Philodendron Brasil | D48: 0 | E48: 0 | J48: Status Pending | L48: ZPRY8N | M48: 1 | N48: 0 | O48: 0 | P48: 1 | Q48: starr8@rocketmail.com | R48: 1.35 | S48: 1.35 | U48: 0
A49: 45894 | B49: HS-PH-BRL-1B | C49: Philodendron Brasil | D49: 0 | E49: 0 | J49: Status Pending | L49: DM8M4Z | M49: 1 | N49: 0 | O49: 0 | P49: 1 | Q49: starr8@rocketmail.com | R49: 1.35 | S49: 1.35 | U49: 0
A50: 45896 | B50: TGOPS-PH-WW-1A-3 | C50: Philodendron White Wizard | D50: 4.4 | E50: 0 | F50: 35 | H50: 29.25 | I50: 0.83571429 | J50: For Sale | L50: EH71UV | M50: 1 | N50: 0 | O50: 0 | P50: 1 | Q50: starr8@rocketmail.com | R50: 1.35 | S50: 5.75 | U50: 0
A51: 45896 | B51: HD-AL-LO-1A-2 | C51: Alocasia Longiloba | D51: 9.99 | E51: 0 | J51: Status Pending | L51: RCEBJL | M51: 1 | N51: 0 | O51: 0 | P51: 1 | Q51: starr8@rocketmail.com | R51: 0.94 | S51: 10.93 | U51: 0
A52: 45896 | B52: TGOPS-PH-WW-1E | C52: Philodendron White Wizard | D52: 2.2 | E52: 0 | J52: Status Pending | L52: N7WDMB | M52: 1 | N52: 0 | O52: 0 | P52: 1 | Q52: starr8@rocketmail.com | R52: 0.13 | S52: 2.33 | U52: 0
A53: 45896 | B53: TGOPS-PH-WW-1A-3C | C53: Philodendron White Wizard | D53: 4.4 | E53: 0 | F53: 16 | H53: 11.31 | I53: 0.706875 | J53: For Sale | L53: N01BZC | M53: 1 | N53: 0 | O53: 0 | P53: 1 | Q53: starr8@rocketmail.com | R53: 0.29 | S53: 4.69 | U53: 0
A54: 45896 | B54: TGOPS-PH-WW-1A-2D | C54: Philodendron White Wizard | D54: 3.3 | E54: 0 | J54: Status Pending | L54: KV0ZRQ | M54: 1 | N54: 0 | O54: 0 | P54: 1 | Q54: starr8@rocketmail.com | R54: 1.35 | S54: 4.65 | U54: 0
A55: 45896 | B55: TGOPS-PH-WW-1A-2C | C55: Philodendron White Wizard | D55: 3.3 | E55: 0 | F55: 25 | H55: 21.24 | I55: 0.8496 | J55: For Sale | L55: U88SGL | M55: 1 | N55: 0 | O55: 0 | P55: 1 | Q55: starr8@rocketmail.com | R55: 0.46 | S55: 3.76 | U55: 5 | V55: 5
A56: 45897 | B56: HS-PO-GO-1A | C56: Pothos Golden | D56: 0 | E56: 0 | F56: 0 | J56: Status Pending | L56: D8B44C | M56: 1 | N56: 0 | O56: 0 | P56: 1 | Q56: starr8@rocketmail.com | R56: 0 | S56: 0 | U56: 0
A57: 45897 | B57: HS-PH-HL-1A | C57: Philodendron Heart Leaf | D57: 0 | E57: 0 | J57: Status Pending | L57: ABC346 | M57: 1 | N57: 0 | O57: 0 | P57: 1 | Q57: starr8@rocketmail.com | R57: 0 | S57: 0 | U57: 0
A58: 45897 | B58: HS-PI-PEP-1A | C58: Pilea Peperomioides | D58: 0 | E58: 0 | J58: Status Pending | L58: 34BTWV | M58: 1 | N58: 0 | O58: 0 | P58: 1 | Q58: starr8@rocketmail.com | R58: 0 | S58: 0 | U58: 0
A59: 45897 | B59: WM-MA-PE-1A | C59: Monstera Peru | D59: 7 | E59: 0 | J59: Status Pending | L59: OF2TEW | M59: 1 | N59: 0 | O59: 0 | P59: 1 | Q59: starr8@rocketmail.com | R59: 0 | S59: 7 | U59: 0
A60: 45897 | B60: ZB-SE-HA-1A | C60: Senecio Haworthii | D60: 0 | E60: 0 | J60: Status Pending | L60: ETTTIO | M60: 1 | N60: 0 | O60: 0 | P60: 1 | Q60: starr8@rocketmail.com | R60: 0 | S60: 0 | U60: 0
A61: 45897 | B61: TGOPS-PH-PPM-1A-3 | C61: Philodendron Pink Princess Marbled | D61: 16.19 | E61: 26.99 | H61: -16.69 | I61: -1 | J61: Dead | L61: 8LG9H1 | M61: 1 | N61: 0 | O61: 1 | P61: 0 | Q61: starr8@rocketmail.com | R61: 0.5 | S61: 16.69 | U61: 5 | V61: 31.99
A62: 45897 | B62: FMY-MA-PE-1B | C62: Monstera Peru | D62: 2.43 | E62: 0 | J62: Status Pending | L62: OWD1CA | M62: 1 | N62: 0 | O62: 0 | P62: 1 | Q62: starr8@rocketmail.com | R62: 0.94 | S62: 3.37 | U62: 0
A63: 45897 | B63: FMY-MA-PE-1C | C63: Monstera Peru | D63: 2.43 | E63: 0 | J63: Status Pending | L63: K42O9G | M63: 1 | N63: 0 | O63: 0 | P63: 1 | Q63: starr8@rocketmail.com | R63: 0.94 | S63: 3.37 | U63: 0
A64: 45897 | B64: FMY-MA-PE-1G | C64: Monstera Peru | D64: 2.43 | E64: 0 | J64: Out of Stock | L64: M36KC1 | M64: 1 | N64: 0 | O64: 1 | P64: 0 | Q64: starr8@rocketmail.com | R64: 1.35 | S64: 3.78 | U64: 0
A65: 45897 | B65: FMY-AG-SPA-1C | C65: Aglaonema Spathonema | D65: 3.33 | E65: 0 | J65: Status Pending | L65: 89LQHE | M65: 1 | N65: 0 | O65: 0 | P65: 1 | Q65: starr8@rocketmail.com | R65: 0.5 | S65: 3.83 | U65: 5 | V65: 5
A66: 45897 | B66: FMY-AG-SPA-1F | C66: Aglaonema Spathonema | D66: 3.33 | E66: 0 | J66: Status Pending | L66: B219F6 | M66: 1 | N66: 0 | O66: 0 | P66: 1 | Q66: starr8@rocketmail.com | R66: 0.92 | S66: 4.25 | U66: 0
A67: 45897 | B67: FMY-MA-DE-1B | C67: Monstera Deliciosa | D67: 2.2 | E67: 5 | J67: Status Pending | L67: XY9MNS | M67: 1 | N67: 0 | O67: 0 | P67: 1 | Q67: starr8@rocketmail.com | R67: 0.94 | S67: 3.14 | U67: 0 | V67: 5
A68: 45897 | B68: FMY-MA-DE-1E | C68: Monstera Deliciosa | D68: 2.2 | E68: 5 | J68: Status Pending | L68: EXZX17 | M68: 1 | N68: 0 | O68: 0 | P68: 1 | Q68: starr8@rocketmail.com | R68: 0.5 | S68: 2.7 | U68: 5 | V68: 10
A69: 45898 | B69: HS-BE-AW-1A | C69: Begonia Angel Wing | D69: 0 | E69: 0 | J69: Status Pending | L69: 7KWQ4P | M69: 1 | N69: 0 | O69: 0 | P69: 1 | Q69: starr8@rocketmail.com | R69: 0.5 | S69: 0.5 | U69: 5 | V69: 5
A70: 45898 | B70: HS-PH-HL-1F | C70: Philodendron Heart Leaf | D70: 0 | E70: 0 | J70: Out of Stock | L70: 2994WG | M70: 1 | N70: 0 | O70: 1 | P70: 0 | Q70: starr8@rocketmail.com | R70: 4.5 | S70: 4.5 | U70: 0
A71: 45898 | B71: HS-PH-BRL-1D | C71: Philodendron Brasil | D71: 0 | E71: 0 | F71: 12 | H71: 7.5 | I71: 0.625 | J71: For Sale | L71: V7I76G | M71: 1 | N71: 0 | O71: 0 | P71: 1 | Q71: starr8@rocketmail.com | R71: 4.5 | S71: 4.5 | U71: 0
A72: 45898 | B72: HS-BE-AW-1K | C72: Begonia Angel Wing | D72: 0 | E72: 0 | J72: Status Pending | L72: 6AA72A | M72: 1 | N72: 0 | O72: 0 | P72: 1 | Q72: starr8@rocketmail.com | R72: 0.29 | S72: 0.29 | U72: 0
A73: 45898 | B73: BWH-PO-PAJ-1B | C73: Pothos Pearls and Jade | D73: 7.8 | E73: 16.99 | J73: Status Pending | L73: J160VY | M73: 1 | N73: 0 | O73: 0 | P73: 1 | Q73: starr8@rocketmail.com | R73: 4.5 | S73: 12.3 | U73: 0 | V73: 16.99
A74: 45898 | B74: HS-PO-GO-1K | C74: Pothos Golden | D74: 0 | E74: 0 | J74: Status Pending | L74: 208D40 | M74: 1 | N74: 0 | O74: 0 | P74: 1 | Q74: starr8@rocketmail.com | R74: 0.29 | S74: 0.29 | U74: 0
A75: 45899 | B75: FMY-MA-DE-1A-4A | C75: Monstera Deliciosa | D75: 1.57 | E75: 0 | G75: 10 | H75: 7.08 | I75: 0.708 | J75: Sold | L75: O23L5L | M75: 1 | N75: 1 | O75: 0 | P75: 0 | Q75: starr8@rocketmail.com | R75: 1.35 | S75: 2.92 | U75: 0
A76: 45899 | B76: HS-CT-BM-1A | C76: Ctenanthe Burle Marxii | D76: 0 | E76: 0 | J76: Status Pending | L76: 2TF3HD | M76: 1 | N76: 0 | O76: 0 | P76: 1 | Q76: starr8@rocketmail.com | R76: 1.06 | S76: 1.06 | U76: 5 | V76: 5
A77: 45899 | B77: FMY-MA-DE-1A-4E | C77: Monstera Deliciosa | D77: 1.57 | E77: 0 | G77: 7 | H77: 4.93 | I77: 0.70428571 | J77: Sold | L77: 2GD051 | M77: 1 | N77: 1 | O77: 0 | P77: 0 | Q77: starr8@rocketmail.com | R77: 0.5 | S77: 2.07 | U77: 5 | V77: 5
A78: 45899 | B78: HS-PO-GO-1I | C78: Pothos Golden | D78: 0 | E78: 0 | G78: 4 | H78: 3.5 | I78: 0.875 | J78: Sold | L78: 22LS7K | M78: 1 | N78: 1 | O78: 0 | P78: 0 | Q78: starr8@rocketmail.com | R78: 0.5 | S78: 0.5 | U78: 5 | V78: 5
A79: 45899 | B79: BWH-PO-PAJ-1A-4B | C79: Pothos Pearls and Jade | D79: 1.95 | E79: 4.25 | G79: 9 | H79: 6.76 | I79: 0.75111111 | J79: Sold | L79: 34XBMM | M79: 1 | N79: 1 | O79: 0 | P79: 0 | Q79: starr8@rocketmail.com | R79: 0.29 | S79: 2.24 | U79: 0 | V79: 4.25
A80: 45899 | B80: BWH-PO-PAJ-1A-4C | C80: Pothos Pearls and Jade | D80: 1.95 | E80: 4.25 | G80: 12 | H80: 9.76 | I80: 0.81333333 | J80: Sold | L80: 7N6HIM | M80: 1 | N80: 1 | O80: 0 | P80: 0 | Q80: starr8@rocketmail.com | R80: 0.29 | S80: 2.24 | U80: 0 | V80: 4.25
A81: 45899 | B81: HD-ST-TR-1B | C81: Stromanthe Triostar | D81: 9.99 | E81: 0 | G81: 10 | H81: -0.49 | I81: -0.049 | J81: Sold | L81: EPHN4D | M81: 1 | N81: 1 | O81: 0 | P81: 0 | Q81: starr8@rocketmail.com | R81: 0.5 | S81: 10.49 | U81: 5 | V81: 5
A82: 45899 | B82: HD-ST-TR-1C | C82: Stromanthe Triostar | D82: 9.99 | E82: 0 | G82: 10 | H82: -0.49 | I82: -0.049 | J82: Sold | L82: X80QAT | M82: 1 | N82: 1 | O82: 0 | P82: 0 | Q82: starr8@rocketmail.com | R82: 0.5 | S82: 10.49 | U82: 5 | V82: 5
A83: 45899 | B83: HS-BE-AW-1B | C83: Begonia Angel Wing | D83: 0 | E83: 0 | G83: 3 | H83: 2.71 | I83: 0.90333333 | J83: Sold | L83: VZMLQY | M83: 1 | N83: 1 | O83: 0 | P83: 0 | Q83: starr8@rocketmail.com | R83: 0.29 | S83: 0.29 | U83: 0
A84: 45899 | B84: FMY-CA-MA-1C | C84: Calathea Makoyana | D84: 3.33 | E84: 2.83 | G84: 12 | H84: 8.17 | I84: 0.68083333 | J84: Sold | L84: NGTZRC | M84: 1 | N84: 1 | O84: 0 | P84: 0 | Q84: starr8@rocketmail.com | R84: 0.5 | S84: 3.83 | U84: 5 | V84: 7.83
A85: 45899 | B85: HS-PO-GO-1B | C85: Pothos Golden | D85: 0 | E85: 0 | G85: 2 | H85: 1.08 | I85: 0.54 | J85: Sold | L85: 2I6UYO | M85: 1 | N85: 1 | O85: 0 | P85: 0 | Q85: starr8@rocketmail.com | R85: 0.92 | S85: 0.92 | U85: 0
A86: 45899 | B86: HS-CT-BM-1B | C86: Ctenanthe Burle Marxii | D86: 0 | E86: 0 | J86: Status Pending | L86: 0HN8KB | M86: 1 | N86: 0 | O86: 0 | P86: 1 | Q86: starr8@rocketmail.com | R86: 1.06 | S86: 1.06 | U86: 5 | V86: 5
A87: 45899 | B87: HS-CT-BM-1C | C87: Ctenanthe Burle Marxii | D87: 0 | E87: 0 | J87: Status Pending | L87: M92SA5 | M87: 1 | N87: 0 | O87: 0 | P87: 1 | Q87: starr8@rocketmail.com | R87: 4 | S87: 4 | U87: 8 | V87: 8
A88: 45899 | B88: BWH-PH-MO-1A-5 | C88: Philodendron Moonlight | D88: 6 | E88: 12.99 | G88: 30 | H88: 22.65 | I88: 0.755 | J88: Sold | L88: 3IHH12 | M88: 1 | N88: 1 | O88: 0 | P88: 0 | Q88: starr8@rocketmail.com | R88: 1.35 | S88: 7.35 | U88: 0 | V88: 12.99
A89: 45899 | B89: BWH-PO-PAJ-1A-3 | C89: Pothos Pearls and Jade | D89: 7.8 | E89: 16.99 | G89: 12 | H89: 2.78 | I89: 0.23166667 | J89: Sold | L89: NKPSC0 | M89: 1 | N89: 1 | O89: 0 | P89: 0 | Q89: starr8@rocketmail.com | R89: 1.42 | S89: 9.22 | U89: 0 | V89: 16.99
A90: 45899 | B90: BWH-PO-PAJ-1A-4 | C90: Pothos Pearls and Jade | D90: 1.95 | E90: 4.25 | G90: 12 | H90: 9.55 | I90: 0.79583333 | J90: Sold | L90: WTTLYJ | M90: 1 | N90: 1 | O90: 0 | P90: 0 | Q90: starr8@rocketmail.com | R90: 0.5 | S90: 2.45 | U90: 5 | V90: 9.25
A91: 45900 | B91: FM-PH-PP-1A | C91: Philodendron Pink Princess | D91: 0 | E91: 0 | J91: Status Pending | L91: 8KA9UI | M91: 1 | N91: 0 | O91: 0 | P91: 1 | Q91: starr8@rocketmail.com | R91: 0.24 | S91: 0.24 | U91: 1 | V91: 1
A92: 45900 | B92: TRL-FIC-TE-1A | C92: Ficus Teneke | D92: 10 | E92: 0 | J92: Status Pending | L92: QWLKQ3 | M92: 1 | N92: 0 | O92: 0 | P92: 1 | Q92: starr8@rocketmail.com | R92: 0.5 | S92: 10.5 | U92: 5 | V92: 5
A93: 45900 | B93: BTPG-HO-KP-1D | C93: Hoya Krimson Princess | D93: 6.08 | E93: 0 | J93: Unverified | L93: DLHG6R | M93: 1 | N93: 0 | O93: 0 | P93: 1 | Q93: starr8@rocketmail.com | R93: 0.29 | S93: 6.37 | U93: 0
A94: 45900 | B94: BTPG-HO-KP-1E | C94: Hoya Krimson Princess | D94: 6.08 | E94: 0 | J94: Status Pending | L94: PAJVGR | M94: 1 | N94: 0 | O94: 0 | P94: 1 | Q94: starr8@rocketmail.com | R94: 0.29 | S94: 6.37 | U94: 0
A95: 45900 | B95: FM-PH-PP-1B | C95: Philodendron Pink Princess | D95: 0 | E95: 0 | F95: 25 | H95: 24.76 | I95: 0.9904 | J95: For Sale | L95: JP6SRE | M95: 1 | N95: 0 | O95: 0 | P95: 1 | Q95: starr8@rocketmail.com | R95: 0.24 | S95: 0.24 | U95: 1 | V95: 1
A96: 45900 | B96: FM-PH-PP-1D | C96: Philodendron Pink Princess | D96: 0 | E96: 0 | J96: Status Pending | L96: ZZ2UQF | M96: 1 | N96: 0 | O96: 0 | P96: 1 | Q96: starr8@rocketmail.com | R96: 0.24 | S96: 0.24 | U96: 1 | V96: 1
A97: 45902 | B97: BPF-CE-SOH-1A-2 | C97: Ceropegia String of Hearts | D97: 5.84 | E97: 8.99 | H97: -5.84 | I97: -1 | J97: Dead | L97: J8TZIZ | M97: 1 | N97: 0 | O97: 1 | P97: 0 | Q97: starr8@rocketmail.com | R97: 0 | S97: 5.84 | U97: 0 | V97: 8.99
A98: 45902 | B98: BPF-CE-SOH-1A-3 | C98: Ceropegia String of Hearts | D98: 5.84 | E98: 8.99 | H98: -5.84 | I98: -1 | J98: Dead | L98: 68FNGY | M98: 1 | N98: 0 | O98: 1 | P98: 0 | Q98: starr8@rocketmail.com | R98: 0 | S98: 5.84 | U98: 0 | V98: 8.99
A99: 45902 | B99: BPF-CE-SOH-1A-4 | C99: Ceropegia String of Hearts | D99: 5.84 | E99: 8.99 | G99: 10 | H99: 4.16 | I99: 0.416 | J99: Sold | L99: L1E23B | M99: 1 | N99: 1 | O99: 0 | P99: 0 | Q99: starr8@rocketmail.com | R99: 0 | S99: 5.84 | U99: 0 | V99: 8.99
A100: 45902 | B100: BPF-CE-SOH-1A-5 | C100: Ceropegia String of Hearts | D100: 5.84 | E100: 8.99 | G100: 10 | H100: 4.16 | I100: 0.416 | J100: Sold | L100: P3MUJA | M100: 1 | N100: 1 | O100: 0 | P100: 0 | Q100: starr8@rocketmail.com | R100: 0 | S100: 5.84 | U100: 0 | V100: 8.99
A101: 45902 | B101: BPF-SE-SOP-1A-2 | C101: Senecio String of Pearls | D101: 4.71 | E101: 7.25 | J101: Status Pending | L101: WURQBD | M101: 1 | N101: 0 | O101: 0 | P101: 1 | Q101: starr8@rocketmail.com | R101: 0 | S101: 4.71 | U101: 0 | V101: 7.25
...

Sheet  PRICING
F1: =SUM(F3:F3005) -> 5645.0427 | G1: =SUM(G3:G3005) -> 0 | H1: =SUM(H3:H3005) -> 0 | I1: =SUM(I3:I3005) -> 0 | J1: =SUM(J3:J3005) -> 69 | K1: =SUM(K3:K3005) -> 691 | M1: =SUM(M3:M3005) -> 750 | N1: =IF(SUM(J3:J992)=0,0,SUM(M3:M992)/SUM(J3:J992)) -> 10.869565
A2: Date | B2: SKU | C2: Product Name | E2: Pot SKU | F2: Pl Co | G2: Pot/Prod Co | H2: OH | I2: Tot Co | J2: Est. Sell Pr | K2: AcSell Pr | L2: Disc | M2: Profit | N2: Margin | O2: Av. Qty | P2: Status | Q2: Notes | R2: Mirror UID | S2: MSRP | T2: Not UID | V2: U ID
A3: {=IF(B3:B3000="","", VLOOKUP( B3:B3000, { TRIM('PLANT Intake Coding'!F3:F1000), 'PLANT Intake Coding'!A3:A1000; TRIM('Transplant Log'!H3:H997), 'Transplant Log'!A3:A997; TRIM('PRODUCT Intake Coding'!I3:I993), 'PRODUCT Intake Coding'!A3:A993 }, 2, FALSE ) )} -> 38202 | B3: =IFERROR(__xludf.DUMMYFUNCTION("ARRAYFORMULA( UNIQUE( FILTER( { UPPER(TRIM(CLEAN(SUBSTITUTE('PLANT Intake Coding'!F3:INDEX('PLANT Intake Coding'!F:F, MATCH(2,1/('PLANT Intake Coding'!F:F<>""""))), CHAR(160), """")))); UPPER(TRIM(CLEAN(SUBSTITUTE('Transplant L"&"og'!H3:INDEX('Transplant Log'!H:H, MATCH(2,1/('Transplant Log'!H:H<>""""))), CHAR(160), """")))); UPPER(TRIM(CLEAN(SUBSTITUTE('PRODUCT Intake Coding'!I3:INDEX('PRODUCT Intake Coding'!I:I, MATCH(2,1/('PRODUCT Intake Coding'!I:I<>""""))), CHAR(160),"&" """")))) }, LEN({ TRIM(CLEAN(SUBSTITUTE('PLANT Intake Coding'!F3:INDEX('PLANT Intake Coding'!F:F, MATCH(2,1/('PLANT Intake Coding'!F:F<>""""))), CHAR(160), """"))); TRIM(CLEAN(SUBSTITUTE('Transplant Log'!H3:INDEX('Transplant L"&"og'!H:H, MATCH(2,1/('Transplant Log'!H:H<>""""))), CHAR(160), """"))); TRIM(CLEAN(SUBSTITUTE('PRODUCT Intake Coding'!I3:INDEX('PRODUCT Intake Coding'!I:I, MATCH(2,1/('PRODUCT Intake Coding'!I:I<>""""))), CHAR(160), """"))) }) ) ) ) "),"HS-BE-AW-1A") -> HS-BE-AW-1A | C3: Angel Wing | E3: =IFERROR(__xludf.DUMMYFUNCTION("ARRAYFORMULA( IF(B3:B3000="""","""", IFNA( VLOOKUP(B3:B3000, FILTER({'Transplant Log'!H3:H997,'Transplant Log'!F3:F997}, LEN('Transplant Log'!H3:H997)), 2, FALSE), IF(COUNTIF('PRODUC"&"T Intake Coding'!I3:I993,B3:B3000), B3:B3000, """") ) ) ) "),"TO-PO-4-MU-1") -> TO-PO-4-MU-1 | F3: {=IF(B3:B3001="","", IFNA( VLOOKUP(B3:B3001, {'Transplant Log'!H3:H997,'Transplant Log'!I3:I997}, 2, FALSE), IFNA( VLOOKUP(B3:B3001, {'PLANT Intake Coding'!F3:F1000,'PLANT Intake Coding'!G3:G1000}, 2, FALSE), 0 ) ) )} -> 0 | L3: None | M3: {=IF(B3:B992="","", IF( (LEN(J3:J992)=0)*(LEN(K3:K992)=0),"", (IF( N(K3:K992)>0, N(K3:K992), N(J3:J992) ) - I3:I992 - IFERROR(N(L3:L992),0) ) ) )} | N3: =IFERROR(__xludf.DUMMYFUNCTION("ARRAYFORMULA( IF(LEN(I3:I3001)=0,"""", IF(LEN(K3:K3001), IFERROR((TO_PURE_NUMBER(K3:K3001)-TO_PURE_NUMBER(I3:I3001))/TO_PURE_NUMBER(K3:K3001),""""), IFERROR((TO_PURE_NUMBER(J3:J3001)-TO_PURE_NUMBER(I3:I3001))/TO_PURE_NUMBER(J3:J3001),"""") ) "&" ) )"),"") | P3: Not for Sale | R3: {=IF(B3:B3000="","", IFERROR( VLOOKUP( B3:B3000, { TRIM('PLANT Intake Coding'!F3:F1000), 'PLANT Intake Coding'!J3:J1000; TRIM('Transplant Log'!H3:H997), 'Transplant Log'!K3:K997; TRIM('PRODUCT Intake Coding'!I3:I993), 'PRODUCT Intake Coding'!P3:P993 }, 2, FALSE ), "" ) )} -> E87921 | S3: {=IF(R3:R3000="","", IFNA( VLOOKUP( R3:R3000, {'PLANT Intake Coding'!$J$3:$J$1000,'PLANT Intake Coding'!$K$3:$K$1000}, 2, FALSE ), "" ) )} | T3: AF49E2 | V3: AF49E2
B4: =IFERROR(__xludf.DUMMYFUNCTION("""COMPUTED_VALUE"""),"HS-PO-GO-1A") -> HS-PO-GO-1A | E4: =IFERROR(__xludf.DUMMYFUNCTION("""COMPUTED_VALUE"""),"") | F4: 0 | L4: Giveaway | N4: =IFERROR(__xludf.DUMMYFUNCTION("""COMPUTED_VALUE"""),"") | R4: 9C3687 | T4: AE5AD3 | V4: AE5AD3
B5: =IFERROR(__xludf.DUMMYFUNCTION("""COMPUTED_VALUE"""),"HS-PH-HL-1A") -> HS-PH-HL-1A | E5: =IFERROR(__xludf.DUMMYFUNCTION("""COMPUTED_VALUE"""),"") | F5: 0 | L5: None | N5: =IFERROR(__xludf.DUMMYFUNCTION("""COMPUTED_VALUE"""),"") | R5: 851D91 | T5: 29FB31 | V5: 29FB31
B6: =IFERROR(__xludf.DUMMYFUNCTION("""COMPUTED_VALUE"""),"HS-PH-BRL-1A") -> HS-PH-BRL-1A | E6: =IFERROR(__xludf.DUMMYFUNCTION("""COMPUTED_VALUE"""),"GA-PO-6-MU-1") -> GA-PO-6-MU-1 | F6: 0 | L6: None | N6: =IFERROR(__xludf.DUMMYFUNCTION("""COMPUTED_VALUE"""),"") | P6: Not for Sale | R6: FB20D8 | T6: 0649C0 | V6: 0649C0
B7: =IFERROR(__xludf.DUMMYFUNCTION("""COMPUTED_VALUE"""),"HS-PI-PEP-1A") -> HS-PI-PEP-1A | E7: =IFERROR(__xludf.DUMMYFUNCTION("""COMPUTED_VALUE"""),"") | F7: 0 | L7: None | N7: =IFERROR(__xludf.DUMMYFUNCTION("""COMPUTED_VALUE"""),"") | R7: 62867D | T7: FE0A2D | V7: FE0A2D
A8: 45899 | B8: =IFERROR(__xludf.DUMMYFUNCTION("""COMPUTED_VALUE"""),"HS-CT-BM-1A") -> HS-CT-BM-1A | E8: =IFERROR(__xludf.DUMMYFUNCTION("""COMPUTED_VALUE"""),"ZO-PO-4-WL-1") -> ZO-PO-4-WL-1 | F8: 0 | N8: =IFERROR(__xludf.DUMMYFUNCTION("""COMPUTED_VALUE"""),"") | R8: 59D755 | T8: 475931 | V8: 475931
B9: =IFERROR(__xludf.DUMMYFUNCTION("""COMPUTED_VALUE"""),"HS-DR-SP-1A") -> HS-DR-SP-1A | E9: =IFERROR(__xludf.DUMMYFUNCTION("""COMPUTED_VALUE"""),"TE-PO-4-MU-3") -> TE-PO-4-MU-3 | F9: 0 | N9: =IFERROR(__xludf.DUMMYFUNCTION("""COMPUTED_VALUE"""),"") | R9: D10239 | T9: 2FF9FD | V9: 2FF9FD
A10: 45873 | B10: =IFERROR(__xludf.DUMMYFUNCTION("""COMPUTED_VALUE"""),"FM-PH-WK-1A") -> FM-PH-WK-1A | E10: =IFERROR(__xludf.DUMMYFUNCTION("""COMPUTED_VALUE"""),"") | F10: 15 | N10: =IFERROR(__xludf.DUMMYFUNCTION("""COMPUTED_VALUE"""),"") | P10: Not for Sale | R10: 8F306F | S10: 0 | T10: 16487D | V10: 16487D
A11: 45872 | B11: =IFERROR(__xludf.DUMMYFUNCTION("""COMPUTED_VALUE"""),"WM-PH-WK-1A") -> WM-PH-WK-1A | E11: =IFERROR(__xludf.DUMMYFUNCTION("""COMPUTED_VALUE"""),"MU-PO-4-WH-1") -> MU-PO-4-WH-1 | F11: 4.9925 | N11: =IFERROR(__xludf.DUMMYFUNCTION("""COMPUTED_VALUE"""),"") | R11: 3A0A52 | T11: A73945 | V11: A73945
B12: =IFERROR(__xludf.DUMMYFUNCTION("""COMPUTED_VALUE"""),"WM-MA-PE-1A") -> WM-MA-PE-1A | C12: White Knight | E12: =IFERROR(__xludf.DUMMYFUNCTION("""COMPUTED_VALUE"""),"") | F12: 7 | K12: 10 | M12: 10 | N12: =IFERROR(__xludf.DUMMYFUNCTION("""COMPUTED_VALUE"""),"") | P12: Sold | R12: C7E314 | T12: 075DBF | V12: 075DBF
A13: 45873 | B13: =IFERROR(__xludf.DUMMYFUNCTION("""COMPUTED_VALUE"""),"TLC-PH-CS-1A") -> TLC-PH-CS-1A | E13: =IFERROR(__xludf.DUMMYFUNCTION("""COMPUTED_VALUE"""),"") | F13: 0 | N13: =IFERROR(__xludf.DUMMYFUNCTION("""COMPUTED_VALUE"""),"") | P13: Damaged | R13: AA4996 | T13: CE10E3 | V13: CE10E3
A14: 45874 | B14: =IFERROR(__xludf.DUMMYFUNCTION("""COMPUTED_VALUE"""),"TAG-AO-DR-1A") -> TAG-AO-DR-1A | E14: =IFERROR(__xludf.DUMMYFUNCTION("""COMPUTED_VALUE"""),"ST-PO-6-NU-1") -> ST-PO-6-NU-1 | F14: 0 | N14: =IFERROR(__xludf.DUMMYFUNCTION("""COMPUTED_VALUE"""),"") | R14: B16039 | T14: F68623 | V14: F68623
A15: 45880 | B15: =IFERROR(__xludf.DUMMYFUNCTION("""COMPUTED_VALUE"""),"FMY-PH-GC-1A") -> FMY-PH-GC-1A | E15: =IFERROR(__xludf.DUMMYFUNCTION("""COMPUTED_VALUE"""),"NR-PO-8-BP-1") -> NR-PO-8-BP-1 | F15: 16.99 | N15: =IFERROR(__xludf.DUMMYFUNCTION("""COMPUTED_VALUE"""),"") | R15: 4546BE | T15: 118596 | V15: 118596
A16: 45880 | B16: =IFERROR(__xludf.DUMMYFUNCTION("""COMPUTED_VALUE"""),"FMY-AL-RSD-1A") -> FMY-AL-RSD-1A | E16: =IFERROR(__xludf.DUMMYFUNCTION("""COMPUTED_VALUE"""),"") | F16: 10.99 | N16: =IFERROR(__xludf.DUMMYFUNCTION("""COMPUTED_VALUE"""),"") | R16: 5DCD93 | T16: EEA2A8 | V16: EEA2A8
A17: 45880 | B17: =IFERROR(__xludf.DUMMYFUNCTION("""COMPUTED_VALUE"""),"FMY-AL-GVF-1A") -> FMY-AL-GVF-1A | E17: =IFERROR(__xludf.DUMMYFUNCTION("""COMPUTED_VALUE"""),"DT-PO-3-GL-1") -> DT-PO-3-GL-1 | F17: 10.99 | N17: =IFERROR(__xludf.DUMMYFUNCTION("""COMPUTED_VALUE"""),"") | R17: 66B4DB | T17: CEB6EA | V17: CEB6EA
A18: 45880 | B18: =IFERROR(__xludf.DUMMYFUNCTION("""COMPUTED_VALUE"""),"FMY-MA-DE-1A") -> FMY-MA-DE-1A | E18: =IFERROR(__xludf.DUMMYFUNCTION("""COMPUTED_VALUE"""),"WO-PO-6-WH-1") -> WO-PO-6-WH-1 | F18: 2.198 | N18: =IFERROR(__xludf.DUMMYFUNCTION("""COMPUTED_VALUE"""),"") | R18: D764EE | S18: 25 | T18: 9652DA | V18: 9652DA
A19: 45880 | B19: =IFERROR(__xludf.DUMMYFUNCTION("""COMPUTED_VALUE"""),"FMY-MA-DE-1A-2") -> FMY-MA-DE-1A-2 | E19: =IFERROR(__xludf.DUMMYFUNCTION("""COMPUTED_VALUE"""),"ST-PO-6-NU-1") -> ST-PO-6-NU-1 | F19: 9.995 | N19: =IFERROR(__xludf.DUMMYFUNCTION("""COMPUTED_VALUE"""),"") | R19: BA6B4C | T19: 64F929 | V19: 64F929
A20: 45880 | B20: =IFERROR(__xludf.DUMMYFUNCTION("""COMPUTED_VALUE"""),"TLC-SC-SS-1A") -> TLC-SC-SS-1A | E20: =IFERROR(__xludf.DUMMYFUNCTION("""COMPUTED_VALUE"""),"TE-PO-4-MU-1") -> TE-PO-4-MU-1 | F20: 1 | N20: =IFERROR(__xludf.DUMMYFUNCTION("""COMPUTED_VALUE"""),"") | P20: Not for Sale | R20: 1DD88F | T20: 339469 | V20: 339469
A21: 45870 | B21: =IFERROR(__xludf.DUMMYFUNCTION("""COMPUTED_VALUE"""),"MMP-MA-AD-1A") -> MMP-MA-AD-1A | E21: =IFERROR(__xludf.DUMMYFUNCTION("""COMPUTED_VALUE"""),"NR-PO-3-BP-1") -> NR-PO-3-BP-1 | F21: 1 | N21: =IFERROR(__xludf.DUMMYFUNCTION("""COMPUTED_VALUE"""),"") | P21: Not for Sale | R21: D78BB8 | T21: 6D8F4B | V21: 6D8F4B
A22: 45866 | B22: =IFERROR(__xludf.DUMMYFUNCTION("""COMPUTED_VALUE"""),"OLN-MA-AD-1A") -> OLN-MA-AD-1A | E22: =IFERROR(__xludf.DUMMYFUNCTION("""COMPUTED_VALUE"""),"NR-PO-3-BP-1") -> NR-PO-3-BP-1 | F22: 3.66 | N22: =IFERROR(__xludf.DUMMYFUNCTION("""COMPUTED_VALUE"""),"") | P22: Not for Sale | R22: DB15AC | T22: 15A7A1 | V22: 15A7A1
A23: 45866 | B23: =IFERROR(__xludf.DUMMYFUNCTION("""COMPUTED_VALUE"""),"OLN-PH-WP-1A") -> OLN-PH-WP-1A | E23: =IFERROR(__xludf.DUMMYFUNCTION("""COMPUTED_VALUE"""),"ST-PO-3-NU-1") -> ST-PO-3-NU-1 | F23: 3.66 | N23: =IFERROR(__xludf.DUMMYFUNCTION("""COMPUTED_VALUE"""),"") | P23: Not for Sale | R23: 1A5668 | T23: 0EC505 | V23: 0EC505
A24: 45866 | B24: =IFERROR(__xludf.DUMMYFUNCTION("""COMPUTED_VALUE"""),"OLN-ALT-PT-1A") -> OLN-ALT-PT-1A | E24: =IFERROR(__xludf.DUMMYFUNCTION("""COMPUTED_VALUE"""),"TO-PO-4-MU-1") -> TO-PO-4-MU-1 | F24: 9.99 | N24: =IFERROR(__xludf.DUMMYFUNCTION("""COMPUTED_VALUE"""),"") | P24: Not for Sale | R24: 30FC62 | T24: 33162E | V24: 33162E
A25: 45866 | B25: =IFERROR(__xludf.DUMMYFUNCTION("""COMPUTED_VALUE"""),"OLN-FI-RF-1A") -> OLN-FI-RF-1A | E25: =IFERROR(__xludf.DUMMYFUNCTION("""COMPUTED_VALUE"""),"") | F25: 3.66 | N25: =IFERROR(__xludf.DUMMYFUNCTION("""COMPUTED_VALUE"""),"") | P25: Not for Sale | R25: C4919B | T25: FF7881 | V25: FF7881
A26: 45902 | B26: =IFERROR(__xludf.DUMMYFUNCTION("""COMPUTED_VALUE"""),"OLN-PH-STS-1A") -> OLN-PH-STS-1A | E26: =IFERROR(__xludf.DUMMYFUNCTION("""COMPUTED_VALUE"""),"WO-PO-6-WH-1") -> WO-PO-6-WH-1 | F26: 52 | N26: =IFERROR(__xludf.DUMMYFUNCTION("""COMPUTED_VALUE"""),"") | P26: Not for Sale | R26: DD2EF3 | T26: 39BA9D | V26: 39BA9D
A27: 45902 | B27: =IFERROR(__xludf.DUMMYFUNCTION("""COMPUTED_VALUE"""),"OLN-PH-SD-1A") -> OLN-PH-SD-1A | E27: =IFERROR(__xludf.DUMMYFUNCTION("""COMPUTED_VALUE"""),"AN-PO-3-MU-1") -> AN-PO-3-MU-1 | F27: 16 | N27: =IFERROR(__xludf.DUMMYFUNCTION("""COMPUTED_VALUE"""),"") | P27: Not for Sale | R27: A09A6D | T27: CD2664 | V27: CD2664
A28: 45871 | B28: =IFERROR(__xludf.DUMMYFUNCTION("""COMPUTED_VALUE"""),"AR-PH-WP-1A") -> AR-PH-WP-1A | E28: =IFERROR(__xludf.DUMMYFUNCTION("""COMPUTED_VALUE"""),"TE-PO-4-MU-1") -> TE-PO-4-MU-1 | F28: 20.4 | N28: =IFERROR(__xludf.DUMMYFUNCTION("""COMPUTED_VALUE"""),"") | P28: Not for Sale | R28: F323DF | T28: 357C92 | V28: 357C92
A29: 45871 | B29: =IFERROR(__xludf.DUMMYFUNCTION("""COMPUTED_VALUE"""),"AR-AL-LM-1A") -> AR-AL-LM-1A | C29: White Princess | E29: =IFERROR(__xludf.DUMMYFUNCTION("""COMPUTED_VALUE"""),"MA-PO-3-SW-1") -> MA-PO-3-SW-1 | F29: 18.9 | N29: =IFERROR(__xludf.DUMMYFUNCTION("""COMPUTED_VALUE"""),"") | P29: Not for Sale | R29: D4D950 | T29: F8821D | V29: F8821D
A30: 45877 | B30: =IFERROR(__xludf.DUMMYFUNCTION("""COMPUTED_VALUE"""),"ZB-SE-HA-1A") -> ZB-SE-HA-1A | C30: Longiloba Mint | E30: =IFERROR(__xludf.DUMMYFUNCTION("""COMPUTED_VALUE"""),"ST-PO-6-NU-1") -> ST-PO-6-NU-1 | F30: 0 | N30: =IFERROR(__xludf.DUMMYFUNCTION("""COMPUTED_VALUE"""),"") | P30: Not for Sale | R30: D8F201 | T30: 695EB4 | V30: 695EB4
A31: 45878 | B31: =IFERROR(__xludf.DUMMYFUNCTION("""COMPUTED_VALUE"""),"IST-PH-PP-1A") -> IST-PH-PP-1A | E31: =IFERROR(__xludf.DUMMYFUNCTION("""COMPUTED_VALUE"""),"MU-PO-4-WH-1") -> MU-PO-4-WH-1 | F31: 10.8 | N31: =IFERROR(__xludf.DUMMYFUNCTION("""COMPUTED_VALUE"""),"") | R31: B46EF4 | T31: 5ECFB2 | V31: 5ECFB2
A32: 45878 | B32: =IFERROR(__xludf.DUMMYFUNCTION("""COMPUTED_VALUE"""),"IST-PH-GCN-1A") -> IST-PH-GCN-1A | E32: =IFERROR(__xludf.DUMMYFUNCTION("""COMPUTED_VALUE"""),"TE-PO-4-MU-1") -> TE-PO-4-MU-1 | F32: 25 | N32: =IFERROR(__xludf.DUMMYFUNCTION("""COMPUTED_VALUE"""),"") | P32: Not for Sale | R32: F3374E | T32: 6AB8A0 | V32: 6AB8A0
A33: 45882 | B33: =IFERROR(__xludf.DUMMYFUNCTION("""COMPUTED_VALUE"""),"TGG-HO-GF-1A") -> TGG-HO-GF-1A | E33: =IFERROR(__xludf.DUMMYFUNCTION("""COMPUTED_VALUE"""),"NR-PO-3-TBP-1") -> NR-PO-3-TBP-1 | F33: 0 | N33: =IFERROR(__xludf.DUMMYFUNCTION("""COMPUTED_VALUE"""),"") | P33: Not for Sale | R33: 1E3D42 | T33: 77D375 | V33: 77D375
A34: 45882 | B34: =IFERROR(__xludf.DUMMYFUNCTION("""COMPUTED_VALUE"""),"TGG-HO-PU-1A") -> TGG-HO-PU-1A | E34: =IFERROR(__xludf.DUMMYFUNCTION("""COMPUTED_VALUE"""),"NR-PO-3-BP-1") -> NR-PO-3-BP-1 | F34: 5 | N34: =IFERROR(__xludf.DUMMYFUNCTION("""COMPUTED_VALUE"""),"") | P34: Not for Sale | R34: C41DCD | T34: 014884 | V34: 014884
A35: 45886 | B35: =IFERROR(__xludf.DUMMYFUNCTION("""COMPUTED_VALUE"""),"FM-MA-DE-1A") -> FM-MA-DE-1A | E35: =IFERROR(__xludf.DUMMYFUNCTION("""COMPUTED_VALUE"""),"") | F35: 5 | N35: =IFERROR(__xludf.DUMMYFUNCTION("""COMPUTED_VALUE"""),"") | P35: Not for Sale | R35: BC6E95 | S35: 0 | T35: 347F64 | V35: 347F64
A36: 45882 | B36: =IFERROR(__xludf.DUMMYFUNCTION("""COMPUTED_VALUE"""),"AM-PH-PP-1A") -> AM-PH-PP-1A | E36: =IFERROR(__xludf.DUMMYFUNCTION("""COMPUTED_VALUE"""),"MU-PO-4-WH-1") -> MU-PO-4-WH-1 | F36: 10.25 | N36: =IFERROR(__xludf.DUMMYFUNCTION("""COMPUTED_VALUE"""),"") | R36: EABB58 | T36: 956D2B | V36: 956D2B
A37: 45882 | B37: =IFERROR(__xludf.DUMMYFUNCTION("""COMPUTED_VALUE"""),"AM-PH-WW-1A") -> AM-PH-WW-1A | C37: Pink Princess | E37: =IFERROR(__xludf.DUMMYFUNCTION("""COMPUTED_VALUE"""),"MU-PO-4-WH-1") -> MU-PO-4-WH-1 | F37: 10.25 | N37: =IFERROR(__xludf.DUMMYFUNCTION("""COMPUTED_VALUE"""),"") | R37: A7877B | T37: B8CD1C | V37: B8CD1C
A38: 45882 | B38: =IFERROR(__xludf.DUMMYFUNCTION("""COMPUTED_VALUE"""),"AM-PH-GL-1A") -> AM-PH-GL-1A | C38: White Wizard | E38: =IFERROR(__xludf.DUMMYFUNCTION("""COMPUTED_VALUE"""),"ZO-PO-4-WL-1") -> ZO-PO-4-WL-1 | F38: 10.25 | N38: =IFERROR(__xludf.DUMMYFUNCTION("""COMPUTED_VALUE"""),"") | R38: 367351 | T38: F99298 | V38: F99298
A39: 45882 | B39: =IFERROR(__xludf.DUMMYFUNCTION("""COMPUTED_VALUE"""),"AM-PH-BI-1A") -> AM-PH-BI-1A | C39: Gloriosum | E39: =IFERROR(__xludf.DUMMYFUNCTION("""COMPUTED_VALUE"""),"ZO-PO-4-WL-1") -> ZO-PO-4-WL-1 | F39: 3.4166667 | N39: =IFERROR(__xludf.DUMMYFUNCTION("""COMPUTED_VALUE"""),"") | R39: EBE164 | T39: EEAE97 | V39: EEAE97
A40: 45881 | B40: =IFERROR(__xludf.DUMMYFUNCTION("""COMPUTED_VALUE"""),"TGOPS-PH-PPM-1A") -> TGOPS-PH-PPM-1A | C40: Birkin | E40: =IFERROR(__xludf.DUMMYFUNCTION("""COMPUTED_VALUE"""),"TE-PO-4-MU-1") -> TE-PO-4-MU-1 | F40: 16.19 | L40: Donation | N40: =IFERROR(__xludf.DUMMYFUNCTION("""COMPUTED_VALUE"""),"") | P40: Available | R40: 3EF9AE | S40: 26.99 | T40: 59E874 | V40: 59E874
A41: 45881 | B41: =IFERROR(__xludf.DUMMYFUNCTION("""COMPUTED_VALUE"""),"TGOPS-PH-PPM-1A-2") -> TGOPS-PH-PPM-1A-2 | E41: =IFERROR(__xludf.DUMMYFUNCTION("""COMPUTED_VALUE"""),"TE-PO-4-MU-1") -> TE-PO-4-MU-1 | F41: 16.19 | K41: 10 | M41: 10 | N41: =IFERROR(__xludf.DUMMYFUNCTION("""COMPUTED_VALUE"""),"") | P41: Sold | R41: 95E24C | S41: 26.99 | T41: A7EF2E | V41: A7EF2E
A42: 45881 | B42: =IFERROR(__xludf.DUMMYFUNCTION("""COMPUTED_VALUE"""),"TGOPS-PH-PPM-1A-3") -> TGOPS-PH-PPM-1A-3 | E42: =IFERROR(__xludf.DUMMYFUNCTION("""COMPUTED_VALUE"""),"TE-PO-4-MU-1") -> TE-PO-4-MU-1 | F42: 16.19 | K42: 20 | M42: 20 | N42: =IFERROR(__xludf.DUMMYFUNCTION("""COMPUTED_VALUE"""),"") | P42: Sold | R42: D83913 | S42: 26.99 | T42: E71AFB | V42: E71AFB
A43: 45881 | B43: =IFERROR(__xludf.DUMMYFUNCTION("""COMPUTED_VALUE"""),"TGOPS-PH-POO-1A") -> TGOPS-PH-POO-1A | E43: =IFERROR(__xludf.DUMMYFUNCTION("""COMPUTED_VALUE"""),"TE-PO-4-MU-1") -> TE-PO-4-MU-1 | F43: 7.79 | N43: =IFERROR(__xludf.DUMMYFUNCTION("""COMPUTED_VALUE"""),"") | R43: F6DAF1 | S43: 12.99 | T43: 048185 | V43: 048185
A44: 45881 | B44: =IFERROR(__xludf.DUMMYFUNCTION("""COMPUTED_VALUE"""),"TGOPS-PH-POO-1A-2") -> TGOPS-PH-POO-1A-2 | E44: =IFERROR(__xludf.DUMMYFUNCTION("""COMPUTED_VALUE"""),"") | F44: 7.79 | K44: 10 | M44: 10 | N44: =IFERROR(__xludf.DUMMYFUNCTION("""COMPUTED_VALUE"""),"") | P44: Sold | R44: D2855E | S44: 12.99 | T44: 0B3C21 | V44: 0B3C21
A45: 45881 | B45: =IFERROR(__xludf.DUMMYFUNCTION("""COMPUTED_VALUE"""),"TGOPS-PH-POO-1A-3") -> TGOPS-PH-POO-1A-3 | E45: =IFERROR(__xludf.DUMMYFUNCTION("""COMPUTED_VALUE"""),"TE-PO-4-MU-1") -> TE-PO-4-MU-1 | F45: 7.79 | L45: 0 | N45: =IFERROR(__xludf.DUMMYFUNCTION("""COMPUTED_VALUE"""),"") | P45: Available | R45: 746666 | S45: 12.99 | T45: 614E69 | V45: 614E69
A46: 45881 | B46: =IFERROR(__xludf.DUMMYFUNCTION("""COMPUTED_VALUE"""),"TGOPS-PH-WW-1A") -> TGOPS-PH-WW-1A | E46: =IFERROR(__xludf.DUMMYFUNCTION("""COMPUTED_VALUE"""),"WO-PO-6-WH-1") -> WO-PO-6-WH-1 | F46: 2.1983333 | N46: =IFERROR(__xludf.DUMMYFUNCTION("""COMPUTED_VALUE"""),"") | R46: FDCDBC | T46: 5C9418 | V46: 5C9418
A47: 45881 | B47: =IFERROR(__xludf.DUMMYFUNCTION("""COMPUTED_VALUE"""),"TGOPS-PH-WW-1A-2") -> TGOPS-PH-WW-1A-2 | E47: =IFERROR(__xludf.DUMMYFUNCTION("""COMPUTED_VALUE"""),"TE-PO-4-MU-1") -> TE-PO-4-MU-1 | F47: 3.2975 | N47: =IFERROR(__xludf.DUMMYFUNCTION("""COMPUTED_VALUE"""),"") | R47: B86EBE | T47: AC63C4 | V47: AC63C4
A48: 45881 | B48: =IFERROR(__xludf.DUMMYFUNCTION("""COMPUTED_VALUE"""),"TGOPS-PH-WW-1A-3") -> TGOPS-PH-WW-1A-3 | E48: =IFERROR(__xludf.DUMMYFUNCTION("""COMPUTED_VALUE"""),"WO-PO-6-WH-1") -> WO-PO-6-WH-1 | F48: 4.3966667 | N48: =IFERROR(__xludf.DUMMYFUNCTION("""COMPUTED_VALUE"""),"") | R48: B248B2 | T48: 1DED83 | V48: 1DED83
A49: 45884 | B49: =IFERROR(__xludf.DUMMYFUNCTION("""COMPUTED_VALUE"""),"BWH-PH-MO-1A") -> BWH-PH-MO-1A | E49: =IFERROR(__xludf.DUMMYFUNCTION("""COMPUTED_VALUE"""),"GA-PO-6-MU-1") -> GA-PO-6-MU-1 | F49: 6 | N49: =IFERROR(__xludf.DUMMYFUNCTION("""COMPUTED_VALUE"""),"") | R49: 865761 | S49: 12.99 | T49: 8DA21B | V49: 8DA21B
A50: 45884 | B50: =IFERROR(__xludf.DUMMYFUNCTION("""COMPUTED_VALUE"""),"BWH-PH-MO-1A-2") -> BWH-PH-MO-1A-2 | E50: =IFERROR(__xludf.DUMMYFUNCTION("""COMPUTED_VALUE"""),"TE-PO-4-MU-1") -> TE-PO-4-MU-1 | F50: 6 | N50: =IFERROR(__xludf.DUMMYFUNCTION("""COMPUTED_VALUE"""),"") | P50: Available | R50: 3475AD | S50: 12.99 | T50: 9062E5 | V50: 9062E5
A51: 45884 | B51: =IFERROR(__xludf.DUMMYFUNCTION("""COMPUTED_VALUE"""),"BWH-PH-MO-1A-3") -> BWH-PH-MO-1A-3 | E51: =IFERROR(__xludf.DUMMYFUNCTION("""COMPUTED_VALUE"""),"TE-PO-4-MU-1") -> TE-PO-4-MU-1 | F51: 6 | N51: =IFERROR(__xludf.DUMMYFUNCTION("""COMPUTED_VALUE"""),"") | P51: Not for Sale | R51: 87BA03 | S51: 12.99 | T51: 01FA5C | V51: 01FA5C
A52: 45884 | B52: =IFERROR(__xludf.DUMMYFUNCTION("""COMPUTED_VALUE"""),"BWH-PH-MO-1A-4") -> BWH-PH-MO-1A-4 | E52: =IFERROR(__xludf.DUMMYFUNCTION("""COMPUTED_VALUE"""),"TE-PO-4-MU-1") -> TE-PO-4-MU-1 | F52: 6 | N52: =IFERROR(__xludf.DUMMYFUNCTION("""COMPUTED_VALUE"""),"") | P52: Available | R52: 9D266F | S52: 12.99 | T52: 1CF82D | V52: 1CF82D
A53: 45884 | B53: =IFERROR(__xludf.DUMMYFUNCTION("""COMPUTED_VALUE"""),"BWH-PH-MO-1A-5") -> BWH-PH-MO-1A-5 | E53: =IFERROR(__xludf.DUMMYFUNCTION("""COMPUTED_VALUE"""),"GA-PO-6-MU-1") -> GA-PO-6-MU-1 | F53: 6 | N53: =IFERROR(__xludf.DUMMYFUNCTION("""COMPUTED_VALUE"""),"") | P53: Available | R53: 11DB77 | S53: 12.99 | T53: 6A34D7 | V53: 6A34D7
A54: 45884 | B54: =IFERROR(__xludf.DUMMYFUNCTION("""COMPUTED_VALUE"""),"BWH-PH-RAPK-1A") -> BWH-PH-RAPK-1A | E54: =IFERROR(__xludf.DUMMYFUNCTION("""COMPUTED_VALUE"""),"EL-PO-4.3-CM-1") -> EL-PO-4.3-CM-1 | F54: 10.2 | K54: 30 | M54: 30 | N54: =IFERROR(__xludf.DUMMYFUNCTION("""COMPUTED_VALUE"""),"") | P54: Sold | R54: DA2B69 | S54: 24.99 | T54: F5A463 | V54: F5A463
A55: 45884 | B55: =IFERROR(__xludf.DUMMYFUNCTION("""COMPUTED_VALUE"""),"BWH-PH-RAPK-1A-2") -> BWH-PH-RAPK-1A-2 | C55: Red Anderson Pink Knight | E55: =IFERROR(__xludf.DUMMYFUNCTION("""COMPUTED_VALUE"""),"NR-PO-8-BP-1") -> NR-PO-8-BP-1 | F55: 10.2 | N55: =IFERROR(__xludf.DUMMYFUNCTION("""COMPUTED_VALUE"""),"") | P55: Not for Sale | R55: DD7D9F | S55: 24.99 | T55: 7055A9 | V55: 7055A9
A56: 45884 | B56: =IFERROR(__xludf.DUMMYFUNCTION("""COMPUTED_VALUE"""),"BWH-PH-RAPK-1A-3") -> BWH-PH-RAPK-1A-3 | C56: Red Anderson Pink Knight | E56: =IFERROR(__xludf.DUMMYFUNCTION("""COMPUTED_VALUE"""),"GA-PO-6-MU-1") -> GA-PO-6-MU-1 | F56: 10.2 | N56: =IFERROR(__xludf.DUMMYFUNCTION("""COMPUTED_VALUE"""),"") | P56: Available | R56: 28945C | S56: 24.99 | T56: 1B1CDA | V56: 1B1CDA
A57: 45884 | B57: =IFERROR(__xludf.DUMMYFUNCTION("""COMPUTED_VALUE"""),"BWH-PH-RAPK-1A-4") -> BWH-PH-RAPK-1A-4 | E57: =IFERROR(__xludf.DUMMYFUNCTION("""COMPUTED_VALUE"""),"GA-PO-6-MU-1") -> GA-PO-6-MU-1 | F57: 10.2 | N57: =IFERROR(__xludf.DUMMYFUNCTION("""COMPUTED_VALUE"""),"") | R57: 29B762 | S57: 24.99 | T57: C74204 | V57: C74204
A58: 45884 | B58: =IFERROR(__xludf.DUMMYFUNCTION("""COMPUTED_VALUE"""),"BWH-PH-RAPK-1A-5") -> BWH-PH-RAPK-1A-5 | E58: =IFERROR(__xludf.DUMMYFUNCTION("""COMPUTED_VALUE"""),"GA-PO-6-MU-1") -> GA-PO-6-MU-1 | F58: 10.2 | N58: =IFERROR(__xludf.DUMMYFUNCTION("""COMPUTED_VALUE"""),"") | R58: B756B2 | S58: 24.99 | T58: 27F46E | V58: 27F46E
A59: 45884 | B59: =IFERROR(__xludf.DUMMYFUNCTION("""COMPUTED_VALUE"""),"BWH-PO-PAJ-1A") -> BWH-PO-PAJ-1A | E59: =IFERROR(__xludf.DUMMYFUNCTION("""COMPUTED_VALUE"""),"WO-PO-6-WH-1") -> WO-PO-6-WH-1 | F59: 7.8 | N59: =IFERROR(__xludf.DUMMYFUNCTION("""COMPUTED_VALUE"""),"") | R59: 347F1B | S59: 16.99 | T59: 9A8D0B | V59: 9A8D0B
A60: 45884 | B60: =IFERROR(__xludf.DUMMYFUNCTION("""COMPUTED_VALUE"""),"BWH-PO-PAJ-1A-2") -> BWH-PO-PAJ-1A-2 | E60: =IFERROR(__xludf.DUMMYFUNCTION("""COMPUTED_VALUE"""),"") | F60: 7.8 | N60: =IFERROR(__xludf.DUMMYFUNCTION("""COMPUTED_VALUE"""),"") | R60: C770F5 | S60: 16.99 | T60: 1FB6A6 | V60: 1FB6A6
A61: 45884 | B61: =IFERROR(__xludf.DUMMYFUNCTION("""COMPUTED_VALUE"""),"BWH-PO-PAJ-1A-3") -> BWH-PO-PAJ-1A-3 | E61: =IFERROR(__xludf.DUMMYFUNCTION("""COMPUTED_VALUE"""),"WO-PO-6-MU-1") -> WO-PO-6-MU-1 | F61: 7.8 | K61: 0 | M61: 0 | N61: =IFERROR(__xludf.DUMMYFUNCTION("""COMPUTED_VALUE"""),"") | P61: Sold | R61: F0D337 | S61: 16.99 | T61: 6F8A35 | V61: 6F8A35
A62: 45884 | B62: =IFERROR(__xludf.DUMMYFUNCTION("""COMPUTED_VALUE"""),"BWH-PO-PAJ-1A-4") -> BWH-PO-PAJ-1A-4 | E62: =IFERROR(__xludf.DUMMYFUNCTION("""COMPUTED_VALUE"""),"TE-PO-4-MU-1") -> TE-PO-4-MU-1 | F62: 1.95 | K62: 12 | M62: 12 | N62: =IFERROR(__xludf.DUMMYFUNCTION("""COMPUTED_VALUE"""),"") | P62: Sold | R62: E5EA44 | S62: 16.99 | T62: 22CFD8 | V62: 22CFD8
A63: 45884 | B63: =IFERROR(__xludf.DUMMYFUNCTION("""COMPUTED_VALUE"""),"BWH-PO-PAJ-1A-5") -> BWH-PO-PAJ-1A-5 | E63: =IFERROR(__xludf.DUMMYFUNCTION("""COMPUTED_VALUE"""),"GA-PO-6-MU-1") -> GA-PO-6-MU-1 | F63: 7.8 | K63: 12 | M63: 12 | N63: =IFERROR(__xludf.DUMMYFUNCTION("""COMPUTED_VALUE"""),"") | P63: Sold | R63: DAE397 | S63: 16.99 | T63: 582E6B | V63: 582E6B
A64: 45884 | B64: =IFERROR(__xludf.DUMMYFUNCTION("""COMPUTED_VALUE"""),"BWH-SYN-PS-1A") -> BWH-SYN-PS-1A | E64: =IFERROR(__xludf.DUMMYFUNCTION("""COMPUTED_VALUE"""),"TE-PO-4-MU-1") -> TE-PO-4-MU-1 | F64: 9 | N64: =IFERROR(__xludf.DUMMYFUNCTION("""COMPUTED_VALUE"""),"") | R64: DAB222 | S64: 19.99 | T64: FB9090 | V64: FB9090
A65: 45884 | B65: =IFERROR(__xludf.DUMMYFUNCTION("""COMPUTED_VALUE"""),"BWH-SYN-PS-1A-2") -> BWH-SYN-PS-1A-2 | E65: =IFERROR(__xludf.DUMMYFUNCTION("""COMPUTED_VALUE"""),"TE-PO-4-MU-1") -> TE-PO-4-MU-1 | F65: 9 | N65: =IFERROR(__xludf.DUMMYFUNCTION("""COMPUTED_VALUE"""),"") | R65: C20928 | S65: 19.99 | T65: 3B2856 | V65: 3B2856
A66: 45884 | B66: =IFERROR(__xludf.DUMMYFUNCTION("""COMPUTED_VALUE"""),"BWH-SYN-PS-1A-3") -> BWH-SYN-PS-1A-3 | E66: =IFERROR(__xludf.DUMMYFUNCTION("""COMPUTED_VALUE"""),"TE-PO-4-MU-1") -> TE-PO-4-MU-1 | F66: 9 | K66: 10 | M66: 10 | N66: =IFERROR(__xludf.DUMMYFUNCTION("""COMPUTED_VALUE"""),"") | P66: Sold | R66: 3D8402 | S66: 19.99 | T66: 3EABDC | V66: 3EABDC
A67: 45884 | B67: =IFERROR(__xludf.DUMMYFUNCTION("""COMPUTED_VALUE"""),"BWH-SYN-PS-1A-4") -> BWH-SYN-PS-1A-4 | E67: =IFERROR(__xludf.DUMMYFUNCTION("""COMPUTED_VALUE"""),"TE-PO-4-MU-1") -> TE-PO-4-MU-1 | F67: 9 | N67: =IFERROR(__xludf.DUMMYFUNCTION("""COMPUTED_VALUE"""),"") | R67: 5A338D | S67: 19.99 | T67: DE2B8E | V67: DE2B8E
A68: 45884 | B68: =IFERROR(__xludf.DUMMYFUNCTION("""COMPUTED_VALUE"""),"BWH-SYN-PS-1A-5") -> BWH-SYN-PS-1A-5 | E68: =IFERROR(__xludf.DUMMYFUNCTION("""COMPUTED_VALUE"""),"TE-PO-4-MU-1") -> TE-PO-4-MU-1 | F68: 9 | K68: 10 | M68: 10 | N68: =IFERROR(__xludf.DUMMYFUNCTION("""COMPUTED_VALUE"""),"") | P68: Sold | R68: 1566D4 | S68: 19.99 | T68: 477552 | V68: 477552
A69: 45885 | B69: =IFERROR(__xludf.DUMMYFUNCTION("""COMPUTED_VALUE"""),"FPH-PH-GCN-1A") -> FPH-PH-GCN-1A | E69: =IFERROR(__xludf.DUMMYFUNCTION("""COMPUTED_VALUE"""),"GA-PO-6-MU-1") -> GA-PO-6-MU-1 | F69: 40 | N69: =IFERROR(__xludf.DUMMYFUNCTION("""COMPUTED_VALUE"""),"") | R69: 41FAF6 | T69: 86F1A4 | V69: 86F1A4
A70: 45885 | B70: =IFERROR(__xludf.DUMMYFUNCTION("""COMPUTED_VALUE"""),"BTPG-HO-KP-1A") -> BTPG-HO-KP-1A | E70: =IFERROR(__xludf.DUMMYFUNCTION("""COMPUTED_VALUE"""),"TE-PO-4-MU-1") -> TE-PO-4-MU-1 | F70: 6.0833333 | N70: =IFERROR(__xludf.DUMMYFUNCTION("""COMPUTED_VALUE"""),"") | P70: Not for Sale | R70: 5FC77C | T70: D71CD7 | V70: D71CD7
A71: 45902 | B71: =IFERROR(__xludf.DUMMYFUNCTION("""COMPUTED_VALUE"""),"BPF-CE-SOH-1A") -> BPF-CE-SOH-1A | C71: Krimson Princess | E71: =IFERROR(__xludf.DUMMYFUNCTION("""COMPUTED_VALUE"""),"") | F71: 5.84 | K71: 10 | M71: 10 | N71: =IFERROR(__xludf.DUMMYFUNCTION("""COMPUTED_VALUE"""),"") | P71: Sold | R71: 8EB23B | S71: 8.99 | T71: D82F34 | V71: D82F34
A72: 45902 | B72: =IFERROR(__xludf.DUMMYFUNCTION("""COMPUTED_VALUE"""),"BPF-CE-SOH-1A-2") -> BPF-CE-SOH-1A-2 | C72: String of Hearts | E72: =IFERROR(__xludf.DUMMYFUNCTION("""COMPUTED_VALUE"""),"") | F72: 5.84 | K72: 10 | M72: 10 | N72: =IFERROR(__xludf.DUMMYFUNCTION("""COMPUTED_VALUE"""),"") | P72: Sold | R72: 4EE16A | S72: 8.99 | T72: 0B738B | V72: 0B738B
A73: 45902 | B73: =IFERROR(__xludf.DUMMYFUNCTION("""COMPUTED_VALUE"""),"BPF-CE-SOH-1A-3") -> BPF-CE-SOH-1A-3 | C73: String of Hearts | E73: =IFERROR(__xludf.DUMMYFUNCTION("""COMPUTED_VALUE"""),"") | F73: 5.84 | N73: =IFERROR(__xludf.DUMMYFUNCTION("""COMPUTED_VALUE"""),"") | R73: 676712 | S73: 8.99 | T73: E8EA78 | V73: E8EA78
A74: 45902 | B74: =IFERROR(__xludf.DUMMYFUNCTION("""COMPUTED_VALUE"""),"BPF-CE-SOH-1A-4") -> BPF-CE-SOH-1A-4 | C74: String of Hearts | E74: =IFERROR(__xludf.DUMMYFUNCTION("""COMPUTED_VALUE"""),"") | F74: 5.84 | N74: =IFERROR(__xludf.DUMMYFUNCTION("""COMPUTED_VALUE"""),"") | R74: EB46AC | S74: 8.99 | T74: CEA65E | V74: CEA65E
A75: 45902 | B75: =IFERROR(__xludf.DUMMYFUNCTION("""COMPUTED_VALUE"""),"BPF-CE-SOH-1A-5") -> BPF-CE-SOH-1A-5 | C75: String of Hearts | E75: =IFERROR(__xludf.DUMMYFUNCTION("""COMPUTED_VALUE"""),"") | F75: 5.84 | K75: 10 | M75: 10 | N75: =IFERROR(__xludf.DUMMYFUNCTION("""COMPUTED_VALUE"""),"") | P75: Sold | R75: 4D2FA7 | S75: 8.99 | T75: 09840D | V75: 09840D
A76: 45902 | B76: =IFERROR(__xludf.DUMMYFUNCTION("""COMPUTED_VALUE"""),"BPF-SE-SOP-1A") -> BPF-SE-SOP-1A | C76: String of Hearts | E76: =IFERROR(__xludf.DUMMYFUNCTION("""COMPUTED_VALUE"""),"") | F76: 4.71 | K76: 10 | M76: 10 | N76: =IFERROR(__xludf.DUMMYFUNCTION("""COMPUTED_VALUE"""),"") | P76: Sold | R76: 7EBCBB | S76: 7.25 | T76: B31032 | V76: B31032
A77: 45902 | B77: =IFERROR(__xludf.DUMMYFUNCTION("""COMPUTED_VALUE"""),"BPF-SE-SOP-1A-2") -> BPF-SE-SOP-1A-2 | C77: String of Pearls | E77: =IFERROR(__xludf.DUMMYFUNCTION("""COMPUTED_VALUE"""),"") | F77: 4.71 | N77: =IFERROR(__xludf.DUMMYFUNCTION("""COMPUTED_VALUE"""),"") | P77: Damaged | R77: 48B232 | S77: 7.25 | T77: C199E2 | V77: C199E2
A78: 45902 | B78: =IFERROR(__xludf.DUMMYFUNCTION("""COMPUTED_VALUE"""),"BPF-SE-SOP-1A-3") -> BPF-SE-SOP-1A-3 | C78: String of Pearls | E78: =IFERROR(__xludf.DUMMYFUNCTION("""COMPUTED_VALUE"""),"") | F78: 4.71 | N78: =IFERROR(__xludf.DUMMYFUNCTION("""COMPUTED_VALUE"""),"") | R78: 6DE8C5 | S78: 7.25 | T78: 5E0E93 | V78: 5E0E93
A79: 45902 | B79: =IFERROR(__xludf.DUMMYFUNCTION("""COMPUTED_VALUE"""),"BPF-SE-SOP-1A-4") -> BPF-SE-SOP-1A-4 | C79: String of Pearls | E79: =IFERROR(__xludf.DUMMYFUNCTION("""COMPUTED_VALUE"""),"") | F79: 4.71 | N79: =IFERROR(__xludf.DUMMYFUNCTION("""COMPUTED_VALUE"""),"") | R79: E07801 | S79: 7.25 | T79: 07F77D | V79: 07F77D
A80: 45902 | B80: =IFERROR(__xludf.DUMMYFUNCTION("""COMPUTED_VALUE"""),"BPF-SE-SOP-1A-5") -> BPF-SE-SOP-1A-5 | C80: String of Pearls | E80: =IFERROR(__xludf.DUMMYFUNCTION("""COMPUTED_VALUE"""),"") | F80: 4.71 | N80: =IFERROR(__xludf.DUMMYFUNCTION("""COMPUTED_VALUE"""),"") | R80: 5EC9AE | S80: 7.25 | T80: 7FE15B | V80: 7FE15B
A81: 45902 | B81: =IFERROR(__xludf.DUMMYFUNCTION("""COMPUTED_VALUE"""),"BPF-PO-NE-1A") -> BPF-PO-NE-1A | E81: =IFERROR(__xludf.DUMMYFUNCTION("""COMPUTED_VALUE"""),"WO-PO-6-WH-1") -> WO-PO-6-WH-1 | F81: 13 | K81: 6 | M81: 6 | N81: =IFERROR(__xludf.DUMMYFUNCTION("""COMPUTED_VALUE"""),"") | P81: Sold | R81: 2B1649 | S81: 20 | T81: B94615 | V81: B94615
A82: 45902 | B82: =IFERROR(__xludf.DUMMYFUNCTION("""COMPUTED_VALUE"""),"BPF-PO-NE-1A-2") -> BPF-PO-NE-1A-2 | C82: Neon Pothos | E82: =IFERROR(__xludf.DUMMYFUNCTION("""COMPUTED_VALUE"""),"MU-PO-4-WH-1") -> MU-PO-4-WH-1 | F82: 4.3333333 | K82: 0 | M82: 0 | N82: =IFERROR(__xludf.DUMMYFUNCTION("""COMPUTED_VALUE"""),"") | P82: Sold | R82: 69DB07 | S82: 20 | T82: BE4EDC | V82: BE4EDC
A83: 45900 | B83: =IFERROR(__xludf.DUMMYFUNCTION("""COMPUTED_VALUE"""),"FM-PH-PP-1A") -> FM-PH-PP-1A | C83: Neon Pothos | E83: =IFERROR(__xludf.DUMMYFUNCTION("""COMPUTED_VALUE"""),"") | F83: 0 | N83: =IFERROR(__xludf.DUMMYFUNCTION("""COMPUTED_VALUE"""),"") | R83: 24FF6A | S83: 0 | T83: C6622C | V83: C6622C
A84: 45903 | B84: =IFERROR(__xludf.DUMMYFUNCTION("""COMPUTED_VALUE"""),"FM-PH-BMV-1A") -> FM-PH-BMV-1A | E84: =IFERROR(__xludf.DUMMYFUNCTION("""COMPUTED_VALUE"""),"EC-PO-5-SW-1") -> EC-PO-5-SW-1 | F84: 7.5 | N84: =IFERROR(__xludf.DUMMYFUNCTION("""COMPUTED_VALUE"""),"") | R84: 5ECF2F | S84: 0 | T84: A14B54 | V84: A14B54
A85: 45904 | B85: =IFERROR(__xludf.DUMMYFUNCTION("""COMPUTED_VALUE"""),"FM-PH-BMV-1A-2") -> FM-PH-BMV-1A-2 | E85: =IFERROR(__xludf.DUMMYFUNCTION("""COMPUTED_VALUE"""),"") | F85: 15 | N85: =IFERROR(__xludf.DUMMYFUNCTION("""COMPUTED_VALUE"""),"") | R85: B923BF | S85: 0 | T85: 4F639F | V85: 4F639F
A86: 45903 | B86: =IFERROR(__xludf.DUMMYFUNCTION("""COMPUTED_VALUE"""),"FM-SYN-BA-1A") -> FM-SYN-BA-1A | E86: =IFERROR(__xludf.DUMMYFUNCTION("""COMPUTED_VALUE"""),"MA-PO-4-SW-1") -> MA-PO-4-SW-1 | F86: 7.5 | N86: =IFERROR(__xludf.DUMMYFUNCTION("""COMPUTED_VALUE"""),"") | R86: E1B355 | S86: 0 | T86: 457BDD | V86: 457BDD
A87: 45886 | B87: =IFERROR(__xludf.DUMMYFUNCTION("""COMPUTED_VALUE"""),"FMY-AL-RSD-1A-2") -> FMY-AL-RSD-1A-2 | E87: =IFERROR(__xludf.DUMMYFUNCTION("""COMPUTED_VALUE"""),"") | F87: 10.99 | N87: =IFERROR(__xludf.DUMMYFUNCTION("""COMPUTED_VALUE"""),"") | R87: EA64D3 | T87: EFC067 | V87: EFC067
A88: 45886 | B88: =IFERROR(__xludf.DUMMYFUNCTION("""COMPUTED_VALUE"""),"FMY-MA-PE-1A") -> FMY-MA-PE-1A | E88: =IFERROR(__xludf.DUMMYFUNCTION("""COMPUTED_VALUE"""),"PS-PO-5.5-MU-1") -> PS-PO-5.5-MU-1 | F88: 2.4271429 | K88: 0 | M88: 0 | N88: =IFERROR(__xludf.DUMMYFUNCTION("""COMPUTED_VALUE"""),"") | P88: Sold | R88: 856273 | T88: 755A04 | V88: 755A04
A89: 45886 | B89: =IFERROR(__xludf.DUMMYFUNCTION("""COMPUTED_VALUE"""),"FMY-AG-SPA-1A") -> FMY-AG-SPA-1A | E89: =IFERROR(__xludf.DUMMYFUNCTION("""COMPUTED_VALUE"""),"TE-PO-4-MU-1") -> TE-PO-4-MU-1 | F89: 3.3316667 | N89: =IFERROR(__xludf.DUMMYFUNCTION("""COMPUTED_VALUE"""),"") | R89: BAFDC6 | T89: 61C173 | V89: 61C173
A90: 45886 | B90: =IFERROR(__xludf.DUMMYFUNCTION("""COMPUTED_VALUE"""),"FMY-CA-MA-1A") -> FMY-CA-MA-1A | E90: =IFERROR(__xludf.DUMMYFUNCTION("""COMPUTED_VALUE"""),"PS-PO-5.5-MU-1") -> PS-PO-5.5-MU-1 | F90: 3.3316667 | N90: =IFERROR(__xludf.DUMMYFUNCTION("""COMPUTED_VALUE"""),"") | R90: C98895 | S90: 16.99 | T90: 803EC7 | V90: 803EC7
A91: 45886 | B91: =IFERROR(__xludf.DUMMYFUNCTION("""COMPUTED_VALUE"""),"FMY-MA-DE-1A-3") -> FMY-MA-DE-1A-3 | E91: =IFERROR(__xludf.DUMMYFUNCTION("""COMPUTED_VALUE"""),"TE-PO-4-MU-1") -> TE-PO-4-MU-1 | F91: 3.3316667 | N91: =IFERROR(__xludf.DUMMYFUNCTION("""COMPUTED_VALUE"""),"") | R91: A6E2FF | T91: 870457 | V91: 870457
A92: 45886 | B92: =IFERROR(__xludf.DUMMYFUNCTION("""COMPUTED_VALUE"""),"FMY-MA-DE-1A-4") -> FMY-MA-DE-1A-4 | E92: =IFERROR(__xludf.DUMMYFUNCTION("""COMPUTED_VALUE"""),"WO-PO-6-MU-1") -> WO-PO-6-MU-1 | F92: 1.57 | N92: =IFERROR(__xludf.DUMMYFUNCTION("""COMPUTED_VALUE"""),"") | R92: 57F95F | T92: 3BF0A6 | V92: 3BF0A6
A93: 45886 | B93: =IFERROR(__xludf.DUMMYFUNCTION("""COMPUTED_VALUE"""),"FMY-MA-DE-1A-5") -> FMY-MA-DE-1A-5 | E93: =IFERROR(__xludf.DUMMYFUNCTION("""COMPUTED_VALUE"""),"GA-PO-6-MU-1") -> GA-PO-6-MU-1 | F93: 2.7475 | K93: 10 | M93: 10 | N93: =IFERROR(__xludf.DUMMYFUNCTION("""COMPUTED_VALUE"""),"") | P93: Sold | R93: 5AF6AE | T93: F83BC6 | V93: F83BC6
A94: 45886 | B94: =IFERROR(__xludf.DUMMYFUNCTION("""COMPUTED_VALUE"""),"FMY-PH-PL-1A") -> FMY-PH-PL-1A | E94: =IFERROR(__xludf.DUMMYFUNCTION("""COMPUTED_VALUE"""),"GA-PO-6-MU-1") -> GA-PO-6-MU-1 | F94: 9.995 | N94: =IFERROR(__xludf.DUMMYFUNCTION("""COMPUTED_VALUE"""),"") | R94: 6B60A0 | S94: 40 | T94: AAB9F9 | V94: AAB9F9
A95: 45886 | B95: =IFERROR(__xludf.DUMMYFUNCTION("""COMPUTED_VALUE"""),"HD-AL-LO-1A") -> HD-AL-LO-1A | E95: =IFERROR(__xludf.DUMMYFUNCTION("""COMPUTED_VALUE"""),"WO-PO-6-MU-1") -> WO-PO-6-MU-1 | F95: 7.495 | N95: =IFERROR(__xludf.DUMMYFUNCTION("""COMPUTED_VALUE"""),"") | R95: 90C267 | T95: DB0C02 | V95: DB0C02
A96: 45886 | B96: =IFERROR(__xludf.DUMMYFUNCTION("""COMPUTED_VALUE"""),"HD-AL-LO-1A-2") -> HD-AL-LO-1A-2 | E96: =IFERROR(__xludf.DUMMYFUNCTION("""COMPUTED_VALUE"""),"PS-PO-5.5-MU-1") -> PS-PO-5.5-MU-1 | F96: 9.9933333 | N96: =IFERROR(__xludf.DUMMYFUNCTION("""COMPUTED_VALUE"""),"") | R96: F2B4F5 | T96: B2C9CF | V96: B2C9CF
A97: 45886 | B97: =IFERROR(__xludf.DUMMYFUNCTION("""COMPUTED_VALUE"""),"HD-AL-GVF-1A-2") -> HD-AL-GVF-1A-2 | E97: =IFERROR(__xludf.DUMMYFUNCTION("""COMPUTED_VALUE"""),"GA-PO-6-MU-1") -> GA-PO-6-MU-1 | F97: 14.99 | N97: =IFERROR(__xludf.DUMMYFUNCTION("""COMPUTED_VALUE"""),"") | R97: DCED1B | T97: B0FFBB | V97: B0FFBB
A98: 45886 | B98: =IFERROR(__xludf.DUMMYFUNCTION("""COMPUTED_VALUE"""),"HD-AL-BDS-1A") -> HD-AL-BDS-1A | E98: =IFERROR(__xludf.DUMMYFUNCTION("""COMPUTED_VALUE"""),"MA-PO-5-SW-1") -> MA-PO-5-SW-1 | F98: 6.66 | N98: =IFERROR(__xludf.DUMMYFUNCTION("""COMPUTED_VALUE"""),"") | R98: 956FA2 | T98: ACF2EB | V98: ACF2EB
A99: 45886 | B99: =IFERROR(__xludf.DUMMYFUNCTION("""COMPUTED_VALUE"""),"HD-PH-GG-1A") -> HD-PH-GG-1A | E99: =IFERROR(__xludf.DUMMYFUNCTION("""COMPUTED_VALUE"""),"") | F99: 19.98 | N99: =IFERROR(__xludf.DUMMYFUNCTION("""COMPUTED_VALUE"""),"") | P99: Available | R99: FD5AF1 | T99: A1651A | V99: A1651A
A100: 45886 | B100: =IFERROR(__xludf.DUMMYFUNCTION("""COMPUTED_VALUE"""),"HD-HO-SSS-1A") -> HD-HO-SSS-1A | E100: =IFERROR(__xludf.DUMMYFUNCTION("""COMPUTED_VALUE"""),"") | F100: 19.98 | N100: =IFERROR(__xludf.DUMMYFUNCTION("""COMPUTED_VALUE"""),"") | P100: Not for Sale | R100: A63DAD | T100: A601C1 | V100: A601C1
...

Sheet Price KEY
A1: Product Name | B1: Pot Code | C1: Pot Size | D1: Disc | F1: Status
A2: Angel Wing | B2: DV-PO-2-WH-1A | C2: 3" | D2: Giveaway | E2: Sold | F2: For Sale
A3: Hoya Krimson Princess | B3: AN-PO-3-MU-1A | C3: 4" | D3: $5 Off | E3: Pending | F3: Sold
A4: McColley's FInale | B4: YA-PO-2-CL-1A | C4: 4.3" | D4: $10 Off | E4: Hold | F4: Delivered
A5: Monstera Deliciosa | B5: EB-PO-4-DO-1A | C5: 2" | D5: None | E5: Available | F5: Pending Sale
A6: String of Hearts | B6: ZO-PO-4-WL-1A | C6: 6" | D6: Donation | E6: Reserved | F6: Keep
A7: String of Pearls | B7: HY-PO-3-DO-1A | C7: 5.5" | D7: Custom | E7: Not for Sale | F7: Hold
A8: Variegated SOH | E8: Giveaway | F8: Shipped
A9: Variegated SOP | C9: 3.7" | E9: Damaged | F9: Pending Shipping
F10: Dead

Sheet Overhead Expenses
G1: =SUM(G3:G997) -> 8671.21 | H1: =SUM(H3:H997) -> 0 | I1: =SUM(I3:I992) -> 926.58 | J1: =G1 - I1 -> 7744.63 | K1: =SUM(K3:K994) -> 7744.63
A2: Date | B2: Vendor | C2: Brand | D2: Category | E2: Description | F2: Qty | G2: Sub Tot | H2: Ship. | I2: Disc. | J2: Un. Cost | K2: Act. Tot | L2: Pmt. M. | M2: Card # | N2: Invoice # | O2: Notes / Project | P2: U ID | Q2: Owner Email | R2: Receipt
A3: 45941 | B3: TikTok | C3: Rosebud Homegoods | D3: Tools & Supplies | E3: Soil Scoop | F3: 1 | G3: 15 | H3: 0 | I3: 0 | J3: {=IF(F3:F997="","", ROUND( (G3:G997 + H3:H997 - I3:I997) / F3:F997, 2 ) )} -> 15 | K3: {=IF(G3:G994="","", G3:G994 - H3:H994 - I3:I994 )} -> 15 | L3: Credit Card | P3: 3779B1 | Q3: starr8@rocketmail.com
A4: 45874 | B4: Amazon | C4: EnHomee | D4: Shelving/Fixtures | E4: Wooden Plant Stand | F4: 1 | G4: 39.99 | H4: 0 | I4: 39.99 | J4: 0 | K4: 0 | L4: Gift Certificate | P4: 6EF362 | Q4: starr8@rocketmail.com
A5: 45874 | B5: Amazon | C5: Homvana | D5: Climate & Environment | E5: Warm & cool mist humidifier | F5: 1 | G5: 29.98 | I5: 29.98 | J5: 0 | K5: 0 | L5: Gift Certificate | P5: A66D13 | Q5: starr8@rocketmail.com
A6: 45874 | B6: Amazon | C6: Legigo | D6: Soil & Amendments | E6: Orchid bark | F6: 1 | G6: 14.99 | I6: 14.99 | J6: 0 | K6: 0 | L6: Gift Certificate | P6: DDE6C4 | Q6: starr8@rocketmail.com
A7: 45874 | B7: Amazon | C7: Mkono | D7: Propagation Supplies | E7: Plant propagation tube wall hanger | F7: 1 | G7: 24.99 | I7: 24.99 | J7: 0 | K7: 0 | L7: Gift Certificate | P7: 156075 | Q7: starr8@rocketmail.com
A8: 45873 | B8: Amazon | C8: Legigo | D8: Soil & Amendments | E8: sphagnum moss (various sizes) | F8: 1 | G8: 11.39 | I8: 11.39 | J8: 0 | K8: 0 | L8: Gift Certificate | P8: 4CDA26 | Q8: starr8@rocketmail.com
A9: 45879 | B9: Amazon | C9: Yuanling | D9: Labels & Stickers | E9: Plastic plant labels (green/red) | F9: 1 | G9: 5.63 | I9: 0 | J9: 5.63 | K9: 5.63 | L9: Credit Card | M9: 1002 | P9: 8453D7 | Q9: starr8@rocketmail.com
A10: 45879 | B10: Amazon | C10: Yuanling | D10: Labels & Stickers | E10: Plastic plant labels (green/red) | F10: 1 | G10: 5.63 | I10: 0 | J10: 5.63 | K10: 5.63 | L10: Credit Card | M10: 1002 | P10: BBCD88 | Q10: starr8@rocketmail.com
A11: 45880 | B11: Amazon | C11: TDHDIKE | D11: Labels & Stickers | E11: Plastic plant labels (white) | F11: 1 | G11: 11.99 | I11: 0 | J11: 11.99 | K11: 11.99 | L11: Credit Card | M11: 1002 | P11: F34739 | Q11: starr8@rocketmail.com
A12: 45877 | B12: Amazon | C12: SupKing | D12: Propagation Supplies | E12: Air layering propagation pods | F12: 1 | G12: 7.59 | I12: 2.28 | J12: 5.31 | K12: 5.31 | L12: Credit Card | M12: 1002 | P12: 2AC0EA | Q12: starr8@rocketmail.com
A13: 45877 | B13: Amazon | C13: HNXTYAOB | D13: Tools & Supplies | E13: Repotting mats (large) | F13: 1 | G13: 28.99 | I13: 0 | J13: 28.99 | K13: 28.99 | L13: Credit Card | M13: 1002 | P13: 623A9B | Q13: starr8@rocketmail.com
A14: 45877 | B14: Amazon | C14: Voulosimi | D14: Soil & Amendments | E14: 30 QT Perlite | F14: 1 | G14: 36.99 | I14: 0 | J14: 36.99 | K14: 36.99 | L14: Credit Card | M14: 1002 | P14: 99B44C | Q14: starr8@rocketmail.com
A15: 45877 | B15: Amazon | C15: SupKing | D15: Propagation Supplies | E15: Air layering propagation pods | F15: 1 | G15: 7.59 | I15: 0 | J15: 7.59 | K15: 7.59 | L15: Credit Card | M15: 1002 | P15: D12DFD | Q15: starr8@rocketmail.com
A16: 45877 | B16: Amazon | C16: TPS NUTRIENTS | D16: Treatments & Fertilizers | E16: Silica plant supplement | F16: 1 | G16: 9.99 | I16: 0 | J16: 9.99 | K16: 9.99 | L16: Credit Card | M16: 1002 | P16: 08A7AE | Q16: starr8@rocketmail.com
A17: 45877 | B17: Amazon | C17: Legigo | D17: Soil & Amendments | E17: sphagnum moss (various sizes) | F17: 1 | G17: 39.89 | I17: 0 | J17: 39.89 | K17: 39.89 | L17: Credit Card | M17: 1002 | P17: 40215F | Q17: starr8@rocketmail.com
A18: 45877 | B18: Amazon | C18: Technaflora | D18: Propagation Supplies | E18: Rootech rooting gel | F18: 1 | G18: 6.63 | I18: 0 | J18: 6.63 | K18: 6.63 | L18: Credit Card | M18: 1002 | P18: 779B10 | Q18: starr8@rocketmail.com
A19: 45877 | B19: Amazon | C19: ferti-lome | D19: Treatments & Fertilizers | E19: Houseplant fertilizer | F19: 1 | G19: 12.77 | J19: 12.77 | K19: 12.77 | L19: Credit Card | M19: 1002 | P19: AF14C1 | Q19: starr8@rocketmail.com
A20: 45877 | B20: Amazon | C20: RWNTAO | D20: Lighting | E20: LED grow light bar set | F20: 1 | G20: 22.79 | J20: 22.79 | K20: 22.79 | L20: Credit Card | M20: 1002 | P20: E68E72 | Q20: starr8@rocketmail.com
A21: 45877 | B21: Amazon | C21: Barrina | D21: Shelving/Fixtures | E21: Heavy duty wire shelving rack w/ lights | F21: 1 | G21: 234.99 | J21: 234.99 | K21: 234.99 | L21: Credit Card | M21: 1002 | P21: 1E0823 | Q21: starr8@rocketmail.com
A22: 45877 | B22: Amazon | C22: Legigo | D22: Soil & Amendments | E22: Orchid bark | F22: 1 | G22: 28.99 | J22: 28.99 | K22: 28.99 | L22: Credit Card | M22: 1002 | P22: 5581D4 | Q22: starr8@rocketmail.com
A23: 45879 | B23: Amazon | C23: Govee | D23: Climate & Environment | E23: Bluetooth hygrometers | F23: 1 | G23: 29.74 | J23: 29.74 | K23: 29.74 | L23: Credit Card | M23: 1002 | P23: 8CFB85 | Q23: starr8@rocketmail.com
A24: 45879 | B24: Amazon | C24: JRD | D24: Climate & Environment | E24: Warm & cool mist humidifier | F24: 1 | G24: 79.99 | I24: 30 | J24: 49.99 | K24: 49.99 | L24: Credit Card | M24: 1002 | P24: C47536 | Q24: starr8@rocketmail.com
A25: 45881 | B25: Amazon | C25: Luxbird | D25: Climate & Environment | E25: Seedling heat mats with thermostat | F25: 1 | G25: 53.59 | J25: 53.59 | K25: 53.59 | L25: Credit Card | M25: 1002 | P25: FBEEE7 | Q25: starr8@rocketmail.com
A26: 45881 | B26: Amazon | C26: RWNTAO | D26: Lighting | E26: LED grow light bar set | F26: 1 | G26: 22.79 | I26: 2.28 | J26: 20.51 | K26: 20.51 | L26: Credit Card | M26: 1002 | P26: 336898 | Q26: starr8@rocketmail.com
A27: 45884 | B27: Amazon | C27: Avery | D27: Labels & Stickers | E27: Waterproof rectangle labels | F27: 1 | G27: 39.3 | I27: 0 | J27: 39.3 | K27: 39.3 | L27: Credit Card | M27: 1002 | P27: 6AE249 | Q27: starr8@rocketmail.com
A28: 45884 | B28: Amazon | C28: Cubic Coating | D28: Labels & Stickers | E28: Custom waterproof vinyl stickers | F28: 1 | G28: 7.99 | I28: 0 | J28: 7.99 | K28: 7.99 | L28: Credit Card | M28: 1002 | P28: A25BFA | Q28: starr8@rocketmail.com
A29: 45884 | B29: Amazon | C29: WOWBOX | D29: Tools & Supplies | E29: Clear drawer organizer set | F29: 1 | G29: 17.99 | I29: 0 | J29: 17.99 | K29: 17.99 | L29: Credit Card | M29: 1002 | P29: D9D5AB | Q29: starr8@rocketmail.com
A30: 45884 | B30: Amazon | C30: Us-garden life | D30: Miscellaneous | E30: Yellow sticky fungus gnat traps | F30: 1 | G30: 11.89 | I30: 0 | J30: 11.89 | K30: 11.89 | L30: Credit Card | M30: 1002 | P30: 114F5C | Q30: starr8@rocketmail.com
A31: 45886 | B31: Amazon | C31: Geyoga | D31: Cleaning & Sanitation | E31: Microfiber dusting gloves | F31: 1 | G31: 19.99 | I31: 0 | J31: 19.99 | K31: 19.99 | L31: Credit Card | M31: 1002 | P31: 48C90D | Q31: starr8@rocketmail.com
A32: 45877 | B32: Amazon | C32: MIIIM | D32: Tools & Supplies | E32: Self-watering moss poles | F32: 1 | G32: 26.79 | I32: 0 | J32: 26.79 | K32: 26.79 | L32: Credit Card | M32: 1002 | P32: 8042BE | Q32: starr8@rocketmail.com
A33: 45881 | B33: Faire | C33: The Gay Ole Plant Shop | D33: Inbound Shipping | E33: Live Plants | F33: 9 | G33: 35.53 | I33: 17.5 | J33: 2 | K33: 18.03 | L33: Debit Card | M33: 6116 | N33: Order #A2XS4KRJ22 | P33: B7BC6F | Q33: starr8@rocketmail.com
A34: 45884 | B34: Faire | C34: BWH Plant Company | D34: Inbound Shipping | E34: Live Plants | F34: 20 | G34: 74.17 | I34: 82.5 | J34: -0.42 | K34: -8.33 | L34: Credit Card | M34: 1002 | N34: Order #S77AG59RJX | P34: EF3620 | Q34: starr8@rocketmail.com
A35: 45902 | B35: Faire | C35: Best Plant Friend | D35: Inbound Shipping | E35: Live Plants | F35: 12 | G35: 0 | I35: 19.69 | J35: -1.64 | K35: -19.69 | L35: Credit Card | M35: 5770 | N35: Order #BUCJZSM9TH | P35: 26AFD1 | Q35: starr8@rocketmail.com
A36: 45909 | B36: Faire | C36: Dicks Sticks & Exotics | D36: Inbound Shipping | E36: Live Plants | F36: 37 | G36: 35 | I36: 0 | J36: 0.95 | K36: 35 | L36: Credit Card | M36: 5770 | N36: Order #7634WQK7TQ | P36: 5E2982 | Q36: starr8@rocketmail.com
A37: 45909 | B37: Faire | C37: Arcadia Garden Products | D37: Inbound Shipping | E37: Live Plants | F37: 15 | G37: 62.88 | I37: 40.75 | J37: 1.48 | K37: 22.13 | L37: Credit Card | M37: 5770 | N37: Order #DYZ5SXKCFD | P37: 95A333 | Q37: starr8@rocketmail.com
A38: 45915 | B38: Faire | C38: BWH Plant Company | D38: Inbound Shipping | E38: Live Plants | F38: 26 | G38: 74.8 | I38: 0 | J38: 2.88 | K38: 74.8 | L38: Credit Card | M38: 1002 | N38: Order #6BTFSUN8P3 | P38: CD1CE4 | Q38: starr8@rocketmail.com
A39: 45915 | B39: Faire | C39: Thorsen's Greenhouse | D39: Inbound Shipping | E39: Live Plants | F39: 16 | G39: 0 | I39: 0 | J39: 0 | K39: 0 | L39: Unpaid Invoice | M39: UI | N39: Order #5BQ26SNEMZ | P39: 049695 | Q39: starr8@rocketmail.com
A40: 45920 | B40: Faire | C40: Jungle Club | D40: Inbound Shipping | E40: Planters | F40: 24 | G40: 0 | I40: 0 | J40: 0 | K40: 0 | L40: Unpaid Invoice | M40: UI | N40: Order #92FFNYJ3EJ | P40: 3C1046 | Q40: starr8@rocketmail.com
A41: 45922 | B41: Faire | C41: BWH Plant Company | D41: Inbound Shipping | E41: Live Plants | F41: 38 | G41: 99.57 | I41: 0 | J41: 2.62 | K41: 99.57 | L41: Unpaid Invoice | M41: UI | N41: Order #VEVVFFVDVP | P41: 7389F7 | Q41: starr8@rocketmail.com
A42: 45929 | B42: Dawn W. | C42: None | D42: Labor | E42: Assistant | F42: 3 | G42: 54 | H42: 0 | I42: 0 | J42: 18 | K42: 54 | L42: Venmo | M42: 6116 | N42: 001 | P42: AB03A8 | Q42: starr8@rocketmail.com
A43: 45929 | B43: Faire | C43: Best Plant Friend | D43: Inbound Shipping | E43: Live Plants | F43: 15 | G43: 10.66 | I43: 9.34 | J43: 0.09 | K43: 1.32 | L43: Unpaid Invoice | M43: UI | N43: Order #Y8CPRUWB69 | P43: E27D59 | Q43: starr8@rocketmail.com
A44: 45929 | B44: Faire | C44: Amano Studio | D44: Inbound Shipping | E44: Jewelry | F44: 15 | G44: 0 | I44: 0 | J44: 0 | K44: 0 | L44: Unpaid Invoice | M44: UI | N44: Order #G97E88E5NF | P44: 19F70A | Q44: starr8@rocketmail.com
A45: 45930 | B45: Dawn W. | C45: Blooming Starr | D45: Labor | E45: Assistant | F45: 4 | G45: 72 | H45: 0 | I45: 0 | J45: 18 | K45: 72 | L45: Venmo | M45: 6116 | N45: 002 | P45: 5170BB | Q45: starr8@rocketmail.com
A46: 45931 | B46: Faire | C46: Axle Rose Co | D46: Inbound Shipping | E46: Tote Bags/Keychains/Stickers | F46: 38 | G46: 11.5 | I46: 0 | J46: 0.3 | K46: 11.5 | L46: Unpaid Invoice | M46: UI | N46: Order #VEEVBT9XJH | P46: 88EA6C | Q46: starr8@rocketmail.com
A47: 45932 | B47: Dawn W. | C47: None | D47: Labor | E47: Assistant | F47: 4 | G47: 72 | H47: 0 | I47: 0 | J47: 18 | K47: 72 | L47: Venmo | M47: 6116 | N47: 003 | P47: C0641D | Q47: starr8@rocketmail.com
A48: 45932 | B48: Faire | C48: Tiny Plant Market | D48: Inbound Shipping | E48: Stickers | F48: 10 | G48: 0 | I48: 0 | J48: 0 | K48: 0 | L48: Unpaid Invoice | M48: UI | N48: Order #5Y27KVGXCF | P48: F7DDCE | Q48: starr8@rocketmail.com
A49: 45934 | B49: Dawn W. | C49: Blooming Starr | D49: Labor | E49: Assistant | F49: 4.62 | G49: 83.1 | I49: 0 | J49: 17.99 | K49: 83.1 | L49: Venmo | M49: 6116 | N49: 004 | P49: 2F577F | Q49: starr8@rocketmail.com
A50: 45936 | B50: Faire | C50: Best Plant Friend | D50: Inbound Shipping | E50: Live Plants | F50: 6 | G50: 5.52 | I50: 9.34 | J50: -0.64 | K50: -3.82 | L50: Unpaid Invoice | M50: UI | N50: Order #FCR7S8VH3Z | P50: 66D130 | Q50: starr8@rocketmail.com
A51: 45937 | B51: Dawn W. | C51: Blooming Starr | D51: Labor | E51: Assistant | F51: 3.82 | G51: 68.7 | I51: 0 | J51: 17.98 | K51: 68.7 | L51: Venmo | M51: 6116 | N51: 005 | P51: 9E4AE1 | Q51: starr8@rocketmail.com
A52: 45939 | B52: Dawn W. | C52: Blooming Starr | D52: Labor | E52: Assistant | F52: 4.13 | G52: 74.4 | I52: 0 | J52: 18.01 | K52: 74.4 | L52: Venmo | M52: 6116 | N52: 006 | P52: D5C492 | Q52: starr8@rocketmail.com
A53: 45940 | B53: Dawn W. | C53: None | D53: Labor | E53: Assistant | F53: 4.12 | G53: 74.1 | I53: 0 | J53: 17.99 | K53: 74.1 | L53: Venmo | M53: 6116 | N53: 007 | O53: Inventory Logging | P53: 0D3E43 | Q53: starr8@rocketmail.com
B54: Faire | C54: Succulents & Such, Inc. | D54: Inbound Shipping | E54: Live Plants | F54: 45 | J54: 0 | L54: Unpaid Invoice | M54: UI | N54: Order #8DCYT58VMA | P54: 44B7F4 | Q54: starr8@rocketmail.com
A55: 45886 | B55: Amazon | C55: Yoshiky | D55: Market Fees & Supplies | E55: Wood display risers | F55: 1 | G55: 24.99 | I55: 0 | J55: 24.99 | K55: 24.99 | L55: Credit Card | M55: 1002 | P55: 7C31A5 | Q55: starr8@rocketmail.com
A56: 45886 | B56: Amazon | C56: Aokrean | D56: Lighting | E56: Adjustable halo grow lights | F56: 1 | G56: 44.99 | I56: 0 | J56: 44.99 | K56: 44.99 | L56: Credit Card | M56: 1002 | P56: B3AB56 | Q56: starr8@rocketmail.com
A57: 45888 | B57: Amazon | C57: Pureegg | D57: Table Covers & Displays | E57: Spandex tablecloth covers | F57: 1 | G57: 12.98 | I57: 0 | J57: 12.98 | K57: 12.98 | L57: Credit Card | M57: 1002 | P57: EB2507 | Q57: starr8@rocketmail.com
A58: 45890 | B58: Amazon | C58: Dutch Harbor Brands | D58: Cleaning & Sanitation | E58: Isopropyl alcohol wipes | F58: 1 | G58: 27.33 | J58: 27.33 | K58: 27.33 | L58: Credit Card | M58: 1002 | P58: 229EB8 | Q58: starr8@rocketmail.com
A59: 45891 | B59: Amazon | C59: Legigo | D59: Soil & Amendments | E59: Orchid bark | F59: 1 | G59: 28.99 | I59: 0 | J59: 28.99 | K59: 28.99 | L59: Credit Card | M59: 1002 | P59: 5A1869 | Q59: starr8@rocketmail.com
A60: 45894 | B60: Amazon | C60: Jassetparty | D60: Table Covers & Displays | E60: Spandex tablecloth covers | F60: 1 | G60: 9.99 | I60: 0 | J60: 9.99 | K60: 9.99 | L60: Credit Card | M60: 1002 | P60: 91921A | Q60: starr8@rocketmail.com
A61: 45894 | C61: Our Modern Space | D61: Tables & Furniture | E61: Folding table with adjustable height | F61: 1 | G61: 49.25 | I61: 0 | J61: 49.25 | K61: 49.25 | L61: Credit Card | M61: 1002 | Q61: starr8@rocketmail.com
A62: 45894 | B62: Amazon | C62: KOALA PAPER | D62: Stationery & Print | E62: Glossy photo paper | F62: 1 | G62: 6.9 | I62: 0 | J62: 6.9 | K62: 6.9 | L62: Credit Card | M62: 1002 | P62: 00857C | Q62: starr8@rocketmail.com
A63: 45895 | B63: Amazon | C63: Tangcaikai | D63: Table Covers & Displays | E63: Mini acrylic display easels | F63: 1 | G63: 20.99 | I63: 2.52 | J63: 18.47 | K63: 18.47 | L63: Credit Card | M63: 1002 | P63: 37FF2D | Q63: starr8@rocketmail.com
A64: 45896 | B64: Amazon | C64: Azhen-XIN | D64: Table Covers & Displays | E64: Mini acrylic display easels | F64: 1 | G64: 29.99 | J64: 29.99 | K64: 29.99 | L64: Credit Card | M64: 1002 | P64: 6F78DE | Q64: starr8@rocketmail.com
A65: 45896 | B65: Amazon | C65: Poer | D65: Table Covers & Displays | E65: Clear acrylic business card holders | F65: 1 | G65: 5.97 | J65: 5.97 | K65: 5.97 | L65: Credit Card | M65: 1002 | P65: A6F28F | Q65: starr8@rocketmail.com
A66: 45896 | B66: Amazon | C66: HIIMIEI | D66: Table Covers & Displays | E66: Acrylic brochure holders | F66: 1 | G66: 15.39 | J66: 15.39 | K66: 15.39 | L66: Credit Card | M66: 1002 | P66: DE6C40 | Q66: starr8@rocketmail.com
A67: 45897 | B67: Amazon | C67: LightRail | D67: Stationery & Print | E67: Postcard paper cardstock | F67: 2 | G67: 13.98 | J67: 6.99 | K67: 13.98 | L67: Credit Card | M67: 1002 | P67: 15E5F1 | Q67: starr8@rocketmail.com
A68: 45900 | B68: Amazon | C68: Yuanseg | D68: Market Fees & Supplies | E68: Black shade cloth tarp | F68: 3 | G68: 80.14 | I68: 4.22 | J68: 25.31 | K68: 75.92 | L68: Credit Card | M68: 0590 | P68: 4D5FA2 | Q68: starr8@rocketmail.com
A69: 45900 | B69: Amazon | C69: Epic Medical Supply | D69: Tools & Supplies | E69: Hydrogen peroxide (bulk) | F69: 1 | G69: 20.99 | J69: 20.99 | K69: 20.99 | L69: Credit Card | M69: 0590 | P69: 84D953 | Q69: starr8@rocketmail.com
A70: 45900 | B70: Amazon | C70: Dr. Bronner's | D70: Treatments & Fertilizers | E70: Castile liquid soap | F70: 1 | G70: 16.97 | J70: 16.97 | K70: 16.97 | L70: Credit Card | M70: 0590 | P70: BC5304 | Q70: starr8@rocketmail.com
A71: 45900 | B71: Amazon | C71: Square Sinks | D71: Cleaning & Sanitation | E71: Isopropyl Alcohol | F71: 1 | G71: 27.95 | I71: 0 | J71: 27.95 | K71: 27.95 | L71: Credit Card | M71: 0590 | P71: F3CCB5 | Q71: starr8@rocketmail.com
A72: 45900 | B72: Amazon | C72: Amazon | D72: Market Fees & Supplies | E72: Pop up canopy tent | F72: 1 | G72: 59.99 | J72: 59.99 | K72: 59.99 | L72: Credit Card | M72: 0590 | P72: 2B4666 | Q72: starr8@rocketmail.com
A73: 45900 | B73: Amazon | C73: Legigo | D73: Soil & Amendments | E73: Orchid bark | F73: 2 | G73: 57.98 | I73: 0.37 | J73: 28.81 | K73: 57.61 | L73: Credit Card | M73: 0590 | P73: 62C017 | Q73: starr8@rocketmail.com
A74: 45900 | B74: Amazon | C74: MDPQT | D74: Soil & Amendments | E74: 20 QT Perlite | F74: 1 | G74: 25.73 | J74: 25.73 | K74: 25.73 | L74: Credit Card | M74: 0590 | P74: 9A39C8 | Q74: starr8@rocketmail.com
A75: 45900 | B75: Amazon | C75: MDPQT | D75: Soil & Amendments | E75: 20 QT Perlite | F75: 1 | G75: 26.99 | J75: 26.99 | K75: 26.99 | L75: Credit Card | M75: 0590 | P75: D1B379 | Q75: starr8@rocketmail.com
A76: 45903 | B76: Amazon | C76: Berkland | D76: Propagation Supplies | E76: Keiki plant cloning paste | F76: 1 | G76: 17.79 | J76: 17.79 | K76: 17.79 | L76: Credit Card | M76: 0590 | P76: 092D2A | Q76: starr8@rocketmail.com
A77: 45946 | B77: Dawn W. | C77: None | D77: Labor | E77: Data Entry | F77: 4 | G77: 72 | H77: 0 | I77: 0 | J77: 18 | K77: 72 | L77: Venmo | M77: 6116 | N77: 008 | O77: Overhead Item Input | P77: 40A6DB | Q77: starr8@rocketmail.com
A78: 45950 | B78: Morgan N. | C78: None | D78: Labor | E78: Working Interview | F78: 2 | G78: 30 | I78: 0 | J78: 15 | K78: 30 | L78: Cash App | M78: 6116 | N78: 1 | P78: 78208C | Q78: starr8@rocketmail.com
A79: 45908 | B79: Amazon | C79: Bonide | D79: Treatments & Fertilizers | E79: Systemic insect control granules | F79: 1 | G79: 19.48 | I79: 1.94 | J79: 17.54 | K79: 17.54 | L79: Credit Card | M79: 0590 | P79: AF9A3D | Q79: starr8@rocketmail.com
A80: 45914 | B80: Amazon | C80: Bonide | D80: Treatments & Fertilizers | E80: Systemic insect control granules | F80: 1 | G80: 33.16 | J80: 33.16 | K80: 33.16 | L80: ACH | M80: 488 | P80: E713EE | Q80: starr8@rocketmail.com
A81: 45921 | B81: Amazon | C81: Zenfun | D81: Bags & Packaging | E81: Wine gift bags with window | F81: 1 | G81: 20.99 | J81: 20.99 | K81: 20.99 | L81: Credit Card | M81: 9565 | P81: 1E8D9F | Q81: starr8@rocketmail.com
A82: 45921 | B82: Amazon | C82: Hondawan | D82: Bags & Packaging | E82: Wine gift bags with window | F82: 1 | G82: 31.99 | J82: 31.99 | K82: 31.99 | L82: Credit Card | M82: 9565 | P82: 560750 | Q82: starr8@rocketmail.com
A83: 45923 | B83: Amazon | C83: MDPQT | D83: Soil & Amendments | E83: 50 QT Perlite | F83: 1 | G83: 49.99 | J83: 49.99 | K83: 49.99 | L83: Credit Card | M83: 9565 | P83: 8D8101 | Q83: starr8@rocketmail.com
A84: 45923 | B84: Amazon | C84: MDPQT | D84: Soil & Amendments | E84: 50 QT Perlite | F84: 1 | G84: 49.99 | J84: 49.99 | K84: 49.99 | L84: Credit Card | M84: 9565 | P84: C4FAB2 | Q84: starr8@rocketmail.com
A85: 45923 | B85: Amazon | C85: Legigo | D85: Soil & Amendments | E85: Orchid bark | F85: 1 | G85: 28.99 | J85: 28.99 | K85: 28.99 | L85: Credit Card | M85: 9565 | P85: FC7463 | Q85: starr8@rocketmail.com
A86: 45922 | B86: Amazon | C86: Bonide | D86: Treatments & Fertilizers | E86: Systemic insect control granules | F86: 1 | G86: 33.47 | I86: 1.2 | J86: 32.27 | K86: 32.27 | L86: Credit Card | M86: 9565 | P86: 33EE14 | Q86: starr8@rocketmail.com
A87: 45924 | B87: Amazon | C87: JRD | D87: Tools & Supplies | E87: Warm & cool mist humidifier | F87: 1 | G87: 59.98 | J87: 59.98 | K87: 59.98 | L87: Credit Card | M87: 9565 | P87: 6B67C5 | Q87: starr8@rocketmail.com
A88: 45924 | B88: Amazon | C88: gegemaoyi | D88: Tools & Supplies | E88: Plastic watering can | F88: 1 | G88: 17.98 | J88: 17.98 | K88: 17.98 | L88: Credit Card | M88: 9565 | P88: A2E176 | Q88: starr8@rocketmail.com
A89: 45925 | B89: Amazon | C89: Shiiajina | D89: Tools & Supplies | E89: shelf liner | F89: 1 | G89: 39.99 | J89: 39.99 | K89: 39.99 | L89: Credit Card | M89: 1002 | P89: DA5B27 | Q89: starr8@rocketmail.com
A90: 45926 | B90: Amazon | C90: Bonide | D90: Treatments & Fertilizers | E90: Systemic insect control granules | F90: 16 | G90: 116.16 | J90: 7.26 | K90: 116.16 | L90: Credit Card | M90: 5770 | P90: 11D4D8 | Q90: starr8@rocketmail.com
A91: 45927 | B91: Amazon | C91: xiaohulipin | D91: Labels & Stickers | E91: Stickers | F91: 1 | G91: 38.99 | I91: 11.51 | J91: 27.48 | K91: 27.48 | L91: Credit Card | M91: 0590 | P91: 494E89 | Q91: starr8@rocketmail.com
A92: 45929 | B92: Amazon | C92: Home Tex | D92: Packing & Shipping | E92: Polyester pillow stuffing | F92: 1 | G92: 26.94 | J92: 26.94 | K92: 26.94 | L92: Credit Card | M92: 0590 | P92: 80C83A | Q92: starr8@rocketmail.com
A93: 45929 | B93: Amazon | C93: Aspamms | D93: Packing & Shipping | E93: Packing air pillows | F93: 1 | G93: 16.99 | J93: 16.99 | K93: 16.99 | L93: Credit Card | M93: 0590 | P93: B841EB | Q93: starr8@rocketmail.com
A94: 45929 | B94: Amazon | C94: Xavier Optimization | D94: Packing & Shipping | E94: Packing air pillows | F94: 1 | G94: 17.99 | J94: 17.99 | K94: 17.99 | L94: Credit Card | M94: 0590 | P94: EFBB9C | Q94: starr8@rocketmail.com
A95: 45929 | B95: Amazon | C95: Union Sales | D95: Packing & Shipping | E95: Heavy duty shipping tape | F95: 1 | G95: 11.38 | J95: 11.38 | K95: 11.38 | L95: Credit Card | M95: 0590 | P95: 27354D | Q95: starr8@rocketmail.com
A96: 45929 | B96: Amazon | C96: Amazon | D96: Packing & Shipping | E96: Stretch wrap roll | F96: 1 | G96: 12.6 | J96: 12.6 | K96: 12.6 | L96: Credit Card | M96: 0590 | P96: 5EAEFE | Q96: starr8@rocketmail.com
A97: 45929 | B97: Amazon | C97: wootile | D97: Labels & Stickers | E97: Stickers | F97: 1 | G97: 8.29 | J97: 8.29 | K97: 8.29 | L97: Credit Card | M97: 0590 | P97: 9628AF | Q97: starr8@rocketmail.com
A98: 45929 | B98: Amazon | C98: MUUZLL | D98: Tools & Supplies | E98: Bonsai pruning scissors | F98: 1 | G98: 4.99 | I98: 1.37 | J98: 3.62 | K98: 3.62 | L98: Credit Card | M98: 0590 | P98: CDA260 | Q98: starr8@rocketmail.com
A99: 45929 | B99: Amazon | C99: US.K M | D99: Treatments & Fertilizers | E99: Yellow sticky fungus gnat traps | F99: 1 | G99: 9.99 | J99: 9.99 | K99: 9.99 | L99: Credit Card | M99: 0590 | P99: 051C11 | Q99: starr8@rocketmail.com
A100: 45929 | B100: Amazon | C100: Maxguard | D100: Treatments & Fertilizers | E100: Clear window fly traps | F100: 1 | G100: 15.95 | J100: 15.95 | K100: 15.95 | L100: Credit Card | M100: 0590 | P100: 3C95C2 | Q100: starr8@rocketmail.com
...

Sheet Overhead KEY
B1: VENDOR | C1: BRAND | D1: CATEGORY | E1: DESCRIPTION | F1: Pmt. Method | G1: Card #
B2: Amazon | C2: AIMFIKIOR | D2: Bags & Packaging | E2: Acrylic brochure holders | F2: ACH | G2: 0590
B3: Dawn W. | C3: Amano Studio | D3: Cash & POS | E3: Acrylic sign holders (multiple sizes) | F3: Credit Card | G3: 1002
B4: Faire | C4: AojSup | D4: Cleaning & Sanitation | E4: Adjustable halo grow lights | F4: Cash | G4: 3150
B5: Fields | C5: Aokrean | D5: Climate & Environment | E5: Air layering propagation pods | F5: Cash App | G5: 5770
B6: Fred Meyer | C6: Arcadia Garden Products | D6: Fuel | E6: Assistant | F6: Other | G6: 6116
B7: Home Depot | C7: Aspamms | D7: Inbound Shipping | E7: Black shade cloth tarp | F7: PayPal | G7: 9565
B8: Palm Street | C8: Aura Rooted | D8: Labels & Stickers | E8: Bluetooth hygrometers | F8: Square | G8: UI
B9: Temu | C9: Avery | D9: Labor | E9: Bonsai pruning scissors | F9: Venmo | G9: 6921
B10: TikTok | C10: Axle Rose Co | D10: Lighting | E10: Castile liquid soap | F10: Zelle
B11: Walmart | C11: Barrina | D11: Market Fees & Supplies | E11: Clear acrylic business card holders | F11: Promotional Credit
C12: Barydat | D12: Office & Admin Supplies | E12: Clear drawer organizer set | F12: Gift Certificate
C13: Berkland | D13: Outbound Shipping | E13: Clear window fly traps | F13: Debit Card
C14: Best Plant Friend | D14: Packing & Shipping | E14: Custom waterproof vinyl stickers | F14: Unpaid Invoice
C15: Bleidruck | D15: Plant Supports | E15: Folding table with adjustable height
C16: Bonide | D16: Plant Tags & Labels | E16: Frosted plastic shelf liners
C17: Brandon The Plant Guy | D17: Professional Services | E17: Glossy photo paper
C18: BWH Plant Company | D18: Propagation Supplies | E18: Glossy white address sticker labels
C19: Dicks Sticks & Exotics | D19: Rent | E19: Half-sheet adhesive shipping labels
C20: Dr. Bronner's | D20: Repairs & Maintenance | E20: Heavy duty shipping tape
C21: Duck | D21: Shade & Protection | E21: Heavy duty wire shelving rack
C22: EnHomee | D22: Shelving/Fixtures | E22: Honeycomb packing paper roll
C23: Epic Medical Supply | D23: Soil & Amendments | E23: Horticultural perlite and vermiculite
C24: EXPO | D24: Stationery & Print | E24: Houseplant fertilizer
C25: Facebook Marketplace | D25: Table Covers & Displays | E25: Hydrogen peroxide (bulk)
C26: Fam Plants | D26: Tables & Furniture | E26: Isopropyl alcohol (bulk)
... C30: gegemaoyi | D30: Uniforms & Workwear | E30: Key Chains
C31: Generic | E31: Kraft paper gift bags with window
C32: Geyoga | E32: Large T-type plastic plant labels
C33: Govee | E33: LED grow light bar set
C34: HIIMIEI | E34: Live plant shipping stickers
C35: HNXTYAOB | E35: Live Plants
C36: Home Stock | E36: Locking cash box
C37: Hometex Canada | E37: Magnetic whiteboard labels
C38: Homvana | E38: Medium T-shape plastic plant tags
C39: It's a Succulent Thang | E39: Microfiber dusting gloves
C40: JRD | E40: Mini acrylic display easels
C41: Jumanji Jon Plants | E41: Mini plastic nursery pots
C42: Jungle Club | E42: Orchid bark
... C73: Technaflora | E73: Heavy duty wire shelving rack w/ lights
C74: The Amazing Garden
C75: The Gay Ole Plant Shop
C76: The Green Escape
C77: The Lady Cove
C78: Thorsen's Greenhouse
C79: Tiny Plant Market
C80: Totally Rooted LLC
C81: Toyosport
C82: TPS NUTRIENTS
C83: Ts Garden Gems
C84: USKICH
C85: Voulosimi
... C96: Zen Botanicals

Sheet Transplant Log
A2: Date | B2: Original SKU | C2: Action | D2: Media | E2: From Pot | F2: To Pot | G2: ID | H2: Division SKU | I2: $ PER | J2: POT COLOR | K2: U ID | L2: Notes | M2: Created At | N2: Owner Email | O2: Add On | P2: Photo | Q2: Plant Name | S2: MSRP
A3: 45885 | B3: HS-PO-GO-1A | C3: Cutting | D3: CM 1 | F3: DV-PO-2-WH-1 | G3: H | H3: HS-PO-GO-1H | I3: =IFERROR(__xludf.DUMMYFUNCTION("ARRAYFORMULA( IF(B3:B987="""","""", LET( dateCol, A3:A987, toPotCol, TRIM(F3:F987), origSKU, TRIM(B3:B987), action, TRIM(C3:C987), sku, TRIM(H3:H987), createdAtCol, INDEX($A$3:$Z$987,, MATCH(""Created At"",$A$2:$Z$2,0)), parentSKU, "&"IF( REGEXMATCH(sku,""-1[A-Z]$""), REGEXREPLACE(sku,""[A-Z]$"",""A""), IF( REGEXMATCH(sku,""[A-Za-z]$""), REGEXREPLACE(sku,""[A-Za-z]$"",""""), sku ) ), rowNums, SEQUENCE(ROWS(origSKU)),"&" baseCost, IFERROR( VLOOKUP( parentSKU, {TRIM('PLANT Intake Coding'!F3:F3063),'PLANT Intake Coding'!G3:G3063}, 2, FALSE ), """" ), isDiv, (action=""Tran/Div"") + (action=""Division""), divCou"&"nt, MAP( rowNums, LAMBDA(r, IF( INDEX(isDiv,r), COUNTIFS( parentSKU, INDEX(parentSKU,r), isDiv, 1 ), """" ) ) ), divCost, IF( isDiv, "&" IF(divCount>0, baseCost / divCount, baseCost), """" ), carryDivCost, MAP( rowNums, LAMBDA(r, IFERROR( LOOKUP( 2, 1/( (parentSKU=INDEX(parentSKU,r)) * (isDi"&"v=1) * (rowNums<=r) * (divCost<>"""") ), divCost ), INDEX(baseCost,r) ) ) ), isComb, (action=""Tran/Comb"") + (action=""Combined""), rowCostComb, IF( i"&"sComb, IFERROR( VLOOKUP( origSKU, {TRIM('PLANT Intake Coding'!F3:F3063),'PLANT Intake Coding'!G3:G3063}, 2, FALSE ), 0 ), 0 ), combStamp, MAP( rowNums, "&" LAMBDA(r, IF( INDEX(action,r)=""Tran/Comb"", INDEX(createdAtCol,r), IF( INDEX(action,r)=""Combined"", IFERROR( LOOKUP( 2, 1/( (a"&"ction=""Tran/Comb"") * (dateCol=INDEX(dateCol,r)) * (createdAtCol<=INDEX(createdAtCol,r)) ), createdAtCol ), """" ), """" ) "&" ) ) ), totalCombCost, MAP( rowNums, LAMBDA(r, IF( INDEX(action,r)=""Tran/Comb"", INDEX(rowCostComb,r) + SUM( FILTER( rowCostComb, (action=""Co"&"mbined"") * (dateCol=INDEX(dateCol,r)) * (combStamp=INDEX(createdAtCol,r)) ) ), """" ) ) ), result, IF( isComb, IF(action=""Tran/Comb"", totalCombCost, """")"&", IF(isDiv, divCost, carryDivCost) ), result )))"),0.0) -> 0 | J3: White | K3: 43C0AB | N3: starr8@rocketmail.com | Q3: Pothos Golden | S3: =IFERROR(__xludf.DUMMYFUNCTION("ARRAYFORMULA( IF(B3:B987="""","""", LET( dateCol, A3:A987, origSKU, TRIM(B3:B987), action, TRIM(C3:C987), sku, TRIM(H3:H987), createdAtCol, INDEX($A$3:$Z$987,, MATCH(""Created At"",$A$2:$Z$2,0)), parentSKU, IF( REGEXMATCH(sku,""-1[A"&"-Z]$""), REGEXREPLACE(sku,""[A-Z]$"",""A""), IF( REGEXMATCH(sku,""[A-Za-z]$""), REGEXREPLACE(sku,""[A-Za-z]$"",""""), sku ) ), rowNums, SEQUENCE(ROWS(origSKU)), baseMSRP, IFERROR( "&" VLOOKUP( parentSKU, {TRIM('PLANT Intake Coding'!F3:F3063),'PLANT Intake Coding'!K3:K3063}, 2, FALSE ), """" ), isDiv, (action=""Tran/Div"") + (action=""Division""), divCount, MAP( rowNums,"&" LAMBDA(r, IF( INDEX(isDiv,r), COUNTIFS( parentSKU, INDEX(parentSKU,r), isDiv, 1 ), """" ) ) ), divMSRP, IF( isDiv, IF(divCount>0, baseMSRP "&"/ divCount, baseMSRP), """" ), carryDivMSRP, MAP( rowNums, LAMBDA(r, IFERROR( LOOKUP( 2, 1/( (parentSKU=INDEX(parentSKU,r)) * (isDiv=1) * (row"&"Nums<=r) * (divMSRP<>"""") ), divMSRP ), INDEX(baseMSRP,r) ) ) ), isComb, (action=""Tran/Comb"") + (action=""Combined""), rowMSRPComb, IF( isComb, IFERROR( "&" VLOOKUP( origSKU, {TRIM('PLANT Intake Coding'!F3:F3063),'PLANT Intake Coding'!K3:K3063}, 2, FALSE ), 0 ), 0 ), combStamp, MAP( rowNums, LAMBDA(r, IF("&" INDEX(action,r)=""Tran/Comb"", INDEX(createdAtCol,r), IF( INDEX(action,r)=""Combined"", IFERROR( LOOKUP( 2, 1/( (action=""Tran/Comb"") *"&" (dateCol=INDEX(dateCol,r)) * (createdAtCol<=INDEX(createdAtCol,r)) ), createdAtCol ), """" ), """" ) ) ) )"&", totalCombMSRP, MAP( rowNums, LAMBDA(r, IF( INDEX(action,r)=""Tran/Comb"", INDEX(rowMSRPComb,r) + SUM( FILTER( rowMSRPComb, (action=""Combined"") * "&" (dateCol=INDEX(dateCol,r)) * (combStamp=INDEX(createdAtCol,r)) ) ), """" ) ) ), result, IF( isComb, IF(action=""Tran/Comb"", totalCombMSRP, """"), IF(isDiv, "&"divMSRP, carryDivMSRP) ), result )))"),"")
A4: 45885 | B4: TGOPS-PH-PPM-1A-2 | C4: Transplant | D4: CM 1 | F4: TE-PO-4-MU-1 | G4: * | H4: TGOPS-PH-PPM-1A-2 | I4: =IFERROR(__xludf.DUMMYFUNCTION("""COMPUTED_VALUE"""),16.19) -> 16.19 | J4: Pink | K4: CC96EB | N4: starr8@rocketmail.com | Q4: Philodendron Pink Princess Marbled | S4: =IFERROR(__xludf.DUMMYFUNCTION("""COMPUTED_VALUE"""),26.99) -> 26.99
A5: 45885 | B5: TOGPS-PH-POO-1A-2 | C5: Transplant | D5: CM 1 | F5: TE-PO-4-MU-1 | G5: * | H5: TOGPS-PH-POO-1A-2 | I5: =IFERROR(__xludf.DUMMYFUNCTION("""COMPUTED_VALUE"""),"") | J5: Orange | K5: F6776B | N5: starr8@rocketmail.com | S5: =IFERROR(__xludf.DUMMYFUNCTION("""COMPUTED_VALUE"""),"")
A6: 45891 | B6: FMY-MA-DE-1A-4 | C6: Tran/Div | D6: CM 2 | E6: GA-PO-4-BL-1 | F6: WO-PO-6-MU-1 | G6: * | H6: FMY-MA-DE-1A-4 | I6: =IFERROR(__xludf.DUMMYFUNCTION("""COMPUTED_VALUE"""),1.57) -> 1.57 | J6: White | K6: 23A2B2 | N6: starr8@rocketmail.com | Q6: Monstera Deliciosa | S6: =IFERROR(__xludf.DUMMYFUNCTION("""COMPUTED_VALUE"""),0.0) -> 0
A7: 45891 | B7: FMY-MA-DE-1A-4 | C7: Division | D7: CM 2 | F7: GA-PO-6-MU-1 | G7: A | H7: FMY-MA-DE-1A-4A | I7: =IFERROR(__xludf.DUMMYFUNCTION("""COMPUTED_VALUE"""),1.57) -> 1.57 | J7: Peach | K7: 785D7D | N7: starr8@rocketmail.com | Q7: Monstera Deliciosa | S7: =IFERROR(__xludf.DUMMYFUNCTION("""COMPUTED_VALUE"""),0.0) -> 0
A8: 45891 | B8: FMY-MA-DE-1A-4 | C8: Division | D8: CM 2 | F8: GA-PO-6-MU-1 | G8: B | H8: FMY-MA-DE-1A-4B | I8: =IFERROR(__xludf.DUMMYFUNCTION("""COMPUTED_VALUE"""),1.57) -> 1.57 | J8: Pink | K8: 1130EE | N8: starr8@rocketmail.com | Q8: Monstera Deliciosa | S8: =IFERROR(__xludf.DUMMYFUNCTION("""COMPUTED_VALUE"""),0.0) -> 0
A9: 45891 | B9: FMY-MA-DE-1A-4 | C9: Division | D9: CM 2 | F9: TE-PO-4-MU-1 | G9: C | H9: FMY-MA-DE-1A-4C | I9: =IFERROR(__xludf.DUMMYFUNCTION("""COMPUTED_VALUE"""),1.57) -> 1.57 | J9: Peach | K9: 38D790 | N9: starr8@rocketmail.com | Q9: Monstera Deliciosa | S9: =IFERROR(__xludf.DUMMYFUNCTION("""COMPUTED_VALUE"""),0.0) -> 0
A10: 45891 | B10: FMY-MA-DE-1A-4 | C10: Division | D10: CM 2 | F10: TE-PO-4-MU-1 | G10: D | H10: FMY-MA-DE-1A-4D | I10: =IFERROR(__xludf.DUMMYFUNCTION("""COMPUTED_VALUE"""),1.57) -> 1.57 | J10: Purple | K10: 695B04 | N10: starr8@rocketmail.com | Q10: Monstera Deliciosa | S10: =IFERROR(__xludf.DUMMYFUNCTION("""COMPUTED_VALUE"""),0.0) -> 0
A11: 45891 | B11: FMY-MA-DE-1A-4 | C11: Division | D11: CM 2 | F11: TE-PO-4-MU-1 | G11: E | H11: FMY-MA-DE-1A-4E | I11: =IFERROR(__xludf.DUMMYFUNCTION("""COMPUTED_VALUE"""),1.57) -> 1.57 | J11: Sage | K11: F277AE | N11: starr8@rocketmail.com | Q11: Monstera Deliciosa | S11: =IFERROR(__xludf.DUMMYFUNCTION("""COMPUTED_VALUE"""),0.0) -> 0
A12: 45891 | B12: FMY-MA-DE-1A-4 | C12: Division | D12: CM 2 | F12: DV-PO-2-WH-1 | G12: F | H12: FMY-MA-DE-1A-4F | I12: =IFERROR(__xludf.DUMMYFUNCTION("""COMPUTED_VALUE"""),1.57) -> 1.57 | J12: White | K12: CD8227 | N12: starr8@rocketmail.com | Q12: Monstera Deliciosa | S12: =IFERROR(__xludf.DUMMYFUNCTION("""COMPUTED_VALUE"""),0.0) -> 0
A13: 45891 | B13: FMY-MA-DE-1A-3 | C13: Tran/Div | D13: CM 2 | F13: TE-PO-4-MU-1 | G13: * | H13: FMY-MA-DE-1A-3 | I13: =IFERROR(__xludf.DUMMYFUNCTION("""COMPUTED_VALUE"""),3.3316666666666666) -> 3.3316667 | J13: Blue | K13: 5021CF | N13: starr8@rocketmail.com | Q13: Monstera Deliciosa | S13: =IFERROR(__xludf.DUMMYFUNCTION("""COMPUTED_VALUE"""),0.0) -> 0
A14: 45891 | B14: FMY-MA-DE-1A-3 | C14: Division | D14: CM 2 | F14: ZO-PO-4-WL-1 | G14: A | H14: FMY-MA-DE-1A-3A | I14: =IFERROR(__xludf.DUMMYFUNCTION("""COMPUTED_VALUE"""),3.3316666666666666) -> 3.3316667 | J14: Blue | K14: 34416A | N14: starr8@rocketmail.com | Q14: Monstera Deliciosa | S14: =IFERROR(__xludf.DUMMYFUNCTION("""COMPUTED_VALUE"""),0.0) -> 0
A15: 45891 | B15: FMY-MA-DE-1A-3 | C15: Division | D15: CM 2 | F15: ZO-PO-4-WL-1 | G15: B | H15: FMY-MA-DE-1A-3B | I15: =IFERROR(__xludf.DUMMYFUNCTION("""COMPUTED_VALUE"""),3.3316666666666666) -> 3.3316667 | J15: Orange | K15: 684FBF | N15: starr8@rocketmail.com | Q15: Monstera Deliciosa | S15: =IFERROR(__xludf.DUMMYFUNCTION("""COMPUTED_VALUE"""),0.0) -> 0
A16: 45891 | B16: FMY-MA-DE-1A-3 | C16: Division | D16: CM 2 | F16: ZO-PO-4-WL-1 | G16: C | H16: FMY-MA-DE-1A-3C | I16: =IFERROR(__xludf.DUMMYFUNCTION("""COMPUTED_VALUE"""),3.3316666666666666) -> 3.3316667 | J16: Sage | K16: E36260 | N16: starr8@rocketmail.com | Q16: Monstera Deliciosa | S16: =IFERROR(__xludf.DUMMYFUNCTION("""COMPUTED_VALUE"""),0.0) -> 0
A17: 45891 | B17: FMY-MA-DE-1A-3 | C17: Division | D17: CM 2 | F17: ZO-PO-4-WL-1 | G17: D | H17: FMY-MA-DE-1A-3D | I17: =IFERROR(__xludf.DUMMYFUNCTION("""COMPUTED_VALUE"""),3.3316666666666666) -> 3.3316667 | J17: Orange | K17: AF3A4B | N17: starr8@rocketmail.com | Q17: Monstera Deliciosa | S17: =IFERROR(__xludf.DUMMYFUNCTION("""COMPUTED_VALUE"""),0.0) -> 0
A18: 45891 | B18: FMY-MA-DE-1A-3 | C18: Division | D18: CM 2 | F18: AN-PO-3-MU-1 | G18: E | H18: FMY-MA-DE-1A-3E | I18: =IFERROR(__xludf.DUMMYFUNCTION("""COMPUTED_VALUE"""),3.3316666666666666) -> 3.3316667 | J18: Pink | K18: 11AE36 | N18: starr8@rocketmail.com | Q18: Monstera Deliciosa | S18: =IFERROR(__xludf.DUMMYFUNCTION("""COMPUTED_VALUE"""),0.0) -> 0
I19: =IFERROR(__xludf.DUMMYFUNCTION("""COMPUTED_VALUE"""),"") | N19: starr8@rocketmail.com | S19: =IFERROR(__xludf.DUMMYFUNCTION("""COMPUTED_VALUE"""),"")
A20: 45896 | B20: HD-AL-LO-1A-2 | C20: Tran/Div | D20: CM 1 | F20: PS-PO-5.5-MU-1 | G20: * | H20: HD-AL-LO-1A-2 | I20: =IFERROR(__xludf.DUMMYFUNCTION("""COMPUTED_VALUE"""),9.993333333333334) -> 9.9933333 | J20: Pink | K20: 2346E2 | N20: starr8@rocketmail.com | Q20: Alocasia Longiloba | S20: =IFERROR(__xludf.DUMMYFUNCTION("""COMPUTED_VALUE"""),0.0) -> 0
A21: 45896 | B21: HD-AL-LO-1A-2 | C21: Division | D21: CM 2 | F21: AN-PO-3-MU-1 | G21: B | H21: HD-AL-LO-1A-2B | I21: =IFERROR(__xludf.DUMMYFUNCTION("""COMPUTED_VALUE"""),9.993333333333334) -> 9.9933333 | J21: Purple | K21: EE2B66 | N21: starr8@rocketmail.com | Q21: Alocasia Longiloba | S21: =IFERROR(__xludf.DUMMYFUNCTION("""COMPUTED_VALUE"""),0.0) -> 0
A22: 45896 | B22: HD-AL-LO-1A-2 | C22: Division | D22: CM 2 | F22: DV-PO-2-WH-1 | G22: C | H22: HD-AL-LO-1A-2C | I22: =IFERROR(__xludf.DUMMYFUNCTION("""COMPUTED_VALUE"""),9.993333333333334) -> 9.9933333 | J22: White | K22: E60350 | N22: starr8@rocketmail.com | Q22: Alocasia Longiloba | S22: =IFERROR(__xludf.DUMMYFUNCTION("""COMPUTED_VALUE"""),0.0) -> 0
A23: 45889 | B23: HS-DR-SP-1A | C23: Tran/Div | D23: CM 1 | F23: TE-PO-4-MU-3 | G23: * | H23: HS-DR-SP-1A | I23: =IFERROR(__xludf.DUMMYFUNCTION("""COMPUTED_VALUE"""),0.0) -> 0 | J23: White | K23: 5C58A3 | N23: starr8@rocketmail.com | Q23: Dracaena Snake Plant | S23: =IFERROR(__xludf.DUMMYFUNCTION("""COMPUTED_VALUE"""),0.0) -> 0
I24: =IFERROR(__xludf.DUMMYFUNCTION("""COMPUTED_VALUE"""),"") | N24: starr8@rocketmail.com | S24: =IFERROR(__xludf.DUMMYFUNCTION("""COMPUTED_VALUE"""),"")
A25: 45885 | B25: HS-PH-HL-1A | C25: Cutting | D25: CM 1 | F25: TE-PO-4-MU-1 | G25: B | H25: HS-PH-HL-1B | I25: =IFERROR(__xludf.DUMMYFUNCTION("""COMPUTED_VALUE"""),0.0) -> 0 | J25: Black | K25: ABFC93 | N25: starr8@rocketmail.com | Q25: Philodendron Heart Leaf
A26: 45885 | B26: HS-PH-HL-1A | C26: Cutting | D26: CM 1 | E26: TE-PO-4-MU-1 | F26: TE-PO-4-MU-1 | G26: C | H26: HS-PH-HL-1C | I26: =IFERROR(__xludf.DUMMYFUNCTION("""COMPUTED_VALUE"""),0.0) -> 0 | J26: Pink | K26: E7090F | N26: starr8@rocketmail.com | Q26: Philodendron Heart Leaf
A27: 45886 | B27: HD-AL-LO-1A | C27: Tran/Div | D27: CM 1 | F27: WO-PO-6-MU-1 | G27: * | H27: HD-AL-LO-1A | I27: =IFERROR(__xludf.DUMMYFUNCTION("""COMPUTED_VALUE"""),7.495) -> 7.495 | J27: White | K27: D71E81 | N27: starr8@rocketmail.com | Q27: Alocasia Longiloba | S27: =IFERROR(__xludf.DUMMYFUNCTION("""COMPUTED_VALUE"""),0.0) -> 0
A28: 45886 | B28: HD-AL-LO-1A | C28: Division | D28: CM 1 | F28: WO-PO-6-MU-1 | G28: B | H28: HD-AL-LO-1B | I28: =IFERROR(__xludf.DUMMYFUNCTION("""COMPUTED_VALUE"""),7.495) -> 7.495 | J28: White | K28: 9E6AF9 | N28: starr8@rocketmail.com | Q28: Alocasia Longiloba | S28: =IFERROR(__xludf.DUMMYFUNCTION("""COMPUTED_VALUE"""),0.0) -> 0
A29: 45888 | B29: HS-PI-PEP-1A | C29: Division | D29: CM 1 | F29: AN-PO-3-MU-1 | G29: C | H29: HS-PI-PEP-1C | I29: =IFERROR(__xludf.DUMMYFUNCTION("""COMPUTED_VALUE"""),0.0) -> 0 | J29: Yellow | K29: 87AB59 | N29: starr8@rocketmail.com | Q29: Pilea Peperomioides | S29: =IFERROR(__xludf.DUMMYFUNCTION("""COMPUTED_VALUE"""),0.0) -> 0
A30: 45889 | B30: BWH-PH-MO-1A-2 | C30: Transplant | D30: CM 1 | E30: NR-PO-5-PBP-1 | F30: TE-PO-4-MU-1 | G30: * | H30: BWH-PH-MO-1A-2 | I30: =IFERROR(__xludf.DUMMYFUNCTION("""COMPUTED_VALUE"""),6.0) -> 6 | J30: Green | K30: 99264B | N30: starr8@rocketmail.com | Q30: Philodendron Moonlight | S30: =IFERROR(__xludf.DUMMYFUNCTION("""COMPUTED_VALUE"""),12.99) -> 12.99
B31: BWH-SYN-PS-1A-3 | C31: Transplant | D31: CM 1 | F31: TE-PO-4-MU-1 | G31: * | H31: BWH-SYN-PS-1A-3 | I31: =IFERROR(__xludf.DUMMYFUNCTION("""COMPUTED_VALUE"""),9.0) -> 9 | J31: Pink | K31: 7E0E13 | N31: starr8@rocketmail.com | Q31: Syngonium Pink Splash | S31: =IFERROR(__xludf.DUMMYFUNCTION("""COMPUTED_VALUE"""),19.99) -> 19.99
A32: 45889 | B32: BWH-PH-MO-1A-3 | C32: Transplant | D32: CM 1 | E32: NR-PO-5-PBP-1 | F32: TE-PO-4-MU-1 | G32: * | H32: BWH-PH-MO-1A-3 | I32: =IFERROR(__xludf.DUMMYFUNCTION("""COMPUTED_VALUE"""),6.0) -> 6 | J32: Green | K32: 7C15DB | N32: starr8@rocketmail.com | Q32: Philodendron Moonlight | S32: =IFERROR(__xludf.DUMMYFUNCTION("""COMPUTED_VALUE"""),12.99) -> 12.99
A33: 45889 | B33: BWH-PH-RAPK-1A-3 | C33: Transplant | D33: CM 1 | F33: GA-PO-6-MU-1 | G33: * | H33: BWH-PH-RAPK-1A-3 | I33: =IFERROR(__xludf.DUMMYFUNCTION("""COMPUTED_VALUE"""),10.2) -> 10.2 | J33: Pink | K33: FABD64 | N33: starr8@rocketmail.com | Q33: Philodendron Red Anderson Pink Knight | S33: =IFERROR(__xludf.DUMMYFUNCTION("""COMPUTED_VALUE"""),24.99) -> 24.99
A34: 45889 | B34: BWH-PH-RAPK-1A-4 | C34: Transplant | D34: CM 1 | F34: GA-PO-6-MU-1 | G34: * | H34: BWH-PH-RAPK-1A-4 | I34: =IFERROR(__xludf.DUMMYFUNCTION("""COMPUTED_VALUE"""),10.2) -> 10.2 | J34: White | K34: 5EF5A3 | N34: starr8@rocketmail.com | Q34: Philodendron Red Anderson Pink Knight | S34: =IFERROR(__xludf.DUMMYFUNCTION("""COMPUTED_VALUE"""),24.99) -> 24.99
A35: 45889 | B35: BWH-PH-RAPK-1A-5 | C35: Transplant | D35: CM 1 | F35: GA-PO-6-MU-1 | G35: * | H35: BWH-PH-RAPK-1A-5 | I35: =IFERROR(__xludf.DUMMYFUNCTION("""COMPUTED_VALUE"""),10.2) -> 10.2 | J35: Peach | K35: BF0ED9 | N35: starr8@rocketmail.com | Q35: Philodendron Red Anderson Pink Knight | S35: =IFERROR(__xludf.DUMMYFUNCTION("""COMPUTED_VALUE"""),24.99) -> 24.99
A36: 45889 | B36: AR-PH-WP-1A | C36: Transplant | D36: CM 2 | E36: NR-PO-5-BP-1 | F36: TE-PO-4-MU-1 | G36: * | H36: AR-PH-WP-1A | I36: =IFERROR(__xludf.DUMMYFUNCTION("""COMPUTED_VALUE"""),20.4) -> 20.4 | J36: White | K36: 8F7F95 | N36: starr8@rocketmail.com | Q36: Philodendron White Princess
A37: 45889 | B37: IST-PH-GCN-1A | C37: Transplant | D37: CM 2 | E37: ST-PO-4-NU-1 | F37: TE-PO-4-MU-1 | G37: * | H37: IST-PH-GCN-1A | I37: =IFERROR(__xludf.DUMMYFUNCTION("""COMPUTED_VALUE"""),25.0) -> 25 | J37: White | K37: 93DE88 | N37: starr8@rocketmail.com | Q37: Philodendron Green Congo Nuclear
A38: 45890 | B38: HS-PO-GO-1A | C38: Division | D38: CM 2 | F38: TE-PO-4-MU-1 | G38: I | H38: HS-PO-GO-1I | I38: =IFERROR(__xludf.DUMMYFUNCTION("""COMPUTED_VALUE"""),0.0) -> 0 | J38: Purple | K38: B515C2 | N38: starr8@rocketmail.com | Q38: Pothos Golden | S38: =IFERROR(__xludf.DUMMYFUNCTION("""COMPUTED_VALUE"""),0.0) -> 0
I39: =IFERROR(__xludf.DUMMYFUNCTION("""COMPUTED_VALUE"""),"") | S39: =IFERROR(__xludf.DUMMYFUNCTION("""COMPUTED_VALUE"""),"")
H40: HS-SPA-PLD-1F | I40: =IFERROR(__xludf.DUMMYFUNCTION("""COMPUTED_VALUE"""),"") | Q40: Spathiphyllum Peace Lily Domino | S40: =IFERROR(__xludf.DUMMYFUNCTION("""COMPUTED_VALUE"""),"")
I41: =IFERROR(__xludf.DUMMYFUNCTION("""COMPUTED_VALUE"""),"") | S41: =IFERROR(__xludf.DUMMYFUNCTION("""COMPUTED_VALUE"""),"")
A42: 45890 | B42: HS-PI-PEP-1A | C42: Division | D42: CM 2 | F42: AN-PO-3-MU-1 | G42: B | H42: HS-PI-PEP-1B | I42: =IFERROR(__xludf.DUMMYFUNCTION("""COMPUTED_VALUE"""),0.0) -> 0 | J42: Blue | K42: EDEE8B | N42: starr8@rocketmail.com | Q42: Pilea Peperomioides | S42: =IFERROR(__xludf.DUMMYFUNCTION("""COMPUTED_VALUE"""),0.0) -> 0
A43: 45890 | B43: WM-PH-WK-1A | C43: Division | D43: CM 2 | F43: HY-PO-3-DO-1 | G43: D | H43: WM-PH-WK-1D | I43: =IFERROR(__xludf.DUMMYFUNCTION("""COMPUTED_VALUE"""),4.9925) -> 4.9925 | J43: Clear | K43: 6EE62B | N43: starr8@rocketmail.com | Q43: Philodendron White Knight | S43: =IFERROR(__xludf.DUMMYFUNCTION("""COMPUTED_VALUE"""),0.0) -> 0
A44: 45890 | B44: BWH-PH-MO-1A | C44: Transplant | D44: CM 2 | E44: NR-PO-8-PBP-1 | F44: GA-PO-6-MU-1 | G44: * | H44: BWH-PH-MO-1A | I44: =IFERROR(__xludf.DUMMYFUNCTION("""COMPUTED_VALUE"""),6.0) -> 6 | J44: White | K44: 613EAA | N44: starr8@rocketmail.com | Q44: Philodendron Moonlight | S44: =IFERROR(__xludf.DUMMYFUNCTION("""COMPUTED_VALUE"""),12.99) -> 12.99
A45: 45890 | B45: BWH-PH-MO-1A-4 | C45: Transplant | D45: CM 2 | F45: TE-PO-4-MU-1 | G45: * | H45: BWH-PH-MO-1A-4 | I45: =IFERROR(__xludf.DUMMYFUNCTION("""COMPUTED_VALUE"""),6.0) -> 6 | J45: Black | K45: 5736A5 | N45: starr8@rocketmail.com | Q45: Philodendron Moonlight | S45: =IFERROR(__xludf.DUMMYFUNCTION("""COMPUTED_VALUE"""),12.99) -> 12.99
A46: 45890 | B46: BWH-PH-MO-1A-5 | C46: Transplant | D46: CM 2 | F46: GA-PO-6-MU-1 | G46: * | H46: BWH-PH-MO-1A-5 | I46: =IFERROR(__xludf.DUMMYFUNCTION("""COMPUTED_VALUE"""),6.0) -> 6 | J46: Sage | K46: FA8110 | N46: starr8@rocketmail.com | Q46: Philodendron Moonlight | S46: =IFERROR(__xludf.DUMMYFUNCTION("""COMPUTED_VALUE"""),12.99) -> 12.99
A47: 45890 | B47: BWH-SYN-PS-1A | C47: Transplant | D47: CM 2 | F47: TE-PO-4-MU-1 | G47: * | H47: BWH-SYN-PS-1A | I47: =IFERROR(__xludf.DUMMYFUNCTION("""COMPUTED_VALUE"""),9.0) -> 9 | J47: White | K47: 74C422 | N47: starr8@rocketmail.com | Q47: Syngonium Pink Splash | S47: =IFERROR(__xludf.DUMMYFUNCTION("""COMPUTED_VALUE"""),19.99) -> 19.99
A48: 45890 | B48: BWH-SYN-PS-1A-2 | C48: Transplant | D48: CM 2 | F48: TE-PO-4-MU-1 | G48: * | H48: BWH-SYN-PS-1A-2 | I48: =IFERROR(__xludf.DUMMYFUNCTION("""COMPUTED_VALUE"""),9.0) -> 9 | J48: Peach | K48: 528FD8 | N48: starr8@rocketmail.com | Q48: Syngonium Pink Splash | S48: =IFERROR(__xludf.DUMMYFUNCTION("""COMPUTED_VALUE"""),19.99) -> 19.99
A49: 45890 | B49: BWH-SYN-PS-1A-4 | C49: Transplant | D49: CM 2 | F49: TE-PO-4-MU-1 | G49: * | H49: BWH-SYN-PS-1A-4 | I49: =IFERROR(__xludf.DUMMYFUNCTION("""COMPUTED_VALUE"""),9.0) -> 9 | J49: Purple | K49: FFC691 | N49: starr8@rocketmail.com | Q49: Syngonium Pink Splash | S49: =IFERROR(__xludf.DUMMYFUNCTION("""COMPUTED_VALUE"""),19.99) -> 19.99
A50: 45890 | B50: BWH-SYN-PS-1A-5 | C50: Transplant | D50: CM 2 | F50: TE-PO-4-MU-1 | G50: * | H50: BWH-SYN-PS-1A-5 | I50: =IFERROR(__xludf.DUMMYFUNCTION("""COMPUTED_VALUE"""),9.0) -> 9 | J50: Green | K50: 56342F | N50: starr8@rocketmail.com | Q50: Syngonium Pink Splash | S50: =IFERROR(__xludf.DUMMYFUNCTION("""COMPUTED_VALUE"""),19.99) -> 19.99
A51: 45890 | B51: BWH-PO-PAJ-1A-4 | C51: Tran/Div | D51: CM 2 | F51: TE-PO-4-MU-1 | G51: * | H51: BWH-PO-PAJ-1A-4 | I51: =IFERROR(__xludf.DUMMYFUNCTION("""COMPUTED_VALUE"""),1.95) -> 1.95 | J51: Tan | K51: 4EA2F5 | N51: starr8@rocketmail.com | Q51: Pothos Pearls and Jade | S51: =IFERROR(__xludf.DUMMYFUNCTION("""COMPUTED_VALUE"""),4.2475) -> 4.2475
A52: 45890 | B52: BWH-PO-PAJ-1A-4 | C52: Division | D52: CM 2 | F52: DV-PO-2-WH-1 | G52: A | H52: BWH-PO-PAJ-1A-4A | I52: =IFERROR(__xludf.DUMMYFUNCTION("""COMPUTED_VALUE"""),1.95) -> 1.95 | J52: White | K52: D10638 | N52: starr8@rocketmail.com | Q52: Pothos Pearls and Jade | S52: =IFERROR(__xludf.DUMMYFUNCTION("""COMPUTED_VALUE"""),4.2475) -> 4.2475
A53: 45890 | B53: BWH-PO-PAJ-1A-4 | C53: Division | D53: CM 2 | F53: AN-PO-3-MU-1 | G53: B | H53: BWH-PO-PAJ-1A-4B | I53: =IFERROR(__xludf.DUMMYFUNCTION("""COMPUTED_VALUE"""),1.95) -> 1.95 | J53: Pink | K53: 7E5D05 | N53: starr8@rocketmail.com | Q53: Pothos Pearls and Jade | S53: =IFERROR(__xludf.DUMMYFUNCTION("""COMPUTED_VALUE"""),4.2475) -> 4.2475
A54: 45890 | B54: BWH-PO-PAJ-1A-4 | C54: Division | D54: CM 2 | F54: AN-PO-3-MU-1 | G54: C | H54: BWH-PO-PAJ-1A-4C | I54: =IFERROR(__xludf.DUMMYFUNCTION("""COMPUTED_VALUE"""),1.95) -> 1.95 | J54: Green | K54: B3EBB1 | N54: starr8@rocketmail.com | Q54: Pothos Pearls and Jade | S54: =IFERROR(__xludf.DUMMYFUNCTION("""COMPUTED_VALUE"""),4.2475) -> 4.2475
A55: 45890 | B55: BWH-PO-PAJ-1A-5 | C55: Transplant | D55: CM 2 | F55: GA-PO-6-MU-1 | G55: * | H55: BWH-PO-PAJ-1A-5 | I55: =IFERROR(__xludf.DUMMYFUNCTION("""COMPUTED_VALUE"""),7.8) -> 7.8 | J55: White | K55: 54EAC8 | N55: starr8@rocketmail.com | Q55: Pothos Pearls and Jade | S55: =IFERROR(__xludf.DUMMYFUNCTION("""COMPUTED_VALUE"""),16.99) -> 16.99
A56: 45891 | B56: FMY-MA-DE-1A-5 | C56: Tran/Div | D56: CM 2 | F56: GA-PO-6-MU-1 | G56: * | H56: FMY-MA-DE-1A-5 | I56: =IFERROR(__xludf.DUMMYFUNCTION("""COMPUTED_VALUE"""),2.7475) -> 2.7475 | J56: Sage | K56: 741911 | N56: starr8@rocketmail.com | Q56: Monstera Deliciosa | S56: =IFERROR(__xludf.DUMMYFUNCTION("""COMPUTED_VALUE"""),0.0) -> 0
A57: 45891 | B57: FMY-MA-DE-1A-5 | C57: Tran/Div | D57: CM 2 | E57: NR-PO-8-TBP-1 | F57: GA-PO-6-MU-1 | G57: B | H57: FMY-MA-DE-1A-5B | I57: =IFERROR(__xludf.DUMMYFUNCTION("""COMPUTED_VALUE"""),2.7475) -> 2.7475 | J57: White | K57: F4B97F | N57: starr8@rocketmail.com | Q57: Monstera Deliciosa | S57: =IFERROR(__xludf.DUMMYFUNCTION("""COMPUTED_VALUE"""),0.0) -> 0
A58: 45891 | B58: FMY-MA-DE-1A-5 | C58: Division | D58: CM 2 | F58: TE-PO-4-MU-1 | G58: C | H58: FMY-MA-DE-1A-5C | I58: =IFERROR(__xludf.DUMMYFUNCTION("""COMPUTED_VALUE"""),2.7475) -> 2.7475 | J58: Peach | K58: 3293D8 | N58: starr8@rocketmail.com | Q58: Monstera Deliciosa | S58: =IFERROR(__xludf.DUMMYFUNCTION("""COMPUTED_VALUE"""),0.0) -> 0
A59: 45891 | B59: FMY-MA-DE-1A-5 | C59: Division | D59: CM 2 | F59: AN-PO-3-MU-1 | G59: D | H59: FMY-MA-DE-1A-5D | I59: =IFERROR(__xludf.DUMMYFUNCTION("""COMPUTED_VALUE"""),2.7475) -> 2.7475 | J59: Blue | K59: BB4F55 | N59: starr8@rocketmail.com | Q59: Monstera Deliciosa | S59: =IFERROR(__xludf.DUMMYFUNCTION("""COMPUTED_VALUE"""),0.0) -> 0
A60: 45892 | B60: WM-PH-WK-1A | C60: Tran/Div | D60: CM 2 | F60: MU-PO-4-WH-1 | G60: * | H60: WM-PH-WK-1A | I60: =IFERROR(__xludf.DUMMYFUNCTION("""COMPUTED_VALUE"""),4.9925) -> 4.9925 | J60: White | K60: 38A14B | N60: starr8@rocketmail.com | Q60: Philodendron White Knight | S60: =IFERROR(__xludf.DUMMYFUNCTION("""COMPUTED_VALUE"""),0.0) -> 0
A61: 45892 | B61: WM-PH-WK-1A | C61: Division | D61: CM 2 | F61: MU-PO-4-WH-1 | G61: B | H61: WM-PH-WK-1B | I61: =IFERROR(__xludf.DUMMYFUNCTION("""COMPUTED_VALUE"""),4.9925) -> 4.9925 | J61: White | K61: 9B993E | N61: starr8@rocketmail.com | Q61: Philodendron White Knight | S61: =IFERROR(__xludf.DUMMYFUNCTION("""COMPUTED_VALUE"""),0.0) -> 0
A62: 45892 | B62: HD-ST-TR-1A | C62: Transplant | D62: CM 2 | F62: MU-PO-4-WH-1 | G62: * | H62: HD-ST-TR-1A | I62: =IFERROR(__xludf.DUMMYFUNCTION("""COMPUTED_VALUE"""),19.98) -> 19.98 | J62: White | K62: 16A72F | N62: starr8@rocketmail.com | Q62: Stromanthe Triostar
A63: 45892 | B63: HD-ST-TR-1A | C63: Tran/Div | D63: CM 2 | F63: TE-PO-4-MU-1 | G63: B | H63: HD-ST-TR-1B | I63: =IFERROR(__xludf.DUMMYFUNCTION("""COMPUTED_VALUE"""),9.99) -> 9.99 | J63: Purple | K63: DFDC56 | N63: starr8@rocketmail.com | Q63: Stromanthe Triostar | S63: =IFERROR(__xludf.DUMMYFUNCTION("""COMPUTED_VALUE"""),0.0) -> 0
A64: 45892 | B64: HD-ST-TR-1A | C64: Tran/Div | D64: CM 2 | F64: TE-PO-4-MU-1 | G64: C | H64: HD-ST-TR-1C | I64: =IFERROR(__xludf.DUMMYFUNCTION("""COMPUTED_VALUE"""),9.99) -> 9.99 | J64: Pink | K64: 7DE858 | N64: starr8@rocketmail.com | Q64: Stromanthe Triostar | S64: =IFERROR(__xludf.DUMMYFUNCTION("""COMPUTED_VALUE"""),0.0) -> 0
A65: 45892 | B65: HS-BE-AW-1A | C65: Transplant | D65: CM 2 | E65: ST-PO-12-NU-1 | F65: TO-PO-4-MU-1 | G65: F | H65: HS-BE-AW-1A | I65: =IFERROR(__xludf.DUMMYFUNCTION("""COMPUTED_VALUE"""),0.0) -> 0 | J65: Black | K65: CFE94D | N65: starr8@rocketmail.com | Q65: Begonia Angel Wing
I66: =IFERROR(__xludf.DUMMYFUNCTION("""COMPUTED_VALUE"""),"") | N66: starr8@rocketmail.com | S66: =IFERROR(__xludf.DUMMYFUNCTION("""COMPUTED_VALUE"""),"")
A67: 45892 | B67: HS-BE-AW-1A | C67: Transplant | D67: CM 2 | E67: TO-PO-4-MU-1 | F67: TO-PO-4-MU-1 | G67: H | H67: HS-BE-AW-1A | I67: =IFERROR(__xludf.DUMMYFUNCTION("""COMPUTED_VALUE"""),0.0) -> 0 | J67: White | K67: 1A53EA | N67: starr8@rocketmail.com | Q67: Begonia Angel Wing
A68: 45892 | B68: IST-PH-PP-1A | C68: Transplant | D68: CM 2 | E68: NR-PO-5-BP-1 | F68: MU-PO-4-WH-1 | G68: * | H68: IST-PH-PP-1A | I68: =IFERROR(__xludf.DUMMYFUNCTION("""COMPUTED_VALUE"""),10.8) -> 10.8 | J68: White | K68: 684EB4 | N68: starr8@rocketmail.com | Q68: Philodendron Pink Princess
A69: 45892 | B69: IST-PH-PP-1A | C69: Division | D69: CM 2 | F69: YA-PO-2-CL-1 | G69: B | H69: IST-PH-PP-1B | I69: =IFERROR(__xludf.DUMMYFUNCTION("""COMPUTED_VALUE"""),5.4) -> 5.4 | J69: Clear | K69: 670B78 | N69: starr8@rocketmail.com | Q69: Philodendron Pink Princess | S69: =IFERROR(__xludf.DUMMYFUNCTION("""COMPUTED_VALUE"""),0.0) -> 0
A70: 45892 | B70: IST-PH-PP-1A | C70: Division | D70: CM 2 | F70: YA-PO-2-CL-1 | G70: C | H70: IST-PH-PP-1C | I70: =IFERROR(__xludf.DUMMYFUNCTION("""COMPUTED_VALUE"""),5.4) -> 5.4 | J70: Clear | K70: 2226D4 | N70: starr8@rocketmail.com | Q70: Philodendron Pink Princess | S70: =IFERROR(__xludf.DUMMYFUNCTION("""COMPUTED_VALUE"""),0.0) -> 0
A71: 45892 | B71: HD-AL-GVF-1A | C71: Transplant | D71: CM 2 | F71: GA-PO-6-MU-1 | G71: * | H71: HD-AL-GVF-1A | I71: =IFERROR(__xludf.DUMMYFUNCTION("""COMPUTED_VALUE"""),"") | J71: Sage | K71: 4E7FD3 | N71: starr8@rocketmail.com | S71: =IFERROR(__xludf.DUMMYFUNCTION("""COMPUTED_VALUE"""),"")
A72: 45892 | B72: HD-AL-GVF-1A-2 | C72: Tran/Div | D72: CM 2 | F72: GA-PO-6-MU-1 | G72: * | H72: HD-AL-GVF-1A-2 | I72: =IFERROR(__xludf.DUMMYFUNCTION("""COMPUTED_VALUE"""),14.99) -> 14.99 | J72: Black | K72: 7645D9 | N72: starr8@rocketmail.com | Q72: Alocasia Green Velvet Frydek | S72: =IFERROR(__xludf.DUMMYFUNCTION("""COMPUTED_VALUE"""),0.0) -> 0
A73: 45892 | B73: HD-AL-GVF-1A-2 | C73: Division | D73: CM 2 | F73: GA-PO-6-MU-1 | G73: B | H73: HD-AL-GVF-1A-2B | I73: =IFERROR(__xludf.DUMMYFUNCTION("""COMPUTED_VALUE"""),14.99) -> 14.99 | J73: Yellow | K73: 29FD19 | N73: starr8@rocketmail.com | Q73: Alocasia Green Velvet Frydek | S73: =IFERROR(__xludf.DUMMYFUNCTION("""COMPUTED_VALUE"""),0.0) -> 0
H74: HS-SPA-PLD-1C | I74: =IFERROR(__xludf.DUMMYFUNCTION("""COMPUTED_VALUE"""),"") | Q74: Spathiphyllum Peace Lily Domino | S74: =IFERROR(__xludf.DUMMYFUNCTION("""COMPUTED_VALUE"""),"")
A75: 45893 | B75: HS-SP-PLD-1A | C75: Division | D75: CM 2 | F75: TE-PO-4-MU-1 | G75: E | H75: HS-SP-PLD-1E | I75: =IFERROR(__xludf.DUMMYFUNCTION("""COMPUTED_VALUE"""),2.49875) -> 2.49875 | J75: Yellow | K75: 435281 | N75: starr8@rocketmail.com | Q75: Spathiphyllum Peace Lily Domino | S75: =IFERROR(__xludf.DUMMYFUNCTION("""COMPUTED_VALUE"""),3.75) -> 3.75
I76: =IFERROR(__xludf.DUMMYFUNCTION("""COMPUTED_VALUE"""),"") | S76: =IFERROR(__xludf.DUMMYFUNCTION("""COMPUTED_VALUE"""),"")
A77: 45893 | B77: HS-BE-AW-1A | C77: Transplant | D77: CM 2 | F77: AN-PO-3-MU-1 | G77: B | H77: HS-BE-AW-1B | I77: =IFERROR(__xludf.DUMMYFUNCTION("""COMPUTED_VALUE"""),0.0) -> 0 | J77: White | K77: CE2A88 | N77: starr8@rocketmail.com | Q77: Begonia Angel Wing
A78: 45893 | B78: HS-BE-AW-1A | C78: Transplant | D78: CM 2 | F78: WO-PO-6-MU-1 | G78: C | H78: HS-BE-AW-1C | I78: =IFERROR(__xludf.DUMMYFUNCTION("""COMPUTED_VALUE"""),0.0) -> 0 | J78: White | K78: 779D19 | N78: starr8@rocketmail.com | Q78: Begonia Angel Wing
A79: 45893 | B79: FMY-CA-MA-1A | C79: Tran/Div | D79: CM 2 | F79: PS-PO-5.5-MU-1 | G79: * | H79: FMY-CA-MA-1A | I79: =IFERROR(__xludf.DUMMYFUNCTION("""COMPUTED_VALUE"""),3.3316666666666666) -> 3.3316667 | J79: White | K79: AB70AC | N79: starr8@rocketmail.com | Q79: Calathea Makoyana | S79: =IFERROR(__xludf.DUMMYFUNCTION("""COMPUTED_VALUE"""),2.8316666666666666) -> 2.8316667
A80: 45893 | B80: FMY-CA-MA-1A | C80: Division | D80: CM 2 | F80: TE-PO-4-MU-1 | G80: B | H80: FMY-CA-MA-1B | I80: =IFERROR(__xludf.DUMMYFUNCTION("""COMPUTED_VALUE"""),3.3316666666666666) -> 3.3316667 | J80: Black | K80: 190070 | N80: starr8@rocketmail.com | Q80: Calathea Makoyana | S80: =IFERROR(__xludf.DUMMYFUNCTION("""COMPUTED_VALUE"""),2.8316666666666666) -> 2.8316667
A81: 45893 | B81: FMY-CA-MA-1A | C81: Division | D81: CM 2 | F81: TE-PO-4-MU-1 | G81: C | H81: FMY-CA-MA-1C | I81: =IFERROR(__xludf.DUMMYFUNCTION("""COMPUTED_VALUE"""),3.3316666666666666) -> 3.3316667 | J81: Green | K81: 5D3624 | N81: starr8@rocketmail.com | Q81: Calathea Makoyana | S81: =IFERROR(__xludf.DUMMYFUNCTION("""COMPUTED_VALUE"""),2.8316666666666666) -> 2.8316667
A82: 45893 | B82: FMY-CA-MA-1A | C82: Division | D82: CM 2 | F82: TE-PO-4-MU-1 | G82: D | H82: FMY-CA-MA-1D | I82: =IFERROR(__xludf.DUMMYFUNCTION("""COMPUTED_VALUE"""),3.3316666666666666) -> 3.3316667 | J82: Purple | K82: D71A32 | N82: starr8@rocketmail.com | Q82: Calathea Makoyana | S82: =IFERROR(__xludf.DUMMYFUNCTION("""COMPUTED_VALUE"""),2.8316666666666666) -> 2.8316667
A83: 45893 | B83: FMY-CA-MA-1A | C83: Division | D83: CM 2 | F83: TO-PO-4-MU-1 | G83: E | H83: FMY-CA-MA-1E | I83: =IFERROR(__xludf.DUMMYFUNCTION("""COMPUTED_VALUE"""),3.3316666666666666) -> 3.3316667 | J83: Pink | K83: F1F87A | N83: starr8@rocketmail.com | Q83: Calathea Makoyana | S83: =IFERROR(__xludf.DUMMYFUNCTION("""COMPUTED_VALUE"""),2.8316666666666666) -> 2.8316667
A84: 45893 | B84: FMY-CA-MA-1A | C84: Division | D84: CM 2 | F84: AN-PO-3-MU-1 | G84: F | H84: FMY-CA-MA-1F | I84: =IFERROR(__xludf.DUMMYFUNCTION("""COMPUTED_VALUE"""),3.3316666666666666) -> 3.3316667 | J84: Green | K84: 327781 | N84: starr8@rocketmail.com | Q84: Calathea Makoyana | S84: =IFERROR(__xludf.DUMMYFUNCTION("""COMPUTED_VALUE"""),2.8316666666666666) -> 2.8316667
A85: 45893 | B85: FMY-CA-MA-1 | C85: Tuber | D85: CM 2 | F85: HY-PO-3-DO-1 | G85: G | H85: FMY-CA-MA-1G | I85: =IFERROR(__xludf.DUMMYFUNCTION("""COMPUTED_VALUE"""),3.3316666666666666) -> 3.3316667 | J85: Clear | K85: 2AF5C4 | N85: starr8@rocketmail.com | Q85: Calathea Makoyana | S85: =IFERROR(__xludf.DUMMYFUNCTION("""COMPUTED_VALUE"""),2.8316666666666666) -> 2.8316667
A86: 45893 | B86: FMY-CA-MA-1 | C86: Tuber | D86: CM 2 | F86: HY-PO-3-DO-1 | G86: H | H86: FMY-CA-MA-1H | I86: =IFERROR(__xludf.DUMMYFUNCTION("""COMPUTED_VALUE"""),3.3316666666666666) -> 3.3316667 | J86: Clear | K86: 7FD2D2 | N86: starr8@rocketmail.com | Q86: Calathea Makoyana | S86: =IFERROR(__xludf.DUMMYFUNCTION("""COMPUTED_VALUE"""),2.8316666666666666) -> 2.8316667
A87: 45894 | B87: HS-PH-BRL-1A | C87: Tran/Div | D87: CM 2 | F87: GA-PO-6-MU-1 | G87: * | H87: HS-PH-BRL-1A | I87: =IFERROR(__xludf.DUMMYFUNCTION("""COMPUTED_VALUE"""),0.0) -> 0 | J87: White | K87: 3016FD | N87: starr8@rocketmail.com | Q87: Philodendron Brasil | S87: =IFERROR(__xludf.DUMMYFUNCTION("""COMPUTED_VALUE"""),0.0) -> 0
A88: 45894 | B88: HS-PH-BRL-1A | C88: Division | D88: CM 2 | F88: GA-PO-6-MU-1 | G88: B | H88: HS-PH-BRL-1B | I88: =IFERROR(__xludf.DUMMYFUNCTION("""COMPUTED_VALUE"""),0.0) -> 0 | J88: White | K88: 2928C6 | N88: starr8@rocketmail.com | Q88: Philodendron Brasil | S88: =IFERROR(__xludf.DUMMYFUNCTION("""COMPUTED_VALUE"""),0.0) -> 0
A89: 45894 | B89: HS-PH-BRL-1A | C89: Division | D89: CM 2 | F89: GA-PO-4-WH-1 | G89: C | H89: HS-PH-BRL-1C | I89: =IFERROR(__xludf.DUMMYFUNCTION("""COMPUTED_VALUE"""),0.0) -> 0 | J89: White | K89: FA6581 | N89: starr8@rocketmail.com | Q89: Philodendron Brasil | S89: =IFERROR(__xludf.DUMMYFUNCTION("""COMPUTED_VALUE"""),0.0) -> 0
A90: 45896 | B90: TGOPS-PH-WW-1A | C90: Tran/Div | D90: CM 2 | F90: WO-PO-6-WH-1 | G90: * | H90: TGOPS-PH-WW-1A | I90: =IFERROR(__xludf.DUMMYFUNCTION("""COMPUTED_VALUE"""),2.1983333333333333) -> 2.1983333 | J90: White | K90: 7BC163 | N90: starr8@rocketmail.com | Q90: Philodendron White Wizard | S90: =IFERROR(__xludf.DUMMYFUNCTION("""COMPUTED_VALUE"""),0.0) -> 0
A91: 45896 | B91: TGOPS-PH-WW-1A | C91: Division | D91: CM 2 | F91: TE-PO-4-MU-1 | G91: B | H91: TGOPS-PH-WW-1B | I91: =IFERROR(__xludf.DUMMYFUNCTION("""COMPUTED_VALUE"""),2.1983333333333333) -> 2.1983333 | J91: Purple | K91: CD38EF | N91: starr8@rocketmail.com | Q91: Philodendron White Wizard | S91: =IFERROR(__xludf.DUMMYFUNCTION("""COMPUTED_VALUE"""),0.0) -> 0
A92: 45896 | B92: TGOPS-PH-WW-1A | C92: Division | D92: CM 2 | F92: TE-PO-4-MU-1 | G92: C | H92: TGOPS-PH-WW-1C | I92: =IFERROR(__xludf.DUMMYFUNCTION("""COMPUTED_VALUE"""),2.1983333333333333) -> 2.1983333 | J92: Blue | K92: 7A10AF | N92: starr8@rocketmail.com | Q92: Philodendron White Wizard | S92: =IFERROR(__xludf.DUMMYFUNCTION("""COMPUTED_VALUE"""),0.0) -> 0
A93: 45896 | B93: TGOPS-PH-WW-1A | C93: Division | D93: CM 2 | F93: TE-PO-4-MU-1 | G93: D | H93: TGOPS-PH-WW-1D | I93: =IFERROR(__xludf.DUMMYFUNCTION("""COMPUTED_VALUE"""),2.1983333333333333) -> 2.1983333 | J93: Blue | K93: E74A9D | N93: starr8@rocketmail.com | Q93: Philodendron White Wizard | S93: =IFERROR(__xludf.DUMMYFUNCTION("""COMPUTED_VALUE"""),0.0) -> 0
A94: 45896 | B94: TGOPS-PH-WW-1A | C94: Division | D94: CM 2 | F94: YA-PO-2-CL-1 | G94: E | H94: TGOPS-PH-WW-1E | I94: =IFERROR(__xludf.DUMMYFUNCTION("""COMPUTED_VALUE"""),2.1983333333333333) -> 2.1983333 | J94: Clear | K94: 11281F | N94: starr8@rocketmail.com | Q94: Philodendron White Wizard | S94: =IFERROR(__xludf.DUMMYFUNCTION("""COMPUTED_VALUE"""),0.0) -> 0
A95: 45896 | B95: TGOPS-PH-WW-1A | C95: Division | D95: CM 2 | F95: YA-PO-2-CL-1 | G95: F | H95: TGOPS-PH-WW-1F | I95: =IFERROR(__xludf.DUMMYFUNCTION("""COMPUTED_VALUE"""),2.1983333333333333) -> 2.1983333 | J95: Clear | K95: 245F96 | N95: starr8@rocketmail.com | Q95: Philodendron White Wizard | S95: =IFERROR(__xludf.DUMMYFUNCTION("""COMPUTED_VALUE"""),0.0) -> 0
A96: 45896 | B96: TGOPS-PH-WW-1A-3 | C96: Tran/Div | D96: CM 2 | F96: WO-PO-6-WH-1 | G96: * | H96: TGOPS-PH-WW-1A-3 | I96: =IFERROR(__xludf.DUMMYFUNCTION("""COMPUTED_VALUE"""),4.3966666666666665) -> 4.3966667 | J96: White | K96: C3D233 | N96: starr8@rocketmail.com | Q96: Philodendron White Wizard | S96: =IFERROR(__xludf.DUMMYFUNCTION("""COMPUTED_VALUE"""),0.0) -> 0
A97: 45896 | B97: TGOPS-PH-WW-1A-3 | C97: Division | D97: CM 2 | F97: GA-PO-4-WH-1 | G97: B | H97: TGOPS-PH-WW-1A-3B | I97: =IFERROR(__xludf.DUMMYFUNCTION("""COMPUTED_VALUE"""),4.3966666666666665) -> 4.3966667 | J97: Pink | K97: 52BD91 | N97: starr8@rocketmail.com | Q97: Philodendron White Wizard | S97: =IFERROR(__xludf.DUMMYFUNCTION("""COMPUTED_VALUE"""),0.0) -> 0
A98: 45896 | B98: TGOPS-PH-WW-1A-3 | C98: Division | D98: CM 2 | F98: AN-PO-3-MU-1 | G98: C | H98: TGOPS-PH-WW-1A-3C | I98: =IFERROR(__xludf.DUMMYFUNCTION("""COMPUTED_VALUE"""),4.3966666666666665) -> 4.3966667 | J98: White | K98: 7037BA | N98: starr8@rocketmail.com | Q98: Philodendron White Wizard | S98: =IFERROR(__xludf.DUMMYFUNCTION("""COMPUTED_VALUE"""),0.0) -> 0
A99: 45896 | B99: TGOPS-PH-WW-1A-2 | C99: Division | D99: CM 2 | F99: GA-PO-6-MU-1 | G99: D | H99: TGOPS-PH-WW-1A-2D | I99: =IFERROR(__xludf.DUMMYFUNCTION("""COMPUTED_VALUE"""),3.2975) -> 3.2975 | J99: Pink | K99: 4D5E99 | N99: starr8@rocketmail.com | Q99: Philodendron White Wizard | S99: =IFERROR(__xludf.DUMMYFUNCTION("""COMPUTED_VALUE"""),0.0) -> 0
A100: 45896 | B100: TGOPS-PH-WW-1A-2 | C100: Tran/Div | D100: CM 2 | F100: TE-PO-4-MU-1 | G100: * | H100: TGOPS-PH-WW-1A-2 | I100: =IFERROR(__xludf.DUMMYFUNCTION("""COMPUTED_VALUE"""),3.2975) -> 3.2975 | J100: Pink | K100: 10B58A | N100: starr8@rocketmail.com | Q100: Philodendron White Wizard | S100: =IFERROR(__xludf.DUMMYFUNCTION("""COMPUTED_VALUE"""),0.0) -> 0
A101: 45896 | B101: TGOPS-PH-WW-1A-2 | C101: Division | D101: CM 2 | F101: TE-PO-4-MU-3 | G101: B | H101: TGOPS-PH-WW-1A-2B | I101: =IFERROR(__xludf.DUMMYFUNCTION("""COMPUTED_VALUE"""),3.2975) -> 3.2975 | J101: Pink | K101: CCCDF4 | N101: starr8@rocketmail.com | Q101: Philodendron White Wizard | S101: =IFERROR(__xludf.DUMMYFUNCTION("""COMPUTED_VALUE"""),0.0) -> 0
...

Sheet SKU Master
A1: SKU | B1: U ID | C1: Owner Email
A2: =IFERROR(__xludf.DUMMYFUNCTION("UNIQUE(ARRAYFORMULA(FILTER( {'PLANT Intake Coding'!F3:F3059;'PRODUCT Intake Coding'!I3:I1000;'Transplant Log'!H3:H2000}, LEN({'PLANT Intake Coding'!F3:F3059;'PRODUCT Intake Coding'!I3:I1000;'Transplant Log'!H3:H2000})>0 )))"),"HS-BE-AW-1A") -> HS-BE-AW-1A | B2: 0EE7BD | C2: starr8@rocketmail.com
A3: =IFERROR(__xludf.DUMMYFUNCTION("""COMPUTED_VALUE"""),"HS-PO-GO-1A") -> HS-PO-GO-1A | B3: 45F0E8 | C3: starr8@rocketmail.com
A4: =IFERROR(__xludf.DUMMYFUNCTION("""COMPUTED_VALUE"""),"HS-PH-HL-1A") -> HS-PH-HL-1A | B4: 83D40A | C4: starr8@rocketmail.com
A5: =IFERROR(__xludf.DUMMYFUNCTION("""COMPUTED_VALUE"""),"HS-PH-BRL-1A") -> HS-PH-BRL-1A | B5: 051015 | C5: starr8@rocketmail.com
A6: =IFERROR(__xludf.DUMMYFUNCTION("""COMPUTED_VALUE"""),"HS-PI-PEP-1A") -> HS-PI-PEP-1A | B6: 30976F | C6: starr8@rocketmail.com
A7: =IFERROR(__xludf.DUMMYFUNCTION("""COMPUTED_VALUE"""),"HS-CT-BM-1A") -> HS-CT-BM-1A | B7: 8F36AD | C7: starr8@rocketmail.com
A8: =IFERROR(__xludf.DUMMYFUNCTION("""COMPUTED_VALUE"""),"HS-DR-SP-1A") -> HS-DR-SP-1A | B8: 0F458D | C8: starr8@rocketmail.com
A9: =IFERROR(__xludf.DUMMYFUNCTION("""COMPUTED_VALUE"""),"FM-PH-WK-1A") -> FM-PH-WK-1A | B9: B570B8 | C9: starr8@rocketmail.com
A10: =IFERROR(__xludf.DUMMYFUNCTION("""COMPUTED_VALUE"""),"WM-PH-WK-1A") -> WM-PH-WK-1A | B10: 533F84 | C10: starr8@rocketmail.com
A11: =IFERROR(__xludf.DUMMYFUNCTION("""COMPUTED_VALUE"""),"WM-MA-PE-1A") -> WM-MA-PE-1A | B11: 096087 | C11: starr8@rocketmail.com
A12: =IFERROR(__xludf.DUMMYFUNCTION("""COMPUTED_VALUE"""),"TLC-PH-CS-1A") -> TLC-PH-CS-1A | B12: 7FE8D2 | C12: starr8@rocketmail.com
A13: =IFERROR(__xludf.DUMMYFUNCTION("""COMPUTED_VALUE"""),"TAG-AO-DR-1A") -> TAG-AO-DR-1A | B13: 11629D | C13: starr8@rocketmail.com
A14: =IFERROR(__xludf.DUMMYFUNCTION("""COMPUTED_VALUE"""),"FMY-PH-GC-1A") -> FMY-PH-GC-1A | B14: F2047D | C14: starr8@rocketmail.com
A15: =IFERROR(__xludf.DUMMYFUNCTION("""COMPUTED_VALUE"""),"FMY-AL-RSD-1A") -> FMY-AL-RSD-1A | B15: CF25E8 | C15: starr8@rocketmail.com
A16: =IFERROR(__xludf.DUMMYFUNCTION("""COMPUTED_VALUE"""),"FMY-AL-GVF-1A") -> FMY-AL-GVF-1A | B16: 3DA0D2 | C16: starr8@rocketmail.com
A17: =IFERROR(__xludf.DUMMYFUNCTION("""COMPUTED_VALUE"""),"FMY-MA-DE-1A") -> FMY-MA-DE-1A | B17: 3E2B8B | C17: starr8@rocketmail.com
A18: =IFERROR(__xludf.DUMMYFUNCTION("""COMPUTED_VALUE"""),"FMY-MA-DE-1A-2") -> FMY-MA-DE-1A-2 | B18: 3E271E | C18: starr8@rocketmail.com
A19: =IFERROR(__xludf.DUMMYFUNCTION("""COMPUTED_VALUE"""),"TLC-SC-SS-1A") -> TLC-SC-SS-1A | B19: 0302E1 | C19: starr8@rocketmail.com
A20: =IFERROR(__xludf.DUMMYFUNCTION("""COMPUTED_VALUE"""),"MMP-MA-AD-1A") -> MMP-MA-AD-1A | B20: F5881C | C20: starr8@rocketmail.com
A21: =IFERROR(__xludf.DUMMYFUNCTION("""COMPUTED_VALUE"""),"OLN-MA-AD-1A") -> OLN-MA-AD-1A | B21: 644B88 | C21: starr8@rocketmail.com
A22: =IFERROR(__xludf.DUMMYFUNCTION("""COMPUTED_VALUE"""),"OLN-PH-WP-1A") -> OLN-PH-WP-1A | B22: 61D50A | C22: starr8@rocketmail.com
A23: =IFERROR(__xludf.DUMMYFUNCTION("""COMPUTED_VALUE"""),"OLN-ALT-PT-1A") -> OLN-ALT-PT-1A | B23: 4CD07B | C23: starr8@rocketmail.com
A24: =IFERROR(__xludf.DUMMYFUNCTION("""COMPUTED_VALUE"""),"OLN-FI-RF-1A") -> OLN-FI-RF-1A | B24: 81209A | C24: starr8@rocketmail.com
A25: =IFERROR(__xludf.DUMMYFUNCTION("""COMPUTED_VALUE"""),"OLN-PH-STS-1A") -> OLN-PH-STS-1A | B25: 4FACA4 | C25: starr8@rocketmail.com
A26: =IFERROR(__xludf.DUMMYFUNCTION("""COMPUTED_VALUE"""),"OLN-PH-SD-1A") -> OLN-PH-SD-1A | B26: 818230 | C26: starr8@rocketmail.com
A27: =IFERROR(__xludf.DUMMYFUNCTION("""COMPUTED_VALUE"""),"AR-PH-WP-1A") -> AR-PH-WP-1A | B27: D59A68 | C27: starr8@rocketmail.com
A28: =IFERROR(__xludf.DUMMYFUNCTION("""COMPUTED_VALUE"""),"AR-AL-LM-1A") -> AR-AL-LM-1A | B28: F9C924 | C28: starr8@rocketmail.com
A29: =IFERROR(__xludf.DUMMYFUNCTION("""COMPUTED_VALUE"""),"ZB-SE-HA-1A") -> ZB-SE-HA-1A | B29: F2950C | C29: starr8@rocketmail.com
A30: =IFERROR(__xludf.DUMMYFUNCTION("""COMPUTED_VALUE"""),"IST-PH-PP-1A") -> IST-PH-PP-1A | B30: 5614FF | C30: starr8@rocketmail.com
A31: =IFERROR(__xludf.DUMMYFUNCTION("""COMPUTED_VALUE"""),"IST-PH-GCN-1A") -> IST-PH-GCN-1A | B31: 2E0C02 | C31: starr8@rocketmail.com
A32: =IFERROR(__xludf.DUMMYFUNCTION("""COMPUTED_VALUE"""),"TGG-HO-GF-1A") -> TGG-HO-GF-1A | B32: ED62DF | C32: starr8@rocketmail.com
A33: =IFERROR(__xludf.DUMMYFUNCTION("""COMPUTED_VALUE"""),"TGG-HO-PU-1A") -> TGG-HO-PU-1A | B33: 635572 | C33: starr8@rocketmail.com
A34: =IFERROR(__xludf.DUMMYFUNCTION("""COMPUTED_VALUE"""),"FM-MA-DE-1A") -> FM-MA-DE-1A | B34: 796F78 | C34: starr8@rocketmail.com
A35: =IFERROR(__xludf.DUMMYFUNCTION("""COMPUTED_VALUE"""),"AM-PH-PP-1A") -> AM-PH-PP-1A | B35: FD0E98 | C35: starr8@rocketmail.com
A36: =IFERROR(__xludf.DUMMYFUNCTION("""COMPUTED_VALUE"""),"AM-PH-WW-1A") -> AM-PH-WW-1A | B36: 9C5072 | C36: starr8@rocketmail.com
A37: =IFERROR(__xludf.DUMMYFUNCTION("""COMPUTED_VALUE"""),"AM-PH-GL-1A") -> AM-PH-GL-1A | B37: 31EDC2 | C37: starr8@rocketmail.com
A38: =IFERROR(__xludf.DUMMYFUNCTION("""COMPUTED_VALUE"""),"AM-PH-BI-1A") -> AM-PH-BI-1A | B38: 661F03 | C38: starr8@rocketmail.com
A39: =IFERROR(__xludf.DUMMYFUNCTION("""COMPUTED_VALUE"""),"TGOPS-PH-PPM-1A") -> TGOPS-PH-PPM-1A | B39: AD730C | C39: starr8@rocketmail.com
A40: =IFERROR(__xludf.DUMMYFUNCTION("""COMPUTED_VALUE"""),"TGOPS-PH-PPM-1A-2") -> TGOPS-PH-PPM-1A-2 | B40: 44390B | C40: starr8@rocketmail.com
A41: =IFERROR(__xludf.DUMMYFUNCTION("""COMPUTED_VALUE"""),"TGOPS-PH-PPM-1A-3") -> TGOPS-PH-PPM-1A-3 | B41: A02229 | C41: starr8@rocketmail.com
A42: =IFERROR(__xludf.DUMMYFUNCTION("""COMPUTED_VALUE"""),"TGOPS-PH-POO-1A") -> TGOPS-PH-POO-1A | B42: BA3D1C | C42: starr8@rocketmail.com
A43: =IFERROR(__xludf.DUMMYFUNCTION("""COMPUTED_VALUE"""),"TGOPS-PH-POO-1A-2") -> TGOPS-PH-POO-1A-2 | B43: 92C0C5 | C43: starr8@rocketmail.com
A44: =IFERROR(__xludf.DUMMYFUNCTION("""COMPUTED_VALUE"""),"TGOPS-PH-POO-1A-3") -> TGOPS-PH-POO-1A-3 | B44: BE392B | C44: starr8@rocketmail.com
A45: =IFERROR(__xludf.DUMMYFUNCTION("""COMPUTED_VALUE"""),"TGOPS-PH-WW-1A") -> TGOPS-PH-WW-1A | B45: 5BBA6C | C45: starr8@rocketmail.com
A46: =IFERROR(__xludf.DUMMYFUNCTION("""COMPUTED_VALUE"""),"TGOPS-PH-WW-1A-2") -> TGOPS-PH-WW-1A-2 | B46: 84CACD | C46: starr8@rocketmail.com
A47: =IFERROR(__xludf.DUMMYFUNCTION("""COMPUTED_VALUE"""),"TGOPS-PH-WW-1A-3") -> TGOPS-PH-WW-1A-3 | B47: 2683E9 | C47: starr8@rocketmail.com
A48: =IFERROR(__xludf.DUMMYFUNCTION("""COMPUTED_VALUE"""),"BWH-PH-MO-1A") -> BWH-PH-MO-1A | B48: 226B4E | C48: starr8@rocketmail.com
A49: =IFERROR(__xludf.DUMMYFUNCTION("""COMPUTED_VALUE"""),"BWH-PH-MO-1A-2") -> BWH-PH-MO-1A-2 | B49: D7E58F | C49: starr8@rocketmail.com
A50: =IFERROR(__xludf.DUMMYFUNCTION("""COMPUTED_VALUE"""),"BWH-PH-MO-1A-3") -> BWH-PH-MO-1A-3 | B50: 4410F8 | C50: starr8@rocketmail.com
A51: =IFERROR(__xludf.DUMMYFUNCTION("""COMPUTED_VALUE"""),"BWH-PH-MO-1A-4") -> BWH-PH-MO-1A-4 | B51: 10B4EE | C51: starr8@rocketmail.com
A52: =IFERROR(__xludf.DUMMYFUNCTION("""COMPUTED_VALUE"""),"BWH-PH-MO-1A-5") -> BWH-PH-MO-1A-5 | B52: B5F25C | C52: starr8@rocketmail.com
A53: =IFERROR(__xludf.DUMMYFUNCTION("""COMPUTED_VALUE"""),"BWH-PH-RAPK-1A") -> BWH-PH-RAPK-1A | B53: 47FBCB | C53: starr8@rocketmail.com
A54: =IFERROR(__xludf.DUMMYFUNCTION("""COMPUTED_VALUE"""),"BWH-PH-RAPK-1A-2") -> BWH-PH-RAPK-1A-2 | B54: C2CF73 | C54: starr8@rocketmail.com
A55: =IFERROR(__xludf.DUMMYFUNCTION("""COMPUTED_VALUE"""),"BWH-PH-RAPK-1A-3") -> BWH-PH-RAPK-1A-3 | B55: A71378 | C55: starr8@rocketmail.com
A56: =IFERROR(__xludf.DUMMYFUNCTION("""COMPUTED_VALUE"""),"BWH-PH-RAPK-1A-4") -> BWH-PH-RAPK-1A-4 | B56: 23EFEA | C56: starr8@rocketmail.com
A57: =IFERROR(__xludf.DUMMYFUNCTION("""COMPUTED_VALUE"""),"BWH-PH-RAPK-1A-5") -> BWH-PH-RAPK-1A-5 | B57: 8B18D3 | C57: starr8@rocketmail.com
A58: =IFERROR(__xludf.DUMMYFUNCTION("""COMPUTED_VALUE"""),"BWH-PO-PAJ-1A") -> BWH-PO-PAJ-1A | B58: 3144F1 | C58: starr8@rocketmail.com
A59: =IFERROR(__xludf.DUMMYFUNCTION("""COMPUTED_VALUE"""),"BWH-PO-PAJ-1A-2") -> BWH-PO-PAJ-1A-2 | B59: 708E88 | C59: starr8@rocketmail.com
A60: =IFERROR(__xludf.DUMMYFUNCTION("""COMPUTED_VALUE"""),"BWH-PO-PAJ-1A-3") -> BWH-PO-PAJ-1A-3 | B60: E51050 | C60: starr8@rocketmail.com
A61: =IFERROR(__xludf.DUMMYFUNCTION("""COMPUTED_VALUE"""),"BWH-PO-PAJ-1A-4") -> BWH-PO-PAJ-1A-4 | B61: 0D486D | C61: starr8@rocketmail.com
A62: =IFERROR(__xludf.DUMMYFUNCTION("""COMPUTED_VALUE"""),"BWH-PO-PAJ-1A-5") -> BWH-PO-PAJ-1A-5 | B62: AE59BB | C62: starr8@rocketmail.com
A63: =IFERROR(__xludf.DUMMYFUNCTION("""COMPUTED_VALUE"""),"BWH-SYN-PS-1A") -> BWH-SYN-PS-1A | B63: 0313FB | C63: starr8@rocketmail.com
A64: =IFERROR(__xludf.DUMMYFUNCTION("""COMPUTED_VALUE"""),"BWH-SYN-PS-1A-2") -> BWH-SYN-PS-1A-2 | B64: C49686 | C64: starr8@rocketmail.com
A65: =IFERROR(__xludf.DUMMYFUNCTION("""COMPUTED_VALUE"""),"BWH-SYN-PS-1A-3") -> BWH-SYN-PS-1A-3 | B65: C03F57 | C65: starr8@rocketmail.com
A66: =IFERROR(__xludf.DUMMYFUNCTION("""COMPUTED_VALUE"""),"BWH-SYN-PS-1A-4") -> BWH-SYN-PS-1A-4 | B66: F4773F | C66: starr8@rocketmail.com
A67: =IFERROR(__xludf.DUMMYFUNCTION("""COMPUTED_VALUE"""),"BWH-SYN-PS-1A-5") -> BWH-SYN-PS-1A-5 | B67: 436156 | C67: starr8@rocketmail.com
A68: =IFERROR(__xludf.DUMMYFUNCTION("""COMPUTED_VALUE"""),"FPH-PH-GCN-1A") -> FPH-PH-GCN-1A | B68: A511DC | C68: starr8@rocketmail.com
A69: =IFERROR(__xludf.DUMMYFUNCTION("""COMPUTED_VALUE"""),"BTPG-HO-KP-1A") -> BTPG-HO-KP-1A | B69: D2DA7D | C69: starr8@rocketmail.com
A70: =IFERROR(__xludf.DUMMYFUNCTION("""COMPUTED_VALUE"""),"BPF-CE-SOH-1A") -> BPF-CE-SOH-1A | B70: 04D668 | C70: starr8@rocketmail.com
A71: =IFERROR(__xludf.DUMMYFUNCTION("""COMPUTED_VALUE"""),"BPF-CE-SOH-1A-2") -> BPF-CE-SOH-1A-2 | B71: A7AFE7 | C71: starr8@rocketmail.com
A72: =IFERROR(__xludf.DUMMYFUNCTION("""COMPUTED_VALUE"""),"BPF-CE-SOH-1A-3") -> BPF-CE-SOH-1A-3 | B72: 022779 | C72: starr8@rocketmail.com
A73: =IFERROR(__xludf.DUMMYFUNCTION("""COMPUTED_VALUE"""),"BPF-CE-SOH-1A-4") -> BPF-CE-SOH-1A-4 | B73: BBDE83 | C73: starr8@rocketmail.com
A74: =IFERROR(__xludf.DUMMYFUNCTION("""COMPUTED_VALUE"""),"BPF-CE-SOH-1A-5") -> BPF-CE-SOH-1A-5 | B74: 7B4EC7 | C74: starr8@rocketmail.com
A75: =IFERROR(__xludf.DUMMYFUNCTION("""COMPUTED_VALUE"""),"BPF-SE-SOP-1A") -> BPF-SE-SOP-1A | B75: 9F5631 | C75: starr8@rocketmail.com
A76: =IFERROR(__xludf.DUMMYFUNCTION("""COMPUTED_VALUE"""),"BPF-SE-SOP-1A-2") -> BPF-SE-SOP-1A-2 | B76: 3019B0 | C76: starr8@rocketmail.com
A77: =IFERROR(__xludf.DUMMYFUNCTION("""COMPUTED_VALUE"""),"BPF-SE-SOP-1A-3") -> BPF-SE-SOP-1A-3 | B77: 81B195 | C77: starr8@rocketmail.com
A78: =IFERROR(__xludf.DUMMYFUNCTION("""COMPUTED_VALUE"""),"BPF-SE-SOP-1A-4") -> BPF-SE-SOP-1A-4 | B78: ABF090 | C78: starr8@rocketmail.com
A79: =IFERROR(__xludf.DUMMYFUNCTION("""COMPUTED_VALUE"""),"BPF-SE-SOP-1A-5") -> BPF-SE-SOP-1A-5 | B79: AAB8AE | C79: starr8@rocketmail.com
A80: =IFERROR(__xludf.DUMMYFUNCTION("""COMPUTED_VALUE"""),"BPF-PO-NE-1A") -> BPF-PO-NE-1A | B80: 04F721 | C80: starr8@rocketmail.com
A81: =IFERROR(__xludf.DUMMYFUNCTION("""COMPUTED_VALUE"""),"BPF-PO-NE-1A-2") -> BPF-PO-NE-1A-2 | B81: E60994 | C81: starr8@rocketmail.com
A82: =IFERROR(__xludf.DUMMYFUNCTION("""COMPUTED_VALUE"""),"FM-PH-PP-1A") -> FM-PH-PP-1A | B82: CAF362 | C82: starr8@rocketmail.com
A83: =IFERROR(__xludf.DUMMYFUNCTION("""COMPUTED_VALUE"""),"FM-PH-BMV-1A") -> FM-PH-BMV-1A | B83: 0023DB | C83: starr8@rocketmail.com
A84: =IFERROR(__xludf.DUMMYFUNCTION("""COMPUTED_VALUE"""),"FM-PH-BMV-1A-2") -> FM-PH-BMV-1A-2 | B84: 6A9BA9 | C84: starr8@rocketmail.com
A85: =IFERROR(__xludf.DUMMYFUNCTION("""COMPUTED_VALUE"""),"FM-SYN-BA-1A") -> FM-SYN-BA-1A | B85: 41C889 | C85: starr8@rocketmail.com
A86: =IFERROR(__xludf.DUMMYFUNCTION("""COMPUTED_VALUE"""),"FMY-AL-RSD-1A-2") -> FMY-AL-RSD-1A-2 | B86: 26C3E4 | C86: starr8@rocketmail.com
A87: =IFERROR(__xludf.DUMMYFUNCTION("""COMPUTED_VALUE"""),"FMY-MA-PE-1A") -> FMY-MA-PE-1A | B87: D36997 | C87: starr8@rocketmail.com
A88: =IFERROR(__xludf.DUMMYFUNCTION("""COMPUTED_VALUE"""),"FMY-AG-SPA-1A") -> FMY-AG-SPA-1A | B88: 53ED2C | C88: starr8@rocketmail.com
A89: =IFERROR(__xludf.DUMMYFUNCTION("""COMPUTED_VALUE"""),"FMY-CA-MA-1A") -> FMY-CA-MA-1A | B89: 6A816D | C89: starr8@rocketmail.com
A90: =IFERROR(__xludf.DUMMYFUNCTION("""COMPUTED_VALUE"""),"FMY-MA-DE-1A-3") -> FMY-MA-DE-1A-3 | B90: EB3A2F | C90: starr8@rocketmail.com
A91: =IFERROR(__xludf.DUMMYFUNCTION("""COMPUTED_VALUE"""),"FMY-MA-DE-1A-4") -> FMY-MA-DE-1A-4 | B91: 775BD2 | C91: starr8@rocketmail.com
A92: =IFERROR(__xludf.DUMMYFUNCTION("""COMPUTED_VALUE"""),"FMY-MA-DE-1A-5") -> FMY-MA-DE-1A-5 | B92: B2FE1E | C92: starr8@rocketmail.com
A93: =IFERROR(__xludf.DUMMYFUNCTION("""COMPUTED_VALUE"""),"FMY-PH-PL-1A") -> FMY-PH-PL-1A | B93: F05F3D | C93: starr8@rocketmail.com
A94: =IFERROR(__xludf.DUMMYFUNCTION("""COMPUTED_VALUE"""),"HD-AL-LO-1A") -> HD-AL-LO-1A | B94: FC4308 | C94: starr8@rocketmail.com
A95: =IFERROR(__xludf.DUMMYFUNCTION("""COMPUTED_VALUE"""),"HD-AL-LO-1A-2") -> HD-AL-LO-1A-2 | B95: 997E89 | C95: starr8@rocketmail.com
A96: =IFERROR(__xludf.DUMMYFUNCTION("""COMPUTED_VALUE"""),"HD-AL-GVF-1A-2") -> HD-AL-GVF-1A-2 | B96: 58FFED | C96: starr8@rocketmail.com
A97: =IFERROR(__xludf.DUMMYFUNCTION("""COMPUTED_VALUE"""),"HD-AL-BDS-1A") -> HD-AL-BDS-1A | B97: 606865 | C97: starr8@rocketmail.com
A98: =IFERROR(__xludf.DUMMYFUNCTION("""COMPUTED_VALUE"""),"HD-PH-GG-1A") -> HD-PH-GG-1A | B98: 3585E8 | C98: starr8@rocketmail.com
A99: =IFERROR(__xludf.DUMMYFUNCTION("""COMPUTED_VALUE"""),"HD-HO-SSS-1A") -> HD-HO-SSS-1A | B99: C98B1A | C99: starr8@rocketmail.com
A100: =IFERROR(__xludf.DUMMYFUNCTION("""COMPUTED_VALUE"""),"HD-ST-TR-1A") -> HD-ST-TR-1A | B100: 1C2F30 | C100: starr8@rocketmail.com
...

Sheet Transplant KEY
A1: Media | B1: Action | C1: From Pot Size | D1: To Pot Size | E1: Media
A2: CM 1 | B2: Combine | C2: 2" Nursery | D2: 2" Nursery | E2: CM 1 | F2: Color In
A3: CM 2 | B3: Cutting | C3: 2" | D3: 2" | E3: CM 2 | F3: Product Key
A4: CM 3 | B4: Division | C4: 4" Nursery | D4: 4" Nursery | E4: CM 3
A5: Sphagnum | B5: Down-pot | C5: 3" | D5: 3" | E5: Sphagnum
A6: ACM | B6: Tran/Div | C6: 3.7" | D6: 3.7" | E6: ACM
A7: Perlite Mix | B7: Transplant | C7: 4" | D7: 4" | E7: Perlite Mix
A8: Soil Mix | B8: Tuber | C8: 4.3" | D8: 4.3" | E8: Soil Mix
A9: Leca | B9: Up-pot | C9: 5" | D9: 5" | E9: Leca
B10: Corm | C10: 5.5" | D10: 5.5" | E10: Verm/Perlite
B11: Tran/Comb | C11: 6" | D11: 6"
B12: Plant | C12: 8" | D12: 8"
C13: 10" | D13: 10"

Sheet Sales
D1: =SUM(D3:D996) -> 172 | F1: =SUM(F3:F996) -> 1717 | J1: =SUM(J3:J996) -> 1024.551 | K1: =SUM(K3:K996) -> 680.77
A2: Date | B2: SKU | C2: Item Name | D2: Qty | E2: Sale Price | F2: Total Sale | G2: Payment Method | H2: Card # | I2: Sale Channel | J2: Cost | K2: Profit | L2: Margin % | M2: Notes | N2: Sale ID | O2: Status | P2: Owner Email | Q2: Customer Name
A3: 45951 | B3: BWH-PO-PAJ-1A-5 | C3: Pothos Pearls and Jade | D3: 1 | E3: 20 | F3: 20 | G3: Cash | H3: None | I3: In Person | J3: 9.15 | K3: 10.85 | L3: 0.5425 | N3: 5e6yy5 | O3: Sold | P3: starr8@rocketmail.com
A4: 45899 | B4: BWH-PH-MO-1A-5 | C4: Philodendron Moonlight | D4: 1 | E4: 30 | F4: 30 | G4: Cash | H4: None | I4: Merlin Outdoor Market | J4: 7.35 | K4: 22.65 | L4: 0.755 | N4: C430FF | O4: Sold | P4: starr8@rocketmail.com
A5: 45899 | B5: HS-BE-AW-1B | C5: Begonia Angel Wing | D5: 1 | E5: 3 | F5: 3 | G5: Cash | H5: None | I5: Merlin Outdoor Market | J5: 0.29 | K5: 2.71 | L5: 0.90333333 | N5: FB5087 | O5: Sold | P5: starr8@rocketmail.com
A6: 45899 | B6: HS-BE-AW-1F | C6: Angel Wing | D6: 1 | E6: 10 | F6: 10 | G6: Cash | H6: None | I6: Merlin Outdoor Market | J6: 0 | K6: 10 | L6: 1 | N6: C75882 | O6: Sold | P6: starr8@rocketmail.com
A7: 45899 | B7: HS-BE-AW-1D | C7: Begonia Angel Wing | D7: 1 | E7: 7 | F7: 7 | G7: Cash | H7: None | I7: Merlin Outdoor Market | J7: 0.5 | K7: 6.5 | L7: 0.92857143 | N7: 62A562 | O7: Sold | P7: starr8@rocketmail.com
A8: 45899 | B8: HS-PO-GO-1B | C8: Pothos Golden | D8: 1 | E8: 2 | F8: 2 | G8: Cash | H8: None | I8: Merlin Outdoor Market | J8: 0.92 | K8: 1.08 | L8: 0.54 | N8: ED61DC | O8: Sold | P8: starr8@rocketmail.com
A9: 45899 | B9: HS-PO-GO-1I | C9: Pothos Golden | D9: 1 | E9: 4 | F9: 4 | G9: Cash | H9: None | I9: Merlin Outdoor Market | J9: 0.5 | K9: 3.5 | L9: 0.875 | N9: ED8B91 | O9: Sold | P9: starr8@rocketmail.com
A10: 45899 | B10: BWH-PO-PAJ-1A-3 | C10: Pothos Pearls and Jade | D10: 1 | E10: 12 | F10: 12 | G10: Cash | H10: None | I10: Merlin Outdoor Market | J10: 9.22 | K10: 2.78 | L10: 0.23166667 | N10: 6F0372 | O10: Sold | P10: starr8@rocketmail.com
A11: 45899 | B11: BWH-PO-PAJ-1A-4 | C11: Pothos Pearls and Jade | D11: 1 | E11: 12 | F11: 12 | G11: Cash | H11: None | I11: Merlin Outdoor Market | J11: 2.45 | K11: 9.55 | L11: 0.79583333 | N11: E89300 | O11: Sold | P11: starr8@rocketmail.com
A12: 45899 | B12: BWH-PO-PAJ-1A-4B | C12: Pothos Pearls and Jade | D12: 1 | E12: 9 | F12: 9 | G12: Cash | H12: None | I12: Merlin Outdoor Market | J12: 2.24 | K12: 6.76 | L12: 0.75111111 | N12: E20E2D | O12: Sold | P12: starr8@rocketmail.com
A13: 45899 | B13: BWH-PO-PAJ-1A-4C | C13: Pothos Pearls and Jade | D13: 1 | E13: 12 | F13: 12 | G13: Cash | H13: None | I13: Merlin Outdoor Market | J13: 2.24 | K13: 9.76 | L13: 0.81333333 | N13: 5ED528 | O13: Sold | P13: starr8@rocketmail.com
A14: 45899 | B14: FMY-MA-DE-1A-4A | C14: Monstera Deliciosa | D14: 1 | E14: 10 | F14: 10 | G14: Cash | H14: None | I14: Merlin Outdoor Market | J14: 2.61 | K14: 7.39 | L14: 0.739 | N14: 2BF0C1 | O14: Sold | P14: starr8@rocketmail.com
A15: 45899 | B15: FMY-MA-DE-1A-4E | C15: Monstera Deliciosa | D15: 1 | E15: 7 | F15: 7 | G15: Cash | H15: None | I15: Merlin Outdoor Market | J15: 2.07 | K15: 4.93 | L15: 0.70428571 | N15: 9.64e+41 | O15: Sold | P15: starr8@rocketmail.com
A16: 45899 | B16: FMY-CA-MA-1C | C16: Calathea Makoyana | D16: 1 | E16: 12 | F16: 12 | G16: Cash | H16: None | I16: Merlin Outdoor Market | J16: 3.83 | K16: 8.17 | L16: 0.68083333 | N16: 3CCDEB | O16: Sold | P16: starr8@rocketmail.com
A17: 45899 | B17: HD-ST-TR-1B | C17: Stromanthe Triostar | D17: 1 | E17: 10 | F17: 10 | G17: Cash | H17: None | I17: Merlin Outdoor Market | J17: 10.49 | K17: -0.49 | L17: -0.049 | N17: 3C8485 | O17: Sold | P17: starr8@rocketmail.com
A18: 45899 | B18: HD-ST-TR-1C | C18: Stromanthe Triostar | D18: 1 | E18: 10 | F18: 10 | G18: Cash | H18: None | I18: Merlin Outdoor Market | J18: 10.49 | K18: -0.49 | L18: -0.049 | N18: FDC040 | O18: Sold | P18: starr8@rocketmail.com
A19: 45899 | B19: BPF-CE-SOH-1A-4 | C19: Ceropegia String of Hearts | D19: 1 | E19: 10 | F19: 10 | G19: Cash | H19: None | I19: Merlin Outdoor Market | J19: 5.84 | K19: 4.16 | L19: 0.416 | N19: 1AD482 | O19: Sold | P19: starr8@rocketmail.com
A20: 45899 | B20: BPF-CE-SOH-1A-5 | C20: Ceropegia String of Hearts | D20: 1 | E20: 10 | F20: 10 | G20: Cash | H20: None | I20: Merlin Outdoor Market | J20: 5.84 | K20: 4.16 | L20: 0.416 | N20: F19DDE | O20: Sold | P20: starr8@rocketmail.com
A21: 45911 | B21: BWH-PO-PAJ-1A-5 | C21: Pothos Pearls and Jade | D21: 1 | E21: 20 | F21: 20 | G21: Cash | H21: None | I21: Square Online | J21: 9.15 | K21: 10.85 | L21: 0.5425 | N21: F0E0F0 | O21: Sold | P21: starr8@rocketmail.com
A22: 45913 | B22: HS-PO-GO-1J | C22: Pothos Golden | D22: 1 | E22: 4 | F22: 4 | G22: Cash | H22: None | I22: Square Online | J22: 0.5 | K22: 3.5 | L22: 0.875 | N22: A3A7BD | O22: Sold | P22: starr8@rocketmail.com
A23: 45913 | B23: BPF-CE-SOH-1A | C23: Ceropegia String of Hearts | D23: 1 | E23: 10 | F23: 10 | G23: Cash | H23: None | I23: Square Online | J23: 5.84 | K23: 4.16 | L23: 0.416 | N23: 498D06 | O23: Sold | P23: starr8@rocketmail.com
A24: 45913 | B24: BPF-SE-SOP-1A | C24: Senecio String of Pearls | D24: 1 | E24: 8 | F24: 8 | G24: Cash | H24: None | I24: Square Online | J24: 4.71 | K24: 3.29 | L24: 0.41125 | N24: BAB38A | O24: Sold | P24: starr8@rocketmail.com
A25: 45913 | B25: BWH-PO-PAJ-1A-3A | C25: Pothos Pearls and Jade | D25: 1 | E25: 8 | F25: 8 | G25: Cash | H25: None | I25: Square Online | J25: 8.3 | K25: -0.3 | L25: -0.0375 | N25: C39146 | O25: Sold | P25: starr8@rocketmail.com
A26: 45913 | B26: FMY-AG-SPA-1A | C26: Aglaonema Spathonema | D26: 1 | E26: 8 | F26: 8 | G26: Cash | H26: None | I26: Square Online | J26: 3.83 | K26: 4.17 | L26: 0.52125 | N26: 4B3C20 | O26: Sold | P26: starr8@rocketmail.com
A27: 45913 | B27: HS-PO-GO-1C | C27: Pothos Golden | D27: 1 | E27: 2 | F27: 2 | G27: Cash | H27: None | I27: Square Online | J27: 0.92 | K27: 1.08 | L27: 0.54 | N27: 3C799B | O27: Sold | P27: starr8@rocketmail.com
... A34: 45920 | B34: BPF-SE-SOP-1A-5 | C34: Senecio String of Pearls | D34: 1 | E34: 6 | F34: 6 | G34: Cash | H34: None | I34: Flea Market | J34: 4.71 | K34: 1.29 | L34: 0.215 | N34: 33D5C6 | O34: Sold | P34: starr8@rocketmail.com
A35: 45920 | B35: FMY-MA-PE-1A | C35: Monstera Peru | D35: 1 | E35: 10 | F35: 10 | G35: Credit Card | H35: 9155 | I35: Flea Market | J35: 3.37 | K35: 6.63 | L35: 0.663 | M35: Square | N35: 55DDB0 | O35: Sold | P35: starr8@rocketmail.com
A36: 45957 | B36: BWH-AL-VM-1A-5 | C36: Alocasia Variegated Macrorrhiza | D36: 1 | E36: 10 | F36: 10 | G36: Credit Card | I36: Palm Street | J36: 13.35 | K36: -3.35 | L36: -0.335 | N36: E1A1A4 | O36: Sold | P36: starr8@rocketmail.com
A37: 45957 | B37: BWH-PH-BMV-1A | C37: Philodendron Burle Marx Variegated | D37: 1 | E37: 10 | F37: 10 | G37: Credit Card | I37: Palm Street | J37: 15.75 | K37: -5.75 | L37: -0.575 | N37: BA759B | O37: Sold | P37: starr8@rocketmail.com
A38: 45957 | B38: BTPG-HO-KP-1B | C38: Hoya Krimson Princess | D38: 1 | E38: 15 | F38: 15 | G38: Credit Card | I38: Palm Street | J38: 10.58 | K38: 4.42 | L38: 0.29466667 | N38: 0FAAAC | O38: Sold | P38: starr8@rocketmail.com
A39: 45959 | B39: AGP-PH-BC-1B | C39: Philodendron Black Cardinal | D39: 1 | E39: 5 | F39: 5 | G39: Credit Card | I39: Palm Street | J39: 2.29 | K39: 2.71 | L39: 0.542 | N39: 2E3C5A | O39: Sold | P39: starr8@rocketmail.com
A40: 45959 | B40: BWH-PH-BMV-1A-2 | C40: Philodendron Burle Marx Variegated | D40: 1 | E40: 10 | F40: 10 | G40: Credit Card | I40: Palm Street | J40: 15.75 | K40: -5.75 | L40: -0.575 | N40: 9CA059 | O40: Sold | P40: starr8@rocketmail.com
A41: 45959 | B41: BWH-AL-VM-1A | C41: Alocasia Variegated Macrorrhiza | D41: 1 | E41: 14 | F41: 14 | G41: Credit Card | I41: Palm Street | J41: 13.35 | K41: 0.65 | L41: 0.046428571 | N41: C40573 | O41: Sold | P41: starr8@rocketmail.com
A42: 45959 | B42: AGP-PH-BC-1A-4 | C42: Philodendron Black Cardinal | D42: 1 | E42: 10 | F42: 10 | G42: Credit Card | I42: Palm Street | J42: 3.46 | K42: 6.54 | L42: 0.654 | N42: D88B84 | O42: Sold | P42: starr8@rocketmail.com
A43: 45959 | B43: BWH-PH-BMV-1A-4 | C43: Philodendron Burle Marx Variegated | D43: 1 | E43: 5 | F43: 5 | G43: Credit Card | I43: Palm Street | J43: 15.01 | K43: -10.01 | L43: -2.002 | N43: AE3FD1 | O43: Sold | P43: starr8@rocketmail.com
A44: 45959 | B44: BWH-PH-PV-1A-5 | C44: Philodendron Paraiso Verde | D44: 1 | E44: 15 | F44: 15 | G44: Credit Card | I44: Palm Street | J44: 10.35 | K44: 4.65 | L44: 0.31 | N44: D4DBAF | O44: Sold | P44: starr8@rocketmail.com
A45: 45960 | B45: BPF-SE-SOP-2B | C45: Senecio String of Pearls | D45: 1 | E45: 0 | F45: 0 | I45: Palm Street | J45: 0 | K45: 0 | L45: 0 | N45: 5C79FB | O45: Giveaway | P45: starr8@rocketmail.com
A46: 45960 | B46: BWH-AL-VM-1A-3 | C46: Alocasia Variegated Macrorrhiza | D46: 1 | E46: 14 | F46: 14 | G46: Credit Card | I46: Palm Street | J46: 13.35 | K46: 0.65 | L46: 0.046428571 | N46: 5597B0 | O46: Sold | P46: starr8@rocketmail.com
A47: 45958 | B47: AGP-AL-NI-1A-2 | C47: Alocasia Ninja | D47: 1 | E47: 15 | F47: 15 | G47: Credit Card | I47: Palm Street | J47: 3.61 | K47: 11.39 | L47: 0.75933333 | N47: B70A34 | O47: Sold | P47: starr8@rocketmail.com
A48: 45959 | B48: DSE-PH-RK-1A-4 | C48: Philodendron Red King | D48: 1 | E48: 5 | F48: 5 | G48: Credit Card | I48: Palm Street | J48: 4.19 | K48: 0.81 | L48: 0.162 | N48: 3434FB | O48: Sold | P48: starr8@rocketmail.com
A49: 45959 | B49: BWH-AL-VM-1A-4 | C49: Alocasia Variegated Macrorrhiza | D49: 1 | E49: 14 | F49: 14 | G49: Credit Card | I49: Palm Street | J49: 13.35 | K49: 0.65 | L49: 0.046428571 | N49: 9CA4AE | O49: Sold | P49: starr8@rocketmail.com
A50: 45959 | B50: DSE-PH-RK-1A-5 | C50: Philodendron Red King | D50: 1 | E50: 8 | F50: 8 | G50: Credit Card | I50: Palm Street | J50: 4.19 | K50: 3.81 | L50: 0.47625 | N50: 3293A4 | O50: Sold | P50: starr8@rocketmail.com
A51: 45958 | B51: DSE-PH-RK-1A-3 | C51: Philodendron Red King | D51: 1 | E51: 5 | F51: 5 | G51: Credit Card | I51: Palm Street | J51: 4.19 | K51: 0.81 | L51: 0.162 | N51: 8A4F2D | O51: Sold | P51: starr8@rocketmail.com
A52: 45958 | B52: DSE-COL-MOJ-1A-8 | C52: Colocasia Mojito | D52: 1 | E52: 0 | F52: 0 | I52: Palm Street | J52: 1.95 | K52: -1.95 | L52: 0 | N52: 628445 | O52: Giveaway | P52: starr8@rocketmail.com
A53: 45958 | B53: BPF-CE-VSH-1B | C53: Ceropegia Variegated String of Hearts | D53: 1 | E53: 0 | F53: 0 | I53: Palm Street | J53: 19.49 | K53: -19.49 | L53: 0 | N53: D01BFC | O53: Giveaway | P53: starr8@rocketmail.com
A54: 45958 | B54: TGOPS-PH-PPM-1A | C54: Philodendron Pink Princess Marbled | D54: 1 | E54: 10 | F54: 10 | G54: Credit Card | I54: Palm Street | J54: 16.69 | K54: -6.69 | L54: -0.669 | N54: 7D9BED | O54: Sold | P54: starr8@rocketmail.com
A55: 45959 | B55: BWH-FIC-SH-1A-5 | C55: Ficus Shivereana | D55: 1 | E55: 0 | F55: 0 | I55: Palm Street | J55: 5 | K55: -5 | L55: 0 | N55: 5EE09A | O55: Giveaway | P55: starr8@rocketmail.com
A56: 45959 | B56: DSE-PH-RK-1A | C56: Philodendron Red King | D56: 1 | E56: 5 | F56: 5 | G56: Credit Card | I56: Palm Street | J56: 4.19 | K56: 0.81 | L56: 0.162 | N56: 53405B | O56: Sold | P56: starr8@rocketmail.com
A57: 45959 | B57: WM-PH-WK-1A | C57: Philodendron White Knight | D57: 1 | E57: 10 | F57: 10 | G57: Credit Card | I57: Palm Street | J57: 5.6 | K57: 4.4 | L57: 0.44 | N57: 629618 | O57: Sold | P57: starr8@rocketmail.com
A58: 45959 | B58: BWH-PH-PV-1A-3 | C58: Philodendron Paraiso Verde | D58: 1 | E58: 24 | F58: 24 | G58: Credit Card | I58: Palm Street | J58: 9.94 | K58: 14.06 | L58: 0.58583333 | N58: B69E0A | O58: Sold | P58: starr8@rocketmail.com
A59: 45957 | B59: TGOPS-PH-WW-1A-3B | C59: Philodendron White Wizard | D59: 1 | E59: 0 | F59: 0 | I59: Palm Street | J59: 4.3966667 | K59: -4.4 | L59: 0 | N59: 272800 | O59: Giveaway | P59: starr8@rocketmail.com
A60: 45959 | B60: BWH-FIC-SH-1A-4 | C60: Ficus Shivereana | D60: 1 | E60: 0 | F60: 0 | I60: Palm Street | J60: 5 | K60: -5 | L60: 0 | N60: B18A26 | O60: Giveaway | P60: starr8@rocketmail.com
A61: 45959 | B61: BWH-HO-KQ-1A-5 | C61: Hoya Krimson Queen | D61: 1 | E61: 10 | F61: 10 | G61: Credit Card | I61: Palm Street | J61: 5.95 | K61: 4.05 | L61: 0.405 | N61: EA21C5 | O61: Sold | P61: starr8@rocketmail.com
A62: 45959 | B62: BTPG-HO-KP-1A | C62: Hoya Krimson Princess | D62: 1 | E62: 10 | F62: 10 | G62: Credit Card | I62: Palm Street | J62: 6.58 | K62: 3.42 | L62: 0.342 | N62: FD32BA | O62: Sold | P62: starr8@rocketmail.com
A63: 45959 | B63: TG-CHA-EL-1A | C63: Chamaedorea Elegans | D63: 1 | E63: 10 | F63: 10 | G63: Credit Card | I63: Palm Street | J63: 9.5 | K63: 0.5 | L63: 0.05 | N63: FC4517 | O63: Sold | P63: starr8@rocketmail.com
A64: 45959 | B64: BWH-PH-BRL-1A-5 | C64: Philodendron Brasil | D64: 1 | E64: 10 | F64: 10 | G64: Credit Card | I64: Palm Street | J64: 7.8 | K64: 2.2 | L64: 0.22 | N64: A3FFF1 | O64: Sold | P64: starr8@rocketmail.com
A65: 45960 | B65: AGP-PH-BC-1A-2A | C65: Philodendron Black Cardinal | D65: 1 | E65: 0 | F65: 0 | I65: Palm Street | J65: 2.29 | K65: -2.29 | L65: -1 | N65: 622309 | O65: Sold | P65: starr8@rocketmail.com
A66: 45958 | B66: FMY-MA-PE-1F | C66: Monstera Peru | D66: 1 | E66: 0 | F66: 0 | I66: Palm Street | J66: 2.4271429 | K66: -2.43 | L66: 0 | N66: ED354B | O66: Giveaway | P66: starr8@rocketmail.com
A67: 45960 | B67: UN-PA-HPA-3 | C67: Heat Pack Packing/Shipping | D67: 1 | E67: 0 | F67: 0 | G67: Palmstreet | I67: Palm Street | J67: 5.66 | K67: -5.66 | L67: 0 | N67: F63415 | O67: Giveaway | P67: starr8@rocketmail.com
A68: 45958 | B68: TLC-PH-CS-1B | C68: Philodendron Cream Splash | D68: 1 | E68: 10 | F68: 10 | G68: Credit Card | I68: Palm Street | J68: 0.29 | K68: 9.71 | L68: 0.971 | N68: 7541BF | O68: Sold | P68: starr8@rocketmail.com
A69: 45959 | B69: AGP-PH-BC-1A-2B | C69: Philodendron Black Cardinal | D69: 1 | E69: 5 | F69: 5 | G69: Credit Card | I69: Palm Street | J69: 2.29 | K69: 2.71 | L69: 0.542 | N69: D2859E | O69: Sold | P69: starr8@rocketmail.com
A70: 45959 | B70: BWH-FIC-SH-1A-3 | C70: Ficus Shivereana | D70: 1 | E70: 0 | F70: 0 | I70: Palm Street | J70: 6.35 | K70: -6.35 | L70: -1 | N70: D0F977 | O70: Sold | P70: starr8@rocketmail.com
A71: 45960 | B71: HS-PO-GO-1G | C71: Pothos Golden | D71: 1 | E71: 0 | F71: 0 | I71: Palm Street | J71: 0 | K71: 0 | L71: 0 | N71: 169CDE | O71: Giveaway | P71: starr8@rocketmail.com
A72: 45957 | B72: WM-PH-WK-1C | C72: Philodendron White Knight | D72: 1 | E72: 0 | F72: 0 | I72: Palm Street | J72: 4.9925 | K72: -4.99 | L72: 0 | N72: 8C5945 | O72: Giveaway | P72: starr8@rocketmail.com
A73: 45960 | B73: HS-PH-HL-1G | C73: Philodendron Heart Leaf | D73: 1 | E73: 0 | F73: 0 | I73: Palm Street | J73: 0 | K73: 0 | L73: 0 | N73: 4FD521 | O73: Giveaway | P73: starr8@rocketmail.com
A74: 45960 | B74: BPF-SE-SOT-1A-3 | C74: Senecio String of Tears | D74: 1 | E74: 6 | F74: 6 | G74: Credit Card | I74: Palm Street | J74: 4.06 | K74: 1.94 | L74: 0.32333333 | N74: D46824 | O74: Sold | P74: starr8@rocketmail.com
A75: 45958 | B75: HS-BE-AW-1S | C75: Begonia Angel Wing | D75: 1 | E75: 0 | F75: 0 | I75: Palm Street | J75: 0 | K75: 0 | L75: 0 | N75: 898BA4 | O75: Giveaway | P75: starr8@rocketmail.com
A76: 45959 | B76: BWH-FIC-SH-1A-2 | C76: Ficus Shivereana | D76: 1 | E76: 0 | F76: 0 | I76: Palm Street | J76: 5 | K76: -5 | L76: 0 | N76: 606CFE | O76: Giveaway | P76: starr8@rocketmail.com
A77: 45958 | B77: HD-AL-LO-1A-2C | C77: Alocasia Longiloba | D77: 1 | E77: 0 | F77: 0 | I77: Palm Street | J77: 9.9933333 | K77: -9.99 | L77: 0 | N77: 4A53EC | O77: Giveaway | P77: starr8@rocketmail.com
A78: 45957 | B78: BWH-SYN-PS-1A-2 | C78: Syngonium Pink Splash | D78: 1 | E78: 10 | F78: 10 | G78: Credit Card | I78: Palm Street | J78: 9.5 | K78: 0.5 | L78: 0.05 | N78: 911C35 | O78: Sold | P78: starr8@rocketmail.com
A79: 45957 | B79: BWH-PH-BMV-1A-5 | C79: Philodendron Burle Marx Variegated | D79: 1 | E79: 10 | F79: 10 | G79: Credit Card | I79: Palm Street | J79: 15.34 | K79: -5.34 | L79: -0.534 | N79: 6D35EC | O79: Sold | P79: starr8@rocketmail.com
A80: 45958 | B80: BWH-CA-MA-1A-5 | C80: Calathea Makoyana | D80: 1 | E80: 10 | F80: 10 | G80: Credit Card | I80: Palm Street | J80: 8.1 | K80: 1.9 | L80: 0.19 | N80: 724774 | O80: Sold | P80: starr8@rocketmail.com
A81: 45957 | B81: BWH-SYN-PS-1A-4 | C81: Syngonium Pink Splash | D81: 1 | E81: 10 | F81: 10 | G81: Credit Card | I81: Palm Street | J81: 9.5 | K81: 0.5 | L81: 0.05 | N81: 3C8CA2 | O81: Sold | P81: starr8@rocketmail.com
A82: 45960 | B82: DSE-PH-MF-1A-2 | C82: Philodendron McColley's Finale | D82: 1 | E82: 10 | F82: 10 | G82: Credit Card | I82: Palm Street | J82: 5.19 | K82: 4.81 | L82: 0.481 | N82: 5849DB | O82: Sold | P82: starr8@rocketmail.com
A83: 45960 | B83: HS-PO-GO-1D | C83: Pothos Golden | D83: 1 | E83: 10 | F83: 10 | G83: Credit Card | I83: Palm Street | J83: 0.29 | K83: 9.71 | L83: 0.971 | N83: EF3428 | O83: Sold | P83: starr8@rocketmail.com
A84: 45960 | B84: DSE-PH-RK-1A-2 | C84: Philodendron Red King | D84: 1 | E84: 5 | F84: 5 | G84: Credit Card | I84: Palm Street | J84: 4.19 | K84: 0.81 | L84: 0.162 | N84: FA0D9F | O84: Sold | P84: starr8@rocketmail.com
A85: 45960 | B85: BPF-CE-SOH-2A | C85: Ceropegia String of Hearts | D85: 1 | E85: 8 | F85: 8 | G85: Credit Card | I85: Palm Street | J85: 14.29 | K85: -6.29 | L85: -0.78625 | N85: 91346B | O85: Sold | P85: starr8@rocketmail.com
A86: 45960 | B86: HS-PO-GO-1L | C86: Pothos Golden | D86: 1 | E86: 0 | F86: 0 | I86: Palm Street | J86: 0 | K86: 0 | L86: 0 | N86: AC3063 | O86: Giveaway | P86: starr8@rocketmail.com
A87: 45960 | B87: BWH-PO-PAJ-2A-4B | C87: Pothos Pearls and Jade | D87: 1 | E87: 0 | F87: 0 | G87: Credit Card | I87: Palm Street | J87: 7.8 | K87: -7.8 | L87: 0 | N87: 3A066D | O87: Giveaway | P87: starr8@rocketmail.com
A89: 45960 | B89: BPF-SE-SOP-2B | C89: Senecio String of Pearls | D89: 1 | E89: 10 | F89: 10 | G89: Credit Card | I89: Palm Street | J89: 0.13 | K89: 9.87 | L89: 0.987 | N89: C9E883 | O89: Sold | P89: starr8@rocketmail.com
A90: 45960 | B90: FS-KC-PLA-7 | C90: Plant Key Chain | D90: 1 | E90: 4 | F90: 4 | G90: Credit Card | I90: Palm Street | J90: 0.57 | K90: 3.43 | L90: 0.8575 | N90: F14CC8 | O90: Sold | P90: starr8@rocketmail.com
A91: 45960 | B91: ARC-TB-DH-3 | C91: Don't Hate, Propogate Tote Bag | D91: 1 | E91: 15 | F91: 15 | G91: Credit Card | I91: Palm Street | J91: 7.12 | K91: 7.88 | L91: 0.52533333 | N91: 9EE21C | O91: Sold | P91: starr8@rocketmail.com
A92: 45961 | B92: BWH-CA-MA-1A | C92: Calathea Makoyana | D92: 1 | E92: 10 | F92: 10 | G92: Cash | I92: Facebook Marketplace | J92: 8.1 | K92: 1.9 | L92: 0.19 | N92: 041B2A | O92: Sold | P92: starr8@rocketmail.com
A93: 45958 | B93: FMY-MA-PE-1E | C93: Monstera Peru | D93: 1 | E93: 0 | F93: 0 | G93: Credit Card | I93: Palm Street | J93: 2.4271429 | K93: -2.43 | L93: 0 | N93: 076C2C | O93: Giveaway | P93: starr8@rocketmail.com
A94: 45957 | B94: TGOPS-PH-POO-1A | C94: Philodendron Prince of Orange | D94: 1 | E94: 10 | F94: 10 | G94: Credit Card | I94: Palm Street | J94: 8.29 | K94: 1.71 | L94: 0.171 | N94: 1D38E2 | O94: Sold | P94: starr8@rocketmail.com
A95: 45960 | B95: BPF-SE-SOP-2C | C95: Senecio String of Pearls | D95: 1 | E95: 0 | F95: 0 | G95: Giveaway | I95: Palm Street | J95: 0 | K95: 0 | L95: 0 | N95: 2EE464 | O95: Giveaway | P95: starr8@rocketmail.com
A96: 45957 | B96: AGP-PH-BC-1A-3A | C96: Philodendron Black Cardinal | D96: 1 | E96: 0 | F96: 0 | G96: Giveaway | I96: Palm Street | J96: 2 | K96: -2 | L96: 0 | N96: A27CF6 | O96: Giveaway | P96: starr8@rocketmail.com
A97: 45957 | B97: TGOPS-PH-WW-1A-2B | C97: Philodendron White Wizard | D97: 1 | E97: 0 | F97: 0 | G97: Giveaway | I97: Palm Street | J97: 3.2975 | K97: -3.3 | L97: 0 | N97: 20726F | O97: Giveaway | P97: starr8@rocketmail.com
A98: 45960 | B98: TGOPS-PH-WW-1F | C98: Philodendron White Wizard | D98: 1 | E98: 0 | F98: 0 | G98: Giveaway | I98: Palm Street | J98: 2.1983333 | K98: -2.2 | L98: 0 | N98: 1AFBE6 | O98: Giveaway | P98: starr8@rocketmail.com
A99: 45959 | B99: AGP-PH-BC-1C | C99: Philodendron Black Cardinal | D99: 1 | E99: 0 | F99: 0 | G99: Giveaway | I99: Palm Street | J99: 2 | K99: -2 | L99: 0 | N99: A64706 | O99: Giveaway | P99: starr8@rocketmail.com
... A102: 45967 | B102: BWH-CA-MA-1A-2 | C102: Calathea Makoyana | D102: 1 | E102: 15 | F102: 15 | G102: Cash | I102: Facebook Marketplace | J102: 8.1 | K102: 6.9 | L102: 0.46 | N102: 0F156A | O102: Sold | P102: starr8@rocketmail.com
P103: starr8@rocketmail.com
A104: 45969 | B104: FMY-CA-MA-1B | C104: Calathea Makoyana | D104: 1 | E104: 10 | F104: 10 | G104: Cash | H104: None | I104: In Person | J104: 3.83 | K104: 6.17 | L104: 0.617 | N104: 685659 | O104: Sold | P104: starr8@rocketmail.com
A105: 45969 | B105: BWH-MA-AD-1A | C105: Monstera Adansonii | D105: 1 | E105: 15 | F105: 15 | G105: Cash | H105: None | I105: In Person | J105: 6.9 | K105: 8.1 | L105: 0.54 | N105: A66462 | O105: Sold | P105: starr8@rocketmail.com
A106: 45969 | B106: FMY-AL-RSD-1A-2 | C106: Alocasia Regal Shield | D106: 1 | E106: 0 | F106: 0 | G106: Gift | H106: None | I106: In Person | J106: 10.99 | K106: -10.99 | L106: 0 | N106: ED0C6D | O106: Giveaway | P106: starr8@rocketmail.com
P107: starr8@rocketmail.com
P108: starr8@rocketmail.com
P109: starr8@rocketmail.com
...

Sheet Fertilizer Log
A2: Date | B2: Plant SKU | C2: Pot SKU | D2: Product | E2: Method | F2: Rate | G2: Unit | H2: Next Earliest | I2: Next Latest | J2: Notes | K2: UID | L2: Owner Email
A3: 46004 | B3: BWH-AL-CU-1A | C3: 4' | D3: Arber | E3: Bottom Water | F3: 2 tbsp | G3: 32 oz | H3: =IF($A3="","",$A3 + IFERROR(VLOOKUP($D3,'Fertilizer Key'!$A:$D,3,FALSE),"")) -> 46011 | I3: =IF($A3="","",$A3 + IFERROR(VLOOKUP($D3,'Fertilizer Key'!$A:$D,4,FALSE),"")) -> 46018 | K3: 4559191f | L3: starr8@rocketmail.com
A4: 46004 | B4: BWH-AL-CU-1A-2 | C4: 4' | D4: Arber | E4: Bottom Water | F4: 2 tbsp | G4: 32 oz | H4: =IF($A4="","",$A4 + IFERROR(VLOOKUP($D4,'Fertilizer Key'!$A:$D,3,FALSE),"")) -> 46011 | I4: =IF($A4="","",$A4 + IFERROR(VLOOKUP($D4,'Fertilizer Key'!$A:$D,4,FALSE),"")) -> 46018 | K4: 77d936e5 | L4: starr8@rocketmail.com
A5: 46004 | B5: BWH-AL-CU-1A-3 | C5: 4' | D5: Arber | E5: Bottom Water | F5: 2 tbsp | G5: 32 oz | H5: =IF($A5="","",$A5 + IFERROR(VLOOKUP($D5,'Fertilizer Key'!$A:$D,3,FALSE),"")) -> 46011 | I5: =IF($A5="","",$A5 + IFERROR(VLOOKUP($D5,'Fertilizer Key'!$A:$D,4,FALSE),"")) -> 46018 | K5: 25bb35c8 | L5: starr8@rocketmail.com
A6: 46004 | B6: BWH-AL-CU-1A-5 | C6: 4' | D6: Arber | E6: Bottom Water | F6: 2 tbsp | G6: 32 oz | H6: =IF($A6="","",$A6 + IFERROR(VLOOKUP($D6,'Fertilizer Key'!$A:$D,3,FALSE),"")) -> 46011 | I6: =IF($A6="","",$A6 + IFERROR(VLOOKUP($D6,'Fertilizer Key'!$A:$D,4,FALSE),"")) -> 46018 | K6: a7ac9af5 | L6: starr8@rocketmail.com
A7: 46004 | B7: BWH-AL-CU-1A-4 | C7: 4' | D7: Arber | E7: Bottom Water | F7: 2 tbsp | G7: 32 oz | H7: =IF($A7="","",$A7 + IFERROR(VLOOKUP($D7,'Fertilizer Key'!$A:$D,3,FALSE),"")) -> 46011 | I7: =IF($A7="","",$A7 + IFERROR(VLOOKUP($D7,'Fertilizer Key'!$A:$D,4,FALSE),"")) -> 46018 | K7: 081be697 | L7: starr8@rocketmail.com
A8: 46004 | B8: DSE-AL-PC-1A-3 | C8: 4' | D8: Ferti-lome | E8: Reservoir Fill | F8: 1 tsp | G8: 1 gal | H8: =IF($A8="","",$A8 + IFERROR(VLOOKUP($D8,'Fertilizer Key'!$A:$D,3,FALSE),"")) -> 46011 | I8: =IF($A8="","",$A8 + IFERROR(VLOOKUP($D8,'Fertilizer Key'!$A:$D,4,FALSE),"")) -> 46018 | K8: aa697dc8 | L8: starr8@rocketmail.com
A9: 46004 | B9: DSE-AL-MAN-1A-2 | C9: 4' | D9: Ferti-lome | E9: Reservoir Fill | F9: 1 tsp | G9: 1 gal | H9: =IF($A9="","",$A9 + IFERROR(VLOOKUP($D9,'Fertilizer Key'!$A:$D,3,FALSE),"")) -> 46011 | I9: =IF($A9="","",$A9 + IFERROR(VLOOKUP($D9,'Fertilizer Key'!$A:$D,4,FALSE),"")) -> 46018 | K9: 6f65490d | L9: starr8@rocketmail.com
A10: 46004 | B10: DSE-AL-PO-1A-4 | C10: 4' | D10: Ferti-lome | E10: Reservoir Fill | F10: 1 tsp | G10: 1 gal | H10: =IF($A10="","",$A10 + IFERROR(VLOOKUP($D10,'Fertilizer Key'!$A:$D,3,FALSE),"")) -> 46011 | I10: =IF($A10="","",$A10 + IFERROR(VLOOKUP($D10,'Fertilizer Key'!$A:$D,4,FALSE),"")) -> 46018 | K10: 25755f2f | L10: starr8@rocketmail.com
A11: 46004 | B11: HD-AL-BDS-1B | C11: 4' | D11: Ferti-lome | E11: Reservoir Fill | F11: 1 tsp | G11: 1 gal | H11: =IF($A11="","",$A11 + IFERROR(VLOOKUP($D11,'Fertilizer Key'!$A:$D,3,FALSE),"")) -> 46011 | I11: =IF($A11="","",$A11 + IFERROR(VLOOKUP($D11,'Fertilizer Key'!$A:$D,4,FALSE),"")) -> 46018 | K11: 9f30c148 | L11: starr8@rocketmail.com
A12: 46004 | B12: AGP-AL-NI-1A-3C | C12: 4' | D12: Ferti-lome | E12: Reservoir Fill | F12: 1 tsp | G12: 1 gal | H12: =IF($A12="","",$A12 + IFERROR(VLOOKUP($D12,'Fertilizer Key'!$A:$D,3,FALSE),"")) -> 46011 | I12: =IF($A12="","",$A12 + IFERROR(VLOOKUP($D12,'Fertilizer Key'!$A:$D,4,FALSE),"")) -> 46018 | K12: bc21b13d | L12: starr8@rocketmail.com
A13: 46004 | B13: FM-SYN-BA-1A | C13: 4' | D13: Ferti-lome | E13: Reservoir Fill | F13: 1 tsp | G13: 1 gal | H13: =IF($A13="","",$A13 + IFERROR(VLOOKUP($D13,'Fertilizer Key'!$A:$D,3,FALSE),"")) -> 46011 | I13: =IF($A13="","",$A13 + IFERROR(VLOOKUP($D13,'Fertilizer Key'!$A:$D,4,FALSE),"")) -> 46018 | K13: a4ea20e5 | L13: starr8@rocketmail.com
